Workbook
Name Slicer_City_Name: #N/A
Name Slicer_Current_Status__Live_Not_Live: #N/A
Name Slicer_Remarks_Grouped: #N/A
Name Slicer_Status: #N/A
Name Slicer_Std_Remarks: #N/A
Name Slicer_Timeline___Monthwise: #N/A

Sheet Area Wise Spread - DB 2
A1: Number of CEMs | B1: =COUNT(B4:B98) -> 95
A3: Row Labels | B3: Sum of Total H.P | C3: Sum of Customers According to % (Market Share) | D3: Sum of HP Based on completion - Realistic
A4: Abbottabad | B4: 1864 | C4: 745.6 | D4: 745.6
A5: Gulfam Town_Mera Muzzafar | B5: 450 | C5: 180 | D5: 180
A6: Malikpura | B6: 714 | C6: 285.6 | D6: 285.6
A7: Salhad | B7: 700 | C7: 280 | D7: 280
A8: Abbottabad Ph2 | B8: 1826 | C8: 730.4 | D8: 730.4
A9: Al Mansoor Town Ext. | B9: 440 | C9: 176 | D9: 176
A10: Jhangi Qazian | B10: 420 | C10: 168 | D10: 168
A11: Jhangi Saeedan Extension | B11: 482 | C11: 192.8 | D11: 192.8
A12: Kaghan Colony Extension | B12: 302 | C12: 120.8 | D12: 120.8
A13: Kareenpura Extension | B13: 182 | C13: 72.8 | D13: 72.8
A14: Al Hafeez Garden & Tariq Garden | B14: 5502 | C14: 2200.8
A15: Al Hafeez Garden Ph-5 | B15: 1450 | C15: 580
A16: Al Hafeez Gdn Ph-2 | B16: 1404 | C16: 561.6
A17: Al Raheem Gdn Ph-2 Extn. | B17: 1150 | C17: 460
A18: Tariq Garden | B18: 1498 | C18: 599.2
A19: Al Jalil & Al khalil LHE | B19: 17546 | C19: 7018.4 | D19: 7018.4
A20: Al Hamra | B20: 424 | C20: 169.6 | D20: 169.6
A21: Al Jalil Housing P2 | B21: 2232 | C21: 892.8 | D21: 892.8
A22: Al Jalil Housing P3 | B22: 2210 | C22: 884 | D22: 884
A23: Al Jalil Housing P4 | B23: 2106 | C23: 842.4 | D23: 842.4
A24: Al Kabeer Ph-2-Pk1 | B24: 2268 | C24: 907.2 | D24: 907.2
A25: Al Kabeer Ph-2-Pk2 | B25: 3086 | C25: 1234.4 | D25: 1234.4
A26: Al Kabeer Ph-2-Pk3 | B26: 776 | C26: 310.4 | D26: 310.4
A27: Al Kabeer Town Ph-1 | B27: 512 | C27: 204.8 | D27: 204.8
A28: Central Park Housing-P1 | B28: 1526 | C28: 610.4 | D28: 610.4
A29: Central Park Housing-P2 | B29: 1200 | C29: 480 | D29: 480
A30: Central Park Housing-P3 | B30: 1206 | C30: 482.4 | D30: 482.4
... A138: Gulshan e Ali | B138: 934 | C138: 373.6 | D138: 373.6
A139: Darussalam_LucknowSociety_DadabhoyTown | B139: 3058 | C139: 1223.2
A140: Darussalam Society | B140: 1074 | C140: 429.6
A141: Lucknow Society | B141: 1322 | C141: 528.8
A142: Dadabhoy Town | B142: 662 | C142: 264.8
A143: Daska | B143: 21078 | C143: 8431.2 | D143: 8431.2
A144: Barkat Town | B144: 592 | C144: 236.8 | D144: 236.8
A145: Bhatti Colony | B145: 536 | C145: 214.4 | D145: 214.4
A146: Civil Lines | B146: 598 | C146: 239.2 | D146: 239.2
A147: Faisal_Town | B147: 320 | C147: 128 | D147: 128
A148: Garden Town | B148: 1288 | C148: 515.2 | D148: 515.2
A149: Ghalotian Mor | B149: 456 | C149: 182.4 | D149: 182.4
A150: Gulistan_town | B150: 1100 | C150: 440 | D150: 440
A151: Gulshan Colony | B151: 752 | C151: 300.8 | D151: 300.8
A152: Habibpura | B152: 778 | C152: 311.2 | D152: 311.2
A153: Islampura | B153: 1132 | C153: 452.8 | D153: 452.8
A154: Model Town | B154: 556 | C154: 222.4 | D154: 222.4
... A218: Zam Zam City | B218: 262 | C218: 117.9 | D218: 117.9
A219: DHA Gujranwala | B219: 528 | C219: 264
A220: DHA Sector A ( Villas ) | B220: 528 | C220: 264
A221: DHA KHI - Common Corridor Project | B221: 19009 | C221: 7603.6 | D221: 7603.6
A222: DKTCC (Remaining Areas) | B222: 19009 | C222: 7603.6 | D222: 7603.6
A223: DHA Multan | B223: 9298 | C223: 5578.8 | D223: 5578.8
A224: Additional Cost | B224: 0 | C224: 0 | D224: 0
A225: Block M | B225: 2576 | C225: 1545.6 | D225: 1545.6
A226: Block Q | B226: 2914 | C226: 1748.4 | D226: 1748.4
A227: Block R | B227: 2466 | C227: 1479.6 | D227: 1479.6
A228: DHA Rumanza-P1 | B228: 724 | C228: 434.4 | D228: 434.4
A229: DHA Villas | B229: 618 | C229: 370.8 | D229: 370.8
A230: DHA PH 1-5 | B230: 5458 | C230: 2729 | D230: 2729
A231: DHA PH-4 KK | B231: 1106 | C231: 553 | D231: 553
A232: DHA PH-5 M | B232: 926 | C232: 463 | D232: 463
... A260: Officers Colony Canal Road | B260: 90 | C260: 36 | D260: 36
A261: Faisalabad Citi Hosuing Extension | B261: 3312 | C261: 1987.2
A262: P4-Citi Housing | B262: 2926 | C262: 1755.6
A263: P1, Extended Part | B263: 386 | C263: 231.6
A264: Faisalabad Misc Areas | B264: 5240 | C264: 2620 | D264: 2620
A265: CITI Housing PH-2_Main | B265: 2620 | C265: 1310 | D265: 1310
A266: Eden Orchards | B266: 1778 | C266: 889 | D266: 889
A267: Kaleem Shaheed Colony-2 | B267: 842 | C267: 421 | D267: 421
A268: Faisalabad Ph4 | B268: 28822 | C268: 11528.8 | D268: 11528.8
A269: Al Barkat Villas | B269: 190 | C269: 76 | D269: 76
A270: Al Rehmat Villa | B270: 228 | C270: 91.2 | D270: 91.2
A271: Bilal City | B271: 170 | C271: 68 | D271: 68
A272: Canal Burg | B272: 206 | C272: 82.4 | D272: 82.4
A273: Canal Garden_Canal Rd | B273: 342 | C273: 136.8 | D273: 136.8
A274: Canal Park | B274: 140 | C274: 56 | D274: 56
A275: CITI Housing D Block | B275: 524 | C275: 209.6 | D275: 209.6
... A303: Tariq Garden & Makki Road Area | B303: 970 | C303: 388 | D303: 388
A304: Gujranwala Makki Road | B304: 13348 | C304: 5339.2
A305: PK-01 | B305: 5402 | C305: 2160.8
A306: PK-02 | B306: 7946 | C306: 3178.4
A307: Gujranwala Ph2 | B307: 76772 | C307: 30708.8 | D307: 30708.8
A308: Al mansoorah colony | B308: 492 | C308: 196.8 | D308: 196.8
A309: Aman Society | B309: 96 | C309: 38.4 | D309: 38.4
A310: Aurangzaib Town | B310: 594 | C310: 237.6 | D310: 237.6
A311: Civil Lines | B311: 1248 | C311: 499.2 | D311: 499.2
A312: DC Colony ext.PK_1 | B312: 1230 | C312: 492 | D312: 492
A313: DC Colony ext.PK_2 | B313: 722 | C313: 288.8 | D313: 288.8
A314: G magnolia Remaining Part | B314: 1520 | C314: 608 | D314: 608
A315: Garjakh Road | B315: 3480 | C315: 1392 | D315: 1392
A316: Ghordor Road P1 | B316: 3824 | C316: 1529.6 | D316: 1529.6
A317: Ghordor Road P2 | B317: 4278 | C317: 1711.2 | D317: 1711.2
A318: Ghordor Road P3 | B318: 3376 | C318: 1350.4 | D318: 1350.4
... A548: Unknown-2 | B548: 324 | C548: 145.8 | D548: 145.8
A549: Jhelum (P4) | B549: 6664 | C549: 2665.6
A550: Bagga | B550: 228 | C550: 91.2
A551: Chitan | B551: 294 | C551: 117.6
A552: Eid Gah | B552: 206 | C552: 82.4
A553: Gharmala | B553: 202 | C553: 80.8
A554: Gujjar pur | B554: 126 | C554: 50.4
...

Sheet Arial, Hybrid, Buried
A1: Number of Total Areas | B1: =COUNTA(B4:B1025) -> 4
A3: Row Labels | B3: Count of Area / Section / Pocket / Society (Original Name)
A4: Arial | B4: 93
A5: Buried | B5: 253
A6: Hybrid | B6: 804
A7: Grand Total | B7: 1150

Sheet HP - Customer Network
A1: Home Passes - Total | B1: =SUBTOTAL(9,B4:B245)/2 -> 1444140 | C1: =SUBTOTAL(9,C4:C245)/2 -> 600881.5 | D1: =SUBTOTAL(9,D4:D245)/2 -> 544448.26 | E1: =SUBTOTAL(9,E4:E245)/2 -> 229830.1 | F1: =SUBTOTAL(9,F4:F245)/2 -> 557486
A3: Row Labels | B3: Sum of Total H.P | C3: Sum of Customers According to % (Market Share) | D3: Sum of HP Based on completion - Realistic | E3: Sum of Sellable Capacity - E | F3: Sum of Sellable Capacity - T
A4: Abbottabad | B4: 3690 | C4: 1476 | D4: 1476 | E4: 1196 | F4: 2990
A5: Bahawalpur | B5: 28960 | C5: 11632.6 | D5: 11632.6 | E5: 3274.2 | F5: 8064
A6: Chitral | B6: 3832 | C6: 1532.8 | D6: 909.2 | E6: 623.6 | F6: 3118
A7: Daska | B7: 21078 | C7: 8431.2 | D7: 8431.2 | E7: 381.6 | F7: 954
A8: Dera Ghazi Khan | B8: 23218 | C8: 10448.1 | D8: 10448.1 | E8: 0 | F8: 0
A9: Faisalabad | B9: 37542 | C9: 16203.2 | D9: 14216 | E9: 13719.2 | F9: 32988
A10: Gujranwala | B10: 144722 | C10: 57941.6 | D10: 52338.4 | E10: 36427.2 | F10: 91068
A11: Hafizabad | B11: 27226 | C11: 12251.7 | D11: 12251.7 | E11: 0 | F11: 0
A12: Haripur | B12: 9672 | C12: 3868.8 | D12: 3868.8 | E12: 3212.8 | F12: 8032
A13: Hyderabad | B13: 17942 | C13: 7176.8 | D13: 6623.16 | E13: 4163.96 | F13: 11054
A14: Islamabad | B14: 103742 | C14: 44256.4 | D14: 43688.08 | E14: 26058.28 | F14: 60594
A15: Jhang | B15: 17360 | C15: 7812 | D15: 7812 | E15: 0 | F15: 0
... A36: Wahh | B36: 10504 | C36: 4716.8 | D36: 4716.8 | E36: 539.2 | F36: 1348
A37: Sukkur | B37: 18858 | C37: 7543.2 | E37: 0 | F37: 0
A38: Grand Total | B38: 1444140 | C38: 600881.5 | D38: 544448.26 | E38: 229830.1 | F38: 557486

Sheet Budgets
A1: Number of Total Areas | B1: =SUBTOTAL(9,B4:B201)/2 -> 1.8581034e+10 | C1: =SUBTOTAL(9,C4:C201)/2 -> 8.480651e+09 | D1: =SUBTOTAL(9,D4:D201)/2 -> 9.5197204e+09
A3: Row Labels | B3: Sum of Allocated Budget | C3: Sum of Revised Budget | D3: Sum of Difference
A4: Abbottabad | B4: 46635361 | C4: 4933262.7 | D4: 41702098
A5: Bahawalpur | B5: 2.3472034e+08 | C5: 78068027 | D5: 48751767
A6: Chitral | B6: 1.0745748e+08 | C6: 69955211 | D6: 37502271
A7: Daska | B7: 2.3819094e+08 | C7: 1.5004045e+08 | D7: 88150495
A8: Dera Ghazi Khan | B8: 4.1567031e+08 | C8: 4.1567031e+08
A9: Faisalabad | B9: 7.1513106e+08 | C9: 91398554 | D9: 5.6781073e+08
A10: Gujranwala | B10: 1.6429799e+09 | C10: 5.917392e+08 | D10: 1.0158168e+09
A11: Hafizabad | B11: 2.525768e+08 | C11: 2.525768e+08
A12: Haripur | B12: 1.661863e+08 | C12: 37229960 | D12: 1.2895634e+08
A13: Hyderabad | B13: 2.4718492e+08 | C13: 62007416 | D13: 1.7899249e+08
A14: Islamabad | B14: 1.8992789e+09 | C14: 8.5374564e+08 | D14: 1.0404171e+09
A15: Jhang | B15: 1.9091471e+08 | C15: 1.9091471e+08
A16: Jhelum | B16: 1.7292679e+08 | C16: 71668193 | D16: 51090933
A17: Karachi | B17: 2.1482582e+09 | C17: 9.1201307e+08 | D17: 1.1443347e+09
A18: Kasur | B18: 2.7718237e+08 | C18: 2.762782e+08
A19: Lahore | B19: 4.6871497e+09 | C19: 2.1832791e+09 | D19: 2.378936e+09
A20: Lalamusa | B20: 1.5178954e+08 | C20: 1.5178954e+08
A21: Mandi Bahauddin | B21: 3.0304575e+08 | C21: 3.0304575e+08
A22: Mardan | B22: 1.9876333e+08 | C22: 27323022 | D22: 1.714403e+08
A23: Multan | B23: 1.2777487e+09 | C23: 4.440241e+08 | D23: 8.0609967e+08
A24: Narowal | B24: 2.7474469e+08 | C24: 2.7474469e+08
A25: Okara | B25: 1.024588e+08 | C25: 15368820 | D25: 87089979
A26: Peshawar | B26: 3.0707597e+08 | C26: 99622300 | D26: 2.0745367e+08
A27: Quetta | B27: 1.3533896e+08 | C27: 22356218 | D27: 1.1298274e+08
A28: Rahim Yar Khan | B28: 1.1107145e+08 | C28: 14964640 | D28: 96106805
A29: Rawalpindi | B29: 1.7727756e+08 | C29: 47104579 | D29: 1.3017298e+08
A30: Sadiqabad | B30: 3.5043392e+08 | C30: 3.5043392e+08
A31: Sahiwal | B31: 85781337 | C31: 42199240 | D31: 39901742
A32: Sargodha | B32: 1.9330305e+08 | C32: 50749454 | D32: 1.425536e+08
A33: Sialkot | B33: 4.8328493e+08 | C33: 1.4187399e+08 | D33: 3.4141093e+08
A34: Swat | B34: 4.659263e+08 | C34: 93712460 | D34: 3.6429266e+08
A35: Torkhan Border | B35: 125214350 | C35: 18782152 | D35: 1.064322e+08
A36: Wahh | B36: 2.1079129e+08 | C36: 19469859 | D36: 1.9132143e+08
A37: Sukkur | B37: 1.8454016e+08 | C37: 1.2156825e+08
A38: Grand Total | B38: 1.8581034e+10 | C38: 8.480651e+09 | D38: 9.5197204e+09

Sheet Timeline Box
A1: Number of Total Areas | B1: =COUNTA(B4:B1025) -> 9
A3: Row Labels | B3: Count of CEM Number | F3: m | G3: C
A4: Apr-2026 | B4: 61 | F4: 46113 | G4: 61
A5: Feedback Awaited | B5: 45 | F5: 46204 | G5: 33
A6: Jul-2026 | B6: 33 | F6: 46174 | G6: 64
A7: Jun-2026 | B7: 64 | F7: 46082 | G7: 37
A8: Mar-2026 | B8: 37 | F8: 46143 | G8: 26
A9: May-2026 | B9: 26 | F9: 46296 | G9: 292
A10: Oct-2026 | B10: 292
A11: Timeline not applicable | B11: 592
A12: Grand Total | B12: 1150

Sheet Table of Contents
B2: Table of Content
B6: Dashboard - Summary
B7: Dashboard - Feasibility
B8: Dashboard - Financials
B9: Data Bank
B10: Timeline Box
B11: Standardized Comments
B12: HP - Customer Network
B13: Arial, Buried, Hybrid
B14: City Names
B15: Budgets
B16: Swap Details
... B20: Live/Not Live

Sheet Data Bank
P1: Feeder | Q1: 0.5 | R1: 1
P2: 100% Live | Q2: 0.15 | S2: 7805702.2 | T2: =S2*0.15 -> 1170855.3
T3: =S2*0.3*0.85 -> 1990454.1
F5: =SUBTOTAL(9,F8:F1380) -> 1444140 | G5: =SUBTOTAL(9,G8:G1380) -> 600881.5 | P5: =SUBTOTAL(9,Table8[Allocated Budget]) -> 2.209571e+10 | Q5: =SUBTOTAL(9,Table8[Revised Budget]) -> 1.0815617e+10 | V5: =SUBTOTAL(9,Table8[Total Civil works - Buried]) -> 7192974.7 | W5: =SUBTOTAL(9,Table8[Total Civil works - Arial]) -> #REF! | AQ5: =AQ520+AQ528+AQ773+AQ775+AQ780+AQ781+AQ793+AQ810+AQ811+AQ822+AQ1256 -> 0 | BP5: ßßßßßßß
Q6: =Q5/P5 -> 0.48948946 | AF6: AZ
A7: CEM Number | B7: CEM Initiation Date | C7: City Name | D7: Fesibility Name | E7: Area / Section / Pocket / Society (Original Name) | F7: Total H.P | G7: Customers According to % (Market Share) | H7: New Customers | I7: Terminated | J7: Active | K7: Not Active | L7: Remarks - Actuals | M7: Customers based on completion | N7: HP% based on Live % ( Work Progress) | O7: HP Based on completion - Realistic | P7: Allocated Budget | Q7: Revised Budget | R7: Difference | S7: Costing Efficiency | T7: Area / Section / Pocket / Society (Revised Name) | U7: Customers Take up %age (Key Factor) | V7: Total Civil works - Buried | W7: Total Civil works - Arial | X7: Originally Approved on: Arial, Buried, Hybrid | Y7: Allocation Percentage | Z7: Current Status (Live/Not Live) | AA7: Live on (Arial,Buried, Hybrid) | AB7: % of Completion of Work Done | AC7: Compeltion % not % | AD7: Start Date.. | AE7: Start Date OffSet | AF7: Duration | AG7: Days Remaining | AH7: Status | AI7: Timeline | AJ7: Timeline - Monthwise | AK7: Remarks by ODN | AL7: Remarks Grouped | AM7: Std Remarks | AN7: Additional Remarks (5-6M) | AO7: Additional Remarks (5-6M)2 | AP7: Swapped With - | AQ7: Swapped/Removal Budget | AR7: HP - Revised | AS7: 71 vs 26 | AT7: 72 vs 26
A8: I250212 | B8: 45549 | C8: Swat | D8: Mingora | E8: Between Fizaghat & Sangota | F8: 62 | G8: 24.8 | L8: NOC and Civil work pending | M8: =Table8[[#This Row],[Std Remarks]] -> NOT LIVE - RETAIN BUDGET | N8: =Table8[[#This Row],[% of Completion of Work Done]] -> 0 | O8: =Table8[[#This Row],[Customers According to % (Market Share)]] -> 24.8 | P8: 5376147.3 | Q8: =(Table8[[#This Row],[Allocated Budget]]*$Q$2)+(Table8[[#This Row],[Allocated Budget]]*(1-Table8[[#This Row],[HP% based on Live % ( Work Progress)]])*(1-$Q$2)) -> 5376147.3 | R8: 0 | S8: -1 | U8: 0.4 | V8: 1617 | W8: 3172.945 | X8: Hybrid | Y8: =Table8[[#This Row],[% of Completion of Work Done]] -> 0 | Z8: NOT LIVE | AB8: 0 | AC8: =VALUE(SUBSTITUTE(AB8,"%","")) -> 0 | AD8: 46082 | AE8: =IFERROR(Table8[[#This Row],[Timeline - Monthwise]]-MIN(Table8[Start Date..]),"None") -> 92 | AF8: =IFERROR(Table8[[#This Row],[Timeline - Monthwise]]-Table8[[#This Row],[Start Date..]]+1,"Duration Doesn't Exsists") -> 93 | AG8: =IFERROR(Table8[[#This Row],[Timeline - Monthwise]]-TODAY(),"No ETA") -> 45 | AH8: =IF(AB8=100%,"Completed",IF(AB8=0%,"Yet to Start","In Progress")) -> Yet to Start | AI8: 46174 | AJ8: Jun-2026 | AK8: Need to retain | AL8: Not Live - Work to be initiated | AM8: NOT LIVE - RETAIN BUDGET | AN8: 2 | AS8: =VLOOKUP(Table8[[#This Row],[CEM Number]],'71 CEMs'!$E$5:$E$76,1,0) -> I250212 | AT8: 46174
A9: I260296 | B9: No Initiation Date | C9: Sukkur | D9: Sukkur | E9: 100 Feet Rd P1 | F9: 1472 | G9: 588.8 | M9: =Table8[[#This Row],[Std Remarks]] -> NOT LIVE - RETAIN BUDGET | N9: =Table8[[#This Row],[% of Completion of Work Done]] -> 0.7 | P9: 22129453 | Q9: =(Table8[[#This Row],[Allocated Budget]]*$Q$2)+(Table8[[#This Row],[Allocated Budget]]*(1-Table8[[#This Row],[HP% based on Live % ( Work Progress)]])*(1-$Q$2)) -> 8962428.5 | V9: 5111.75 | W9: 19417.636 | X9: Hybrid | Y9: =Table8[[#This Row],[% of Completion of Work Done]] -> 0.7 | Z9: NOT LIVE | AB9: 0.7 | AC9: =VALUE(SUBSTITUTE(AB9,"%","")) -> 0.7 | AD9: 46082 | AE9: =IFERROR(Table8[[#This Row],[Timeline - Monthwise]]-MIN(Table8[Start Date..]),"None") -> 31 | AF9: =IFERROR(Table8[[#This Row],[Timeline - Monthwise]]-Table8[[#This Row],[Start Date..]]+1,"Duration Doesn't Exsists") -> 32 | AG9: =IFERROR(Table8[[#This Row],[Timeline - Monthwise]]-TODAY(),"No ETA") -> -16 | AH9: =IF(AB9=100%,"Completed",IF(AB9=0%,"Yet to Start","In Progress")) -> In Progress | AI9: 1 Month | AJ9: Apr-2026 | AK9: Crossing Pending and Other Civil Related work pending | AL9: Not Live - Work in Progress (WIP) | AM9: NOT LIVE - RETAIN BUDGET | AS9: =VLOOKUP(Table8[[#This Row],[CEM Number]],'71 CEMs'!$E$5:$E$76,1,0) -> #N/A | AT9: 46113
A10: I260296 | B10: No Initiation Date | C10: Sukkur | D10: Sukkur | E10: 100 Feet Rd P2 | F10: 2416 | G10: 966.4 | M10: =Table8[[#This Row],[Std Remarks]] -> NOT LIVE - RETAIN BUDGET | N10: =Table8[[#This Row],[% of Completion of Work Done]] -> 0.7 | P10: 26522964 | Q10: =(Table8[[#This Row],[Allocated Budget]]*$Q$2)+(Table8[[#This Row],[Allocated Budget]]*(1-Table8[[#This Row],[HP% based on Live % ( Work Progress)]])*(1-$Q$2)) -> 10741800 | V10: 4135.4 | W10: 30832.346 | X10: Hybrid | Y10: =Table8[[#This Row],[% of Completion of Work Done]] -> 0.7 | Z10: NOT LIVE | AB10: 0.7 | AC10: =VALUE(SUBSTITUTE(AB10,"%","")) -> 0.7 | AD10: 46082 | AE10: =IFERROR(Table8[[#This Row],[Timeline - Monthwise]]-MIN(Table8[Start Date..]),"None") -> 31 | AF10: =IFERROR(Table8[[#This Row],[Timeline - Monthwise]]-Table8[[#This Row],[Start Date..]]+1,"Duration Doesn't Exsists") -> 32 | AG10: =IFERROR(Table8[[#This Row],[Timeline - Monthwise]]-TODAY(),"No ETA") -> -16 | AH10: =IF(AB10=100%,"Completed",IF(AB10=0%,"Yet to Start","In Progress")) -> In Progress | AI10: 1 Month | AJ10: Apr-2026 | AK10: Crossing Pending and Other Civil Related work pending | AL10: Not Live - Work in Progress (WIP) | AM10: NOT LIVE - RETAIN BUDGET | AS10: =VLOOKUP(Table8[[#This Row],[CEM Number]],'71 CEMs'!$E$5:$E$76,1,0) -> #N/A | AT10: 46113
A11: I240683 | B11: 45427 | C11: Okara | D11: Okara | E11: 1-4L | F11: 708 | G11: 283.2 | H11: 231 | I11: 54 | K11: 177 | M11: =Table8[[#This Row],[Std Remarks]] -> LIVE - 100% Completed | N11: =Table8[[#This Row],[% of Completion of Work Done]] -> 1 | O11: =Table8[[#This Row],[Customers According to % (Market Share)]] -> 283.2 | P11: 14710666 | Q11: =Table8[[#This Row],[Allocated Budget]]*Table8[[#This Row],[Allocation Percentage]] -> 2206599.9 | R11: 12504066 | S11: -1 | U11: 0.4 | V11: 2849.7 | W11: 18016.25 | X11: Hybrid | Y11: =$Q$2 -> 0.15 | Z11: LIVE | AA11: Hybrid | AB11: 1 | AC11: =VALUE(SUBSTITUTE(AB11,"%","")) -> 1 | AD11: 46082 | AE11: =IFERROR(Table8[[#This Row],[Timeline - Monthwise]]-MIN(Table8[Start Date..]),"None") -> None | AF11: =IFERROR(Table8[[#This Row],[Timeline - Monthwise]]-Table8[[#This Row],[Start Date..]]+1,"Duration Doesn't Exsists") -> Duration Doesn't Exsists | AG11: =IFERROR(Table8[[#This Row],[Timeline - Monthwise]]-TODAY(),"No ETA") -> No ETA | AH11: =IF(AB11=100%,"Completed",IF(AB11=0%,"Yet to Start","In Progress")) -> Completed | AJ11: Timeline not applicable | AL11: Live - As per Plan | AM11: LIVE - 100% Completed | AS11: =VLOOKUP(Table8[[#This Row],[CEM Number]],'71 CEMs'!$E$5:$E$76,1,0) -> I240683 | AT11: Timeline not applicable
A12: I240518 | B12: 45349 | C12: Islamabad | D12: Naval Anchorage and other Areas (ISB) | E12: 18_P1 | F12: 888 | G12: 444 | H12: 14 | J12: 2 | K12: 12 | M12: =Table8[[#This Row],[Std Remarks]] -> LIVE - 100% Completed | N12: =Table8[[#This Row],[% of Completion of Work Done]] -> 1 | O12: =Table8[[#This Row],[Customers According to % (Market Share)]] -> 444 | P12: 5022290.1 | Q12: =Table8[[#This Row],[Allocated Budget]]*Table8[[#This Row],[Allocation Percentage]] -> 753343.52 | R12: 4268946.6 | S12: 0 | U12: 0.5 | V12: 1743.75 | W12: 2788.9897 | X12: Buried | Y12: =$Q$2 -> 0.15 | Z12: LIVE | AA12: Buried | AB12: 1 | AC12: =VALUE(SUBSTITUTE(AB12,"%","")) -> 1 | AD12: 46082 | AE12: =IFERROR(Table8[[#This Row],[Timeline - Monthwise]]-MIN(Table8[Start Date..]),"None") -> None | AF12: =IFERROR(Table8[[#This Row],[Timeline - Monthwise]]-Table8[[#This Row],[Start Date..]]+1,"Duration Doesn't Exsists") -> Duration Doesn't Exsists | AG12: =IFERROR(Table8[[#This Row],[Timeline - Monthwise]]-TODAY(),"No ETA") -> No ETA | AH12: =IF(AB12=100%,"Completed",IF(AB12=0%,"Yet to Start","In Progress")) -> Completed | AJ12: Timeline not applicable | AL12: Live - As per Plan | AM12: LIVE - 100% Completed | AS12: =VLOOKUP(Table8[[#This Row],[CEM Number]],'71 CEMs'!$E$5:$E$76,1,0) -> I240518 | AT12: Timeline not applicable
A13: I240518 | B13: 45349 | C13: Islamabad | D13: Naval Anchorage and other Areas (ISB) | E13: 18_P2 | F13: 278 | G13: 139 | H13: 0 | M13: =Table8[[#This Row],[Std Remarks]] -> REMOVE BUDGET (T) | N13: =Table8[[#This Row],[% of Completion of Work Done]] -> 0 | O13: =Table8[[#This Row],[Customers According to % (Market Share)]] -> 139 | P13: 4525188.2 | Q13: 0 | R13: 4525188.2 | S13: -1 | U13: 0.5 | V13: 1706.25 | W13: 6137.5094 | X13: Buried | Z13: NOT LIVE | AB13: 0 | AC13: =VALUE(SUBSTITUTE(AB13,"%","")) -> 0 | AD13: 46082 | AE13: =IFERROR(Table8[[#This Row],[Timeline - Monthwise]]-MIN(Table8[Start Date..]),"None") -> None | AF13: =IFERROR(Table8[[#This Row],[Timeline - Monthwise]]-Table8[[#This Row],[Start Date..]]+1,"Duration Doesn't Exsists") -> Duration Doesn't Exsists | AG13: =IFERROR(Table8[[#This Row],[Timeline - Monthwise]]-TODAY(),"No ETA") -> No ETA | AH13: =IF(AB13=100%,"Completed",IF(AB13=0%,"Yet to Start","In Progress")) -> Yet to Start | AJ13: Timeline not applicable | AK13: remove (after June) | AL13: Temporary Budget Removal | AM13: REMOVE BUDGET (T) | AQ13: =Table8[[#This Row],[Allocated Budget]]-Table8[[#This Row],[Allocated Budget]] -> 0 | AS13: =VLOOKUP(Table8[[#This Row],[CEM Number]],'71 CEMs'!$E$5:$E$76,1,0) -> I240518 | AT13: Timeline not applicable
A14: I240701 | B14: 45428 | C14: Feeders/Transportations | D14: Swat | E14: 24F Cable | F14: 0 | G14: 0 | M14: =Table8[[#This Row],[Std Remarks]] -> FEEDER ETC WORK - RETAIN BUDGET | N14: =Table8[[#This Row],[% of Completion of Work Done]] -> 0 | O14: =Table8[[#This Row],[Customers According to % (Market Share)]] -> 0 | P14: 660000 | Q14: =Table8[[#This Row],[Allocated Budget]]*Table8[[#This Row],[Allocation Percentage]] -> 330000 | R14: 330000 | S14: -1 | V14: 0 | W14: 0 | Y14: =$Q$1 -> 0.5 | AB14: 0 | AC14: =VALUE(SUBSTITUTE(AB14,"%","")) -> 0 | AD14: 46082 | AE14: =IFERROR(Table8[[#This Row],[Timeline - Monthwise]]-MIN(Table8[Start Date..]),"None") -> None | AF14: =IFERROR(Table8[[#This Row],[Timeline - Monthwise]]-Table8[[#This Row],[Start Date..]]+1,"Duration Doesn't Exsists") -> Duration Doesn't Exsists | AG14: =IFERROR(Table8[[#This Row],[Timeline - Monthwise]]-TODAY(),"No ETA") -> No ETA | AH14: =IF(AB14=100%,"Completed",IF(AB14=0%,"Yet to Start","In Progress")) -> Yet to Start | AJ14: Timeline not applicable | AL14: Feeders/Trans | AM14: FEEDER ETC WORK - RETAIN BUDGET | AS14: =VLOOKUP(Table8[[#This Row],[CEM Number]],'71 CEMs'!$E$5:$E$76,1,0) -> I240701 | AT14: Timeline not applicable
A15: I250734 | B15: No Initiation Date | C15: Bahawalpur | D15: Bahwalpur (P2)-B | E15: 3 Marla Scheme | F15: 1730 | G15: 692 | H15: Not Live Yet | M15: =Table8[[#This Row],[Std Remarks]] -> NOT LIVE - RETAIN BUDGET | N15: =Table8[[#This Row],[% of Completion of Work Done]] -> 0.85 | O15: =Table8[[#This Row],[Customers According to % (Market Share)]] -> 692 | P15: 8809572.5 | Q15: =(Table8[[#This Row],[Allocated Budget]]*$Q$2)+(Table8[[#This Row],[Allocated Budget]]*(1-Table8[[#This Row],[HP% based on Live % ( Work Progress)]])*(1-$Q$2)) -> 2444656.4 | V15: 1286.5177 | W15: 9419.8009 | X15: Hybrid | Y15: =Table8[[#This Row],[% of Completion of Work Done]] -> 0.85 | Z15: Not Live | AB15: 0.85 | AC15: =VALUE(SUBSTITUTE(AB15,"%","")) -> 0.85 | AD15: 46082 | AE15: =IFERROR(Table8[[#This Row],[Timeline - Monthwise]]-MIN(Table8[Start Date..]),"None") -> 31 | AF15: =IFERROR(Table8[[#This Row],[Timeline - Monthwise]]-Table8[[#This Row],[Start Date..]]+1,"Duration Doesn't Exsists") -> 32 | AG15: =IFERROR(Table8[[#This Row],[Timeline - Monthwise]]-TODAY(),"No ETA") -> -16 | AH15: =IF(AB15=100%,"Completed",IF(AB15=0%,"Yet to Start","In Progress")) -> In Progress | AI15: 1 Month | AJ15: Apr-2026 | AK15: Cable pulling pending | AL15: Not Live - Work in Progress (WIP) | AM15: NOT LIVE - RETAIN BUDGET | AS15: =VLOOKUP(Table8[[#This Row],[CEM Number]],'71 CEMs'!$E$5:$E$76,1,0) -> #N/A | AT15: 46113
A16: I260599 | B16: No Initiation Date | C16: Dera Ghazi Khan | D16: DG Khan | E16: Adam Housing-P1 | F16: 554 | G16: 249.3 | M16: =Table8[[#This Row],[Std Remarks]] -> NOT LIVE - RETAIN BUDGET | N16: =Table8[[#This Row],[% of Completion of Work Done]] -> 0 | O16: =Table8[[#This Row],[Customers According to % (Market Share)]] -> 249.3 | P16: 16702836 | Q16: =(Table8[[#This Row],[Allocated Budget]]*$Q$2)+(Table8[[#This Row],[Allocated Budget]]*(1-Table8[[#This Row],[HP% based on Live % ( Work Progress)]])*(1-$Q$2)) -> 16702836 | U16: 0.45 | V16: 8363.7 | W16: 7443 | X16: Hybrid | Y16: =Table8[[#This Row],[% of Completion of Work Done]] -> 0 | Z16: NOT LIVE | AB16: 0 | AC16: =VALUE(SUBSTITUTE(AB16,"%","")) -> 0 | AD16: 46082 | AE16: =IFERROR(Table8[[#This Row],[Timeline - Monthwise]]-MIN(Table8[Start Date..]),"None") -> 214 | AF16: =IFERROR(Table8[[#This Row],[Timeline - Monthwise]]-Table8[[#This Row],[Start Date..]]+1,"Duration Doesn't Exsists") -> 215 | AG16: =IFERROR(Table8[[#This Row],[Timeline - Monthwise]]-TODAY(),"No ETA") -> 167 | AH16: =IF(AB16=100%,"Completed",IF(AB16=0%,"Yet to Start","In Progress")) -> Yet to Start | AI16: 6 Months | AJ16: Oct-2026 | AK16: These Projects have not been started yet, proceedings shall be done post eid | AL16: Not Live - Work to be initiated | AM16: NOT LIVE - RETAIN BUDGET | AS16: =VLOOKUP(Table8[[#This Row],[CEM Number]],'71 CEMs'!$E$5:$E$76,1,0) -> #N/A | AT16: 46296
A17: I260599 | B17: No Initiation Date | C17: Dera Ghazi Khan | D17: DG Khan | E17: Adam Housing-P2 | F17: 428 | G17: 192.6 | M17: =Table8[[#This Row],[Std Remarks]] -> NOT LIVE - RETAIN BUDGET | N17: =Table8[[#This Row],[% of Completion of Work Done]] -> 0 | O17: =Table8[[#This Row],[Customers According to % (Market Share)]] -> 192.6 | P17: 14769070 | Q17: =(Table8[[#This Row],[Allocated Budget]]*$Q$2)+(Table8[[#This Row],[Allocated Budget]]*(1-Table8[[#This Row],[HP% based on Live % ( Work Progress)]])*(1-$Q$2)) -> 14769070 | U17: 0.45 | V17: 7360.65 | W17: 6328.5 | X17: Hybrid | Y17: =Table8[[#This Row],[% of Completion of Work Done]] -> 0 | Z17: NOT LIVE | AB17: 0 | AC17: =VALUE(SUBSTITUTE(AB17,"%","")) -> 0 | AD17: 46082 | AE17: =IFERROR(Table8[[#This Row],[Timeline - Monthwise]]-MIN(Table8[Start Date..]),"None") -> 214 | AF17: =IFERROR(Table8[[#This Row],[Timeline - Monthwise]]-Table8[[#This Row],[Start Date..]]+1,"Duration Doesn't Exsists") -> 215 | AG17: =IFERROR(Table8[[#This Row],[Timeline - Monthwise]]-TODAY(),"No ETA") -> 167 | AH17: =IF(AB17=100%,"Completed",IF(AB17=0%,"Yet to Start","In Progress")) -> Yet to Start | AI17: 6 Months | AJ17: Oct-2026 | AK17: These Projects have not been started yet, proceedings shall be done post eid | AL17: Not Live - Work to be initiated | AM17: NOT LIVE - RETAIN BUDGET | AS17: =VLOOKUP(Table8[[#This Row],[CEM Number]],'71 CEMs'!$E$5:$E$76,1,0) -> #N/A | AT17: 46296
A18: I240540 | B18: 45350 | C18: Mardan | D18: Mardan Ph2 | E18: Abdullah Colony & Nawa Killy | F18: 394 | G18: 157.6 | H18: 394 | I18: 13 | J18: 12 | K18: 1 | L18: 0 | N18: =Table8[[#This Row],[% of Completion of Work Done]] -> 1 | O18: =Table8[[#This Row],[Customers According to % (Market Share)]] -> 157.6 | P18: 7472398.9 | Q18: =Table8[[#This Row],[Allocated Budget]]*Table8[[#This Row],[Allocation Percentage]] -> 1120859.8 | R18: 6351539.1 | S18: -1 | U18: 0.4 | V18: 0 | W18: 19592.513 | X18: Hybrid | Y18: =$Q$2 -> 0.15 | Z18: LIVE | AA18: Hybrid | AB18: 1 | AC18: =VALUE(SUBSTITUTE(AB18,"%","")) -> 1 | AD18: 46082 | AE18: =IFERROR(Table8[[#This Row],[Timeline - Monthwise]]-MIN(Table8[Start Date..]),"None") -> None | AF18: =IFERROR(Table8[[#This Row],[Timeline - Monthwise]]-Table8[[#This Row],[Start Date..]]+1,"Duration Doesn't Exsists") -> Duration Doesn't Exsists | AG18: =IFERROR(Table8[[#This Row],[Timeline - Monthwise]]-TODAY(),"No ETA") -> No ETA | AH18: =IF(AB18=100%,"Completed",IF(AB18=0%,"Yet to Start","In Progress")) -> Completed | AJ18: Timeline not applicable | AL18: Live - As per Plan | AM18: LIVE - 100% Completed | AS18: =VLOOKUP(Table8[[#This Row],[CEM Number]],'71 CEMs'!$E$5:$E$76,1,0) -> I240540 | AT18: Timeline not applicable
A19: I240702 | B19: 45427 | C19: Hyderabad | D19: Hyderabad | E19: Abdullah Sports Tower Ext | F19: 96 | G19: 38.4 | H19: 58 | I19: 0 | M19: =Table8[[#This Row],[Std Remarks]] -> NOT LIVE - RETAIN BUDGET | N19: =Table8[[#This Row],[% of Completion of Work Done]] -> 1 | O19: =Table8[[#This Row],[Customers According to % (Market Share)]] -> 38.4 | P19: 3652917.5 | Q19: =(Table8[[#This Row],[Allocated Budget]]*$Q$2)+(Table8[[#This Row],[Allocated Budget]]*(1-Table8[[#This Row],[HP% based on Live % ( Work Progress)]])*(1-$Q$2)) -> 547937.62 | R19: 3104979.9 | S19: -1 | U19: 0.4 | V19: 1375.8562 | W19: 840.29761 | X19: Buried | Y19: =Table8[[#This Row],[% of Completion of Work Done]] -> 1 | Z19: NOT LIVE | AB19: 1 | AC19: =VALUE(SUBSTITUTE(AB19,"%","")) -> 1 | AD19: 46082 | AE19: =IFERROR(Table8[[#This Row],[Timeline - Monthwise]]-MIN(Table8[Start Date..]),"None") -> 92 | AF19: =IFERROR(Table8[[#This Row],[Timeline - Monthwise]]-Table8[[#This Row],[Start Date..]]+1,"Duration Doesn't Exsists") -> 93 | AG19: =IFERROR(Table8[[#This Row],[Timeline - Monthwise]]-TODAY(),"No ETA") -> 45 | AH19: =IF(AB19=100%,"Completed",IF(AB19=0%,"Yet to Start","In Progress")) -> Completed | AI19: 46174 | AJ19: Jun-2026 | AK19: Civil work completed, but not live due to pending customer possession from the builder. | AL19: Not Live - Work in Progress (WIP) | AM19: NOT LIVE - RETAIN BUDGET | AN19: 1 | AS19: =VLOOKUP(Table8[[#This Row],[CEM Number]],'71 CEMs'!$E$5:$E$76,1,0) -> I240702 | AT19: 46174
A20: I260599 | B20: No Initiation Date | C20: Dera Ghazi Khan | D20: DG Khan | E20: Al Hussain Garden | F20: 228 | G20: 102.6 | M20: =Table8[[#This Row],[Std Remarks]] -> NOT LIVE - RETAIN BUDGET | N20: =Table8[[#This Row],[% of Completion of Work Done]] -> 0 | O20: =Table8[[#This Row],[Customers According to % (Market Share)]] -> 102.6 | P20: 6341933 | Q20: =(Table8[[#This Row],[Allocated Budget]]*$Q$2)+(Table8[[#This Row],[Allocated Budget]]*(1-Table8[[#This Row],[HP% based on Live % ( Work Progress)]])*(1-$Q$2)) -> 6341933 | U20: 0.45 | V20: 3085.35 | W20: 2785.5 | X20: Hybrid | Y20: =Table8[[#This Row],[% of Completion of Work Done]] -> 0 | Z20: NOT LIVE | AB20: 0 | AC20: =VALUE(SUBSTITUTE(AB20,"%","")) -> 0 | AD20: 46082 | AE20: =IFERROR(Table8[[#This Row],[Timeline - Monthwise]]-MIN(Table8[Start Date..]),"None") -> 214 | AF20: =IFERROR(Table8[[#This Row],[Timeline - Monthwise]]-Table8[[#This Row],[Start Date..]]+1,"Duration Doesn't Exsists") -> 215 | AG20: =IFERROR(Table8[[#This Row],[Timeline - Monthwise]]-TODAY(),"No ETA") -> 167 | AH20: =IF(AB20=100%,"Completed",IF(AB20=0%,"Yet to Start","In Progress")) -> Yet to Start | AI20: 6 Months | AJ20: Oct-2026 | AK20: These Projects have not been started yet, proceedings shall be done post eid | AL20: Not Live - Work to be initiated | AM20: NOT LIVE - RETAIN BUDGET | AS20: =VLOOKUP(Table8[[#This Row],[CEM Number]],'71 CEMs'!$E$5:$E$76,1,0) -> #N/A | AT20: 46296
A21: I240703 | B21: 45427 | C21: Lahore | D21: Lahore Ph5 | E21: Abid Market | F21: 656 | G21: 262.4 | M21: =Table8[[#This Row],[Std Remarks]] -> NOT LIVE - RETAIN BUDGET | N21: =Table8[[#This Row],[% of Completion of Work Done]] -> 0.8 | O21: =Table8[[#This Row],[Customers According to % (Market Share)]] -> 262.4 | P21: 7827127.3 | Q21: =(Table8[[#This Row],[Allocated Budget]]*$Q$2)+(Table8[[#This Row],[Allocated Budget]]*(1-Table8[[#This Row],[HP% based on Live % ( Work Progress)]])*(1-$Q$2)) -> 2504680.7 | R21: 5322446.6 | S21: -1 | U21: 0.4 | V21: 874 | W21: 2022.5 | X21: Hybrid | Y21: =Table8[[#This Row],[% of Completion of Work Done]] -> 0.8 | Z21: NOT LIVE | AB21: 0.8 | AC21: =VALUE(SUBSTITUTE(AB21,"%","")) -> 0.8 | AD21: 46082 | AE21: =IFERROR(Table8[[#This Row],[Timeline - Monthwise]]-MIN(Table8[Start Date..]),"None") -> 0 | AF21: =IFERROR(Table8[[#This Row],[Timeline - Monthwise]]-Table8[[#This Row],[Start Date..]]+1,"Duration Doesn't Exsists") -> 1 | AG21: =IFERROR(Table8[[#This Row],[Timeline - Monthwise]]-TODAY(),"No ETA") -> -47 | AH21: =IF(AB21=100%,"Completed",IF(AB21=0%,"Yet to Start","In Progress")) -> In Progress | AI21: 46054 | AJ21: Mar-2026 | AK21: Cable pulling pending | AL21: Not Live - Work in Progress (WIP) | AM21: NOT LIVE - RETAIN BUDGET | AN21: 1 | AS21: =VLOOKUP(Table8[[#This Row],[CEM Number]],'71 CEMs'!$E$5:$E$76,1,0) -> I240703 | AT21: 46082
A22: I240705 | B22: 45427 | C22: Karachi | D22: Karachi Ph5 | E22: AbrazulMinal_KingsBridgeView | F22: 1400 | G22: 560 | M22: =Table8[[#This Row],[Std Remarks]] -> NOT LIVE - RETAIN BUDGET | N22: =Table8[[#This Row],[% of Completion of Work Done]] -> 0 | O22: =Table8[[#This Row],[Customers According to % (Market Share)]] -> 560 | P22: 4430148.1 | Q22: =(Table8[[#This Row],[Allocated Budget]]*$Q$2)+(Table8[[#This Row],[Allocated Budget]]*(1-Table8[[#This Row],[HP% based on Live % ( Work Progress)]])*(1-$Q$2)) -> 4430148.1 | R22: 0 | S22: -0.833 | U22: 0.4 | V22: 415.14421 | W22: 1275.481 | X22: Hybrid | Y22: =Table8[[#This Row],[% of Completion of Work Done]] -> 0 | Z22: NOT LIVE | AB22: 0 | AC22: =VALUE(SUBSTITUTE(AB22,"%","")) -> 0 | AD22: 46082 | AE22: =IFERROR(Table8[[#This Row],[Timeline - Monthwise]]-MIN(Table8[Start Date..]),"None") -> 31 | AF22: =IFERROR(Table8[[#This Row],[Timeline - Monthwise]]-Table8[[#This Row],[Start Date..]]+1,"Duration Doesn't Exsists") -> 32 | AG22: =IFERROR(Table8[[#This Row],[Timeline - Monthwise]]-TODAY(),"No ETA") -> -16 | AH22: =IF(AB22=100%,"Completed",IF(AB22=0%,"Yet to Start","In Progress")) -> Yet to Start | AI22: 46204 | AJ22: Apr-2026 | AK22: Permission Issue | AL22: Not Live - Permission Issues | AM22: NOT LIVE - RETAIN BUDGET | AN22: 2 | AS22: =VLOOKUP(Table8[[#This Row],[CEM Number]],'71 CEMs'!$E$5:$E$76,1,0) -> I240705 | AT22: 46113
A23: I240704 | B23: 45427 | C23: Multan | D23: Multan Ph3 | E23: Adam Housing | F23: 1130 | G23: 452 | H23: 0 | I23: 0 | J23: 0 | K23: 0 | L23: Budget Shifted | M23: =Table8[[#This Row],[Std Remarks]] -> LIVE - 100% Completed | N23: =Table8[[#This Row],[% of Completion of Work Done]] -> 1 | O23: =Table8[[#This Row],[Customers According to % (Market Share)]] -> 452 | P23: 36999249 | Q23: =Table8[[#This Row],[Allocated Budget]]*Table8[[#This Row],[Allocation Percentage]] -> 5549887.3 | R23: 31449362 | S23: #DIV/0! | U23: 0.4 | V23: 18159.3 | W23: 13746 | X23: Buried | Y23: =$Q$2 -> 0.15 | Z23: LIVE | AA23: Buried | AB23: 1 | AC23: =VALUE(SUBSTITUTE(AB23,"%","")) -> 1 | AD23: 46082 | AE23: =IFERROR(Table8[[#This Row],[Timeline - Monthwise]]-MIN(Table8[Start Date..]),"None") -> None | AF23: =IFERROR(Table8[[#This Row],[Timeline - Monthwise]]-Table8[[#This Row],[Start Date..]]+1,"Duration Doesn't Exsists") -> Duration Doesn't Exsists | AG23: =IFERROR(Table8[[#This Row],[Timeline - Monthwise]]-TODAY(),"No ETA") -> No ETA | AH23: =IF(AB23=100%,"Completed",IF(AB23=0%,"Yet to Start","In Progress")) -> Completed | AJ23: Timeline not applicable | AK23: Swapped with Manic Block Buch Villas | AL23: Swap Cases | AM23: LIVE - 100% Completed | AS23: =VLOOKUP(Table8[[#This Row],[CEM Number]],'71 CEMs'!$E$5:$E$76,1,0) -> I240704 | AT23: Timeline not applicable
A24: I260599 | B24: No Initiation Date | C24: Dera Ghazi Khan | D24: DG Khan | E24: Al Inam Gardens | F24: 316 | G24: 142.2 | M24: =Table8[[#This Row],[Std Remarks]] -> NOT LIVE - RETAIN BUDGET | N24: =Table8[[#This Row],[% of Completion of Work Done]] -> 0 | O24: =Table8[[#This Row],[Customers According to % (Market Share)]] -> 142.2 | P24: 10497665 | Q24: =(Table8[[#This Row],[Allocated Budget]]*$Q$2)+(Table8[[#This Row],[Allocated Budget]]*(1-Table8[[#This Row],[HP% based on Live % ( Work Progress)]])*(1-$Q$2)) -> 10497665 | U24: 0.45 | V24: 5045.6 | W24: 4503.7 | X24: Hybrid | Y24: =Table8[[#This Row],[% of Completion of Work Done]] -> 0 | Z24: NOT LIVE | AB24: 0 | AC24: =VALUE(SUBSTITUTE(AB24,"%","")) -> 0 | AD24: 46082 | AE24: =IFERROR(Table8[[#This Row],[Timeline - Monthwise]]-MIN(Table8[Start Date..]),"None") -> 214 | AF24: =IFERROR(Table8[[#This Row],[Timeline - Monthwise]]-Table8[[#This Row],[Start Date..]]+1,"Duration Doesn't Exsists") -> 215 | AG24: =IFERROR(Table8[[#This Row],[Timeline - Monthwise]]-TODAY(),"No ETA") -> 167 | AH24: =IF(AB24=100%,"Completed",IF(AB24=0%,"Yet to Start","In Progress")) -> Yet to Start | AI24: 6 Months | AJ24: Oct-2026 | AK24: These Projects have not been started yet, proceedings shall be done post eid | AL24: Not Live - Work to be initiated | AM24: NOT LIVE - RETAIN BUDGET | AS24: =VLOOKUP(Table8[[#This Row],[CEM Number]],'71 CEMs'!$E$5:$E$76,1,0) -> #N/A | AT24: 46296
A25: I260599 | B25: No Initiation Date | C25: Dera Ghazi Khan | D25: DG Khan | E25: Al Rasool Town | F25: 310 | G25: 139.5 | M25: =Table8[[#This Row],[Std Remarks]] -> NOT LIVE - RETAIN BUDGET | N25: =Table8[[#This Row],[% of Completion of Work Done]] -> 0 | O25: =Table8[[#This Row],[Customers According to % (Market Share)]] -> 139.5 | P25: 9129729 | Q25: =(Table8[[#This Row],[Allocated Budget]]*$Q$2)+(Table8[[#This Row],[Allocated Budget]]*(1-Table8[[#This Row],[HP% based on Live % ( Work Progress)]])*(1-$Q$2)) -> 9129729 | U25: 0.45 | V25: 4880.9 | W25: 4476 | X25: Hybrid | Y25: =Table8[[#This Row],[% of Completion of Work Done]] -> 0 | Z25: NOT LIVE | AB25: 0 | AC25: =VALUE(SUBSTITUTE(AB25,"%","")) -> 0 | AD25: 46082 | AE25: =IFERROR(Table8[[#This Row],[Timeline - Monthwise]]-MIN(Table8[Start Date..]),"None") -> 214 | AF25: =IFERROR(Table8[[#This Row],[Timeline - Monthwise]]-Table8[[#This Row],[Start Date..]]+1,"Duration Doesn't Exsists") -> 215 | AG25: =IFERROR(Table8[[#This Row],[Timeline - Monthwise]]-TODAY(),"No ETA") -> 167 | AH25: =IF(AB25=100%,"Completed",IF(AB25=0%,"Yet to Start","In Progress")) -> Yet to Start | AI25: 6 Months | AJ25: Oct-2026 | AK25: These Projects have not been started yet, proceedings shall be done post eid | AL25: Not Live - Work to be initiated | AM25: NOT LIVE - RETAIN BUDGET | AS25: =VLOOKUP(Table8[[#This Row],[CEM Number]],'71 CEMs'!$E$5:$E$76,1,0) -> #N/A | AT25: 46296
A26: I260599 | B26: No Initiation Date | C26: Dera Ghazi Khan | D26: DG Khan | E26: Canal View | F26: 582 | G26: 261.9 | M26: =Table8[[#This Row],[Std Remarks]] -> NOT LIVE - RETAIN BUDGET | N26: =Table8[[#This Row],[% of Completion of Work Done]] -> 0 | O26: =Table8[[#This Row],[Customers According to % (Market Share)]] -> 261.9 | P26: 5787365.8 | Q26: =(Table8[[#This Row],[Allocated Budget]]*$Q$2)+(Table8[[#This Row],[Allocated Budget]]*(1-Table8[[#This Row],[HP% based on Live % ( Work Progress)]])*(1-$Q$2)) -> 5787365.8 | U26: 0.45 | V26: 998.4 | W26: 4521.0697 | X26: Hybrid | Y26: =Table8[[#This Row],[% of Completion of Work Done]] -> 0 | Z26: NOT LIVE | AB26: 0 | AC26: =VALUE(SUBSTITUTE(AB26,"%","")) -> 0 | AD26: 46082 | AE26: =IFERROR(Table8[[#This Row],[Timeline - Monthwise]]-MIN(Table8[Start Date..]),"None") -> 214 | AF26: =IFERROR(Table8[[#This Row],[Timeline - Monthwise]]-Table8[[#This Row],[Start Date..]]+1,"Duration Doesn't Exsists") -> 215 | AG26: =IFERROR(Table8[[#This Row],[Timeline - Monthwise]]-TODAY(),"No ETA") -> 167 | AH26: =IF(AB26=100%,"Completed",IF(AB26=0%,"Yet to Start","In Progress")) -> Yet to Start | AI26: 6 Months | AJ26: Oct-2026 | AK26: These Projects have not been started yet, proceedings shall be done post eid | AL26: Not Live - Work to be initiated | AM26: NOT LIVE - RETAIN BUDGET | AS26: =VLOOKUP(Table8[[#This Row],[CEM Number]],'71 CEMs'!$E$5:$E$76,1,0) -> #N/A | AT26: 46296
A27: I240705 | B27: 45427 | C27: Karachi | D27: Karachi Ph5 | E27: AFOHS PK-1 | F27: 984 | G27: 393.6 | M27: =Table8[[#This Row],[Std Remarks]] -> LIVE - 100% Completed | N27: =Table8[[#This Row],[% of Completion of Work Done]] -> 1 | O27: =Table8[[#This Row],[Customers According to % (Market Share)]] -> 393.6 | P27: 52832203 | Q27: =Table8[[#This Row],[Allocated Budget]]*Table8[[#This Row],[Allocation Percentage]] -> 7924830.5 | R27: 44907373 | S27: -1 | U27: 0.4 | V27: 25051.586 | W27: 17445.469 | X27: Buried | Y27: =$Q$2 -> 0.15 | Z27: LIVE | AA27: Buried | AB27: 1 | AC27: =VALUE(SUBSTITUTE(AB27,"%","")) -> 1 | AD27: 46082 | AE27: =IFERROR(Table8[[#This Row],[Timeline - Monthwise]]-MIN(Table8[Start Date..]),"None") -> None | AF27: =IFERROR(Table8[[#This Row],[Timeline - Monthwise]]-Table8[[#This Row],[Start Date..]]+1,"Duration Doesn't Exsists") -> Duration Doesn't Exsists | AG27: =IFERROR(Table8[[#This Row],[Timeline - Monthwise]]-TODAY(),"No ETA") -> No ETA | AH27: =IF(AB27=100%,"Completed",IF(AB27=0%,"Yet to Start","In Progress")) -> Completed | AJ27: Timeline not applicable | AL27: Live - As per Plan | AM27: LIVE - 100% Completed | AS27: =VLOOKUP(Table8[[#This Row],[CEM Number]],'71 CEMs'!$E$5:$E$76,1,0) -> I240705 | AT27: Timeline not applicable
A28: I240705 | B28: 45427 | C28: Karachi | D28: Karachi Ph5 | E28: AFOHS PK-2 | F28: 478 | G28: 191.2 | M28: =Table8[[#This Row],[Std Remarks]] -> LIVE - 100% Completed | N28: =Table8[[#This Row],[% of Completion of Work Done]] -> 1 | O28: =Table8[[#This Row],[Customers According to % (Market Share)]] -> 191.2 | P28: 23923706 | Q28: =Table8[[#This Row],[Allocated Budget]]*Table8[[#This Row],[Allocation Percentage]] -> 3588555.9 | R28: 20335150 | S28: -0.765 | U28: 0.4 | V28: 11643.157 | W28: 9277.2194 | X28: Buried | Y28: =$Q$2 -> 0.15 | Z28: LIVE | AA28: Buried | AB28: 1 | AC28: =VALUE(SUBSTITUTE(AB28,"%","")) -> 1 | AD28: 46082 | AE28: =IFERROR(Table8[[#This Row],[Timeline - Monthwise]]-MIN(Table8[Start Date..]),"None") -> None | AF28: =IFERROR(Table8[[#This Row],[Timeline - Monthwise]]-Table8[[#This Row],[Start Date..]]+1,"Duration Doesn't Exsists") -> Duration Doesn't Exsists | AG28: =IFERROR(Table8[[#This Row],[Timeline - Monthwise]]-TODAY(),"No ETA") -> No ETA | AH28: =IF(AB28=100%,"Completed",IF(AB28=0%,"Yet to Start","In Progress")) -> Completed | AJ28: Timeline not applicable | AL28: Live - As per Plan | AM28: LIVE - 100% Completed | AS28: =VLOOKUP(Table8[[#This Row],[CEM Number]],'71 CEMs'!$E$5:$E$76,1,0) -> I240705 | AT28: Timeline not applicable
A29: I240705 | B29: 45427 | C29: Karachi | D29: Karachi Ph5 | E29: AFOHS PK-3 | F29: 1256 | G29: 502.4 | M29: =Table8[[#This Row],[Std Remarks]] -> NOT LIVE - RETAIN BUDGET | N29: =Table8[[#This Row],[% of Completion of Work Done]] -> 0 | O29: =Table8[[#This Row],[Customers According to % (Market Share)]] -> 502.4 | P29: 64454759 | Q29: =(Table8[[#This Row],[Allocated Budget]]*$Q$2)+(Table8[[#This Row],[Allocated Budget]]*(1-Table8[[#This Row],[HP% based on Live % ( Work Progress)]])*(1-$Q$2)) -> 64454759 | R29: 0 | S29: -1 | U29: 0.4 | V29: 29179.386 | W29: 25756.043 | X29: Buried | Y29: =Table8[[#This Row],[% of Completion of Work Done]] -> 0 | Z29: NOT LIVE | AB29: 0 | AC29: =VALUE(SUBSTITUTE(AB29,"%","")) -> 0 | AD29: 46082 | AE29: =IFERROR(Table8[[#This Row],[Timeline - Monthwise]]-MIN(Table8[Start Date..]),"None") -> 92 | AF29: =IFERROR(Table8[[#This Row],[Timeline - Monthwise]]-Table8[[#This Row],[Start Date..]]+1,"Duration Doesn't Exsists") -> 93 | AG29: =IFERROR(Table8[[#This Row],[Timeline - Monthwise]]-TODAY(),"No ETA") -> 45 | AH29: =IF(AB29=100%,"Completed",IF(AB29=0%,"Yet to Start","In Progress")) -> Yet to Start | AI29: 46174 | AJ29: Jun-2026 | AK29: Need to retain | AL29: Not Live - Work to be initiated | AM29: NOT LIVE - RETAIN BUDGET | AN29: 1 | AS29: =VLOOKUP(Table8[[#This Row],[CEM Number]],'71 CEMs'!$E$5:$E$76,1,0) -> I240705 | AT29: 46174
A30: INT-23-00445 | B30: 44924 | C30: Rawalpindi | D30: Rawalpindi Misc Areas | E30: Afzal Town Expansion(Aerial) | F30: 1428 | G30: 714 | H30: 245 | I30: 49 | J30: 53 | K30: 143 | M30: =Table8[[#This Row],[Std Remarks]] -> LIVE - 100% Completed | N30: =Table8[[#This Row],[% of Completion of Work Done]] -> 1 | O30: =Table8[[#This Row],[Customers According to % (Market Share)]] -> 714 | P30: 9210946.3 | Q30: =Table8[[#This Row],[Allocated Budget]]*Table8[[#This Row],[Allocation Percentage]] -> 1381641.9 | R30: 7829304.4 | S30: #DIV/0! | U30: 0.5 | V30: 0 | W30: 12237.876 | X30: Arial | Y30: =$Q$2 -> 0.15 | Z30: LIVE | AA30: Arial | AB30: 1 | AC30: =VALUE(SUBSTITUTE(AB30,"%","")) -> 1 | AD30: 46082 | AE30: =IFERROR(Table8[[#This Row],[Timeline - Monthwise]]-MIN(Table8[Start Date..]),"None") -> None | AF30: =IFERROR(Table8[[#This Row],[Timeline - Monthwise]]-Table8[[#This Row],[Start Date..]]+1,"Duration Doesn't Exsists") -> Duration Doesn't Exsists | AG30: =IFERROR(Table8[[#This Row],[Timeline - Monthwise]]-TODAY(),"No ETA") -> No ETA | AH30: =IF(AB30=100%,"Completed",IF(AB30=0%,"Yet to Start","In Progress")) -> Completed | AJ30: Timeline not applicable | AL30: Live - As per Plan | AM30: LIVE - 100% Completed | AS30: =VLOOKUP(Table8[[#This Row],[CEM Number]],'71 CEMs'!$E$5:$E$76,1,0) -> INT-23-00445 | AT30: Timeline not applicable
A31: I250212 | B31: 45549 | C31: Swat | D31: Mingora | E31: Airport (Ghanshal village) P01 | F31: 266 | G31: 106.4 | H31: 121 | I31: 107 | J31: 9 | K31: 5 | M31: =Table8[[#This Row],[Std Remarks]] -> LIVE - 100% Completed | N31: =Table8[[#This Row],[% of Completion of Work Done]] -> 1 | O31: =Table8[[#This Row],[Customers According to % (Market Share)]] -> 106.4 | P31: 2211881.5 | Q31: =Table8[[#This Row],[Allocated Budget]]*Table8[[#This Row],[Allocation Percentage]] -> 331782.22 | R31: 1880099.2 | S31: -1 | U31: 0.4 | V31: 0 | W31: 2931.9471 | X31: Arial | Y31: =$Q$2 -> 0.15 | Z31: LIVE | AA31: Arial | AB31: 1 | AC31: =VALUE(SUBSTITUTE(AB31,"%","")) -> 1 | AD31: 46082 | AE31: =IFERROR(Table8[[#This Row],[Timeline - Monthwise]]-MIN(Table8[Start Date..]),"None") -> None | AF31: =IFERROR(Table8[[#This Row],[Timeline - Monthwise]]-Table8[[#This Row],[Start Date..]]+1,"Duration Doesn't Exsists") -> Duration Doesn't Exsists | AG31: =IFERROR(Table8[[#This Row],[Timeline - Monthwise]]-TODAY(),"No ETA") -> No ETA | AH31: =IF(AB31=100%,"Completed",IF(AB31=0%,"Yet to Start","In Progress")) -> Completed | AJ31: Timeline not applicable | AL31: Live - As per Plan | AM31: LIVE - 100% Completed | AS31: =VLOOKUP(Table8[[#This Row],[CEM Number]],'71 CEMs'!$E$5:$E$76,1,0) -> I250212 | AT31: Timeline not applicable
A32: I250212 | B32: 45549 | C32: Swat | D32: Mingora | E32: Airport (Ghanshal village) P01 | F32: 234 | G32: 93.6 | H32: 108 | I32: 95 | J32: 6 | K32: 7 | M32: =Table8[[#This Row],[Std Remarks]] -> LIVE - 100% Completed | N32: =Table8[[#This Row],[% of Completion of Work Done]] -> 1 | O32: =Table8[[#This Row],[Customers According to % (Market Share)]] -> 93.6 | P32: 1910813 | Q32: =Table8[[#This Row],[Allocated Budget]]*Table8[[#This Row],[Allocation Percentage]] -> 286621.96 | R32: 1624191.1 | S32: -0.85 | U32: 0.4 | V32: 0 | W32: 3442.6945 | X32: Arial | Y32: =$Q$2 -> 0.15 | Z32: LIVE | AA32: Arial | AB32: 1 | AC32: =VALUE(SUBSTITUTE(AB32,"%","")) -> 1 | AD32: 46082 | AE32: =IFERROR(Table8[[#This Row],[Timeline - Monthwise]]-MIN(Table8[Start Date..]),"None") -> None | AF32: =IFERROR(Table8[[#This Row],[Timeline - Monthwise]]-Table8[[#This Row],[Start Date..]]+1,"Duration Doesn't Exsists") -> Duration Doesn't Exsists | AG32: =IFERROR(Table8[[#This Row],[Timeline - Monthwise]]-TODAY(),"No ETA") -> No ETA | AH32: =IF(AB32=100%,"Completed",IF(AB32=0%,"Yet to Start","In Progress")) -> Completed | AJ32: Timeline not applicable | AL32: Live - As per Plan | AM32: LIVE - 100% Completed | AS32: =VLOOKUP(Table8[[#This Row],[CEM Number]],'71 CEMs'!$E$5:$E$76,1,0) -> I250212 | AT32: Timeline not applicable
A33: I260599 | B33: No Initiation Date | C33: Dera Ghazi Khan | D33: DG Khan | E33: CPC Colony | F33: 346 | G33: 155.7 | M33: =Table8[[#This Row],[Std Remarks]] -> NOT LIVE - RETAIN BUDGET | N33: =Table8[[#This Row],[% of Completion of Work Done]] -> 0 | O33: =Table8[[#This Row],[Customers According to % (Market Share)]] -> 155.7 | P33: 6395179.5 | Q33: =(Table8[[#This Row],[Allocated Budget]]*$Q$2)+(Table8[[#This Row],[Allocated Budget]]*(1-Table8[[#This Row],[HP% based on Live % ( Work Progress)]])*(1-$Q$2)) -> 6395179.5 | U33: 0.45 | V33: 1705.2 | W33: 5519.602 | X33: Hybrid | Y33: =Table8[[#This Row],[% of Completion of Work Done]] -> 0 | Z33: NOT LIVE | AB33: 0 | AC33: =VALUE(SUBSTITUTE(AB33,"%","")) -> 0 | AD33: 46082 | AE33: =IFERROR(Table8[[#This Row],[Timeline - Monthwise]]-MIN(Table8[Start Date..]),"None") -> 214 | AF33: =IFERROR(Table8[[#This Row],[Timeline - Monthwise]]-Table8[[#This Row],[Start Date..]]+1,"Duration Doesn't Exsists") -> 215 | AG33: =IFERROR(Table8[[#This Row],[Timeline - Monthwise]]-TODAY(),"No ETA") -> 167 | AH33: =IF(AB33=100%,"Completed",IF(AB33=0%,"Yet to Start","In Progress")) -> Yet to Start | AI33: 6 Months | AJ33: Oct-2026 | AK33: These Projects have not been started yet, proceedings shall be done post eid | AL33: Not Live - Work to be initiated | AM33: NOT LIVE - RETAIN BUDGET | AS33: =VLOOKUP(Table8[[#This Row],[CEM Number]],'71 CEMs'!$E$5:$E$76,1,0) -> #N/A | AT33: 46296
A34: I260599 | B34: No Initiation Date | C34: Dera Ghazi Khan | D34: DG Khan | E34: Dream City | F34: 532 | G34: 239.4 | M34: =Table8[[#This Row],[Std Remarks]] -> NOT LIVE - RETAIN BUDGET | N34: =Table8[[#This Row],[% of Completion of Work Done]] -> 0 | O34: =Table8[[#This Row],[Customers According to % (Market Share)]] -> 239.4 | P34: 15928200 | Q34: =(Table8[[#This Row],[Allocated Budget]]*$Q$2)+(Table8[[#This Row],[Allocated Budget]]*(1-Table8[[#This Row],[HP% based on Live % ( Work Progress)]])*(1-$Q$2)) -> 15928200 | U34: 0.45 | V34: 7953.9 | W34: 7119 | X34: Hybrid | Y34: =Table8[[#This Row],[% of Completion of Work Done]] -> 0 | Z34: NOT LIVE | AB34: 0 | AC34: =VALUE(SUBSTITUTE(AB34,"%","")) -> 0 | AD34: 46082 | AE34: =IFERROR(Table8[[#This Row],[Timeline - Monthwise]]-MIN(Table8[Start Date..]),"None") -> 214 | AF34: =IFERROR(Table8[[#This Row],[Timeline - Monthwise]]-Table8[[#This Row],[Start Date..]]+1,"Duration Doesn't Exsists") -> 215 | AG34: =IFERROR(Table8[[#This Row],[Timeline - Monthwise]]-TODAY(),"No ETA") -> 167 | AH34: =IF(AB34=100%,"Completed",IF(AB34=0%,"Yet to Start","In Progress")) -> Yet to Start | AI34: 6 Months | AJ34: Oct-2026 | AK34: These Projects have not been started yet, proceedings shall be done post eid | AL34: Not Live - Work to be initiated | AM34: NOT LIVE - RETAIN BUDGET | AS34: =VLOOKUP(Table8[[#This Row],[CEM Number]],'71 CEMs'!$E$5:$E$76,1,0) -> #N/A | AT34: 46296
A35: I240700 | B35: 45427 | C35: Gujranwala | D35: Gujranwala Ph3 | E35: Ajwa City_P1 | F35: 2202 | G35: 880.8 | M35: =Table8[[#This Row],[Std Remarks]] -> LIVE - 100% Completed | N35: =Table8[[#This Row],[% of Completion of Work Done]] -> 1 | O35: =Table8[[#This Row],[Customers According to % (Market Share)]] -> 880.8 | P35: 60544036 | Q35: =Table8[[#This Row],[Allocated Budget]]*Table8[[#This Row],[Allocation Percentage]] -> 9081605.4 | R35: 51462430 | S35: -1 | U35: 0.4 | V35: 33561.646 | W35: 26265.255 | X35: Buried | Y35: =$Q$2 -> 0.15 | Z35: LIVE | AA35: Buried | AB35: 1 | AC35: =VALUE(SUBSTITUTE(AB35,"%","")) -> 1 | AD35: 46082 | AE35: =IFERROR(Table8[[#This Row],[Timeline - Monthwise]]-MIN(Table8[Start Date..]),"None") -> None | AF35: =IFERROR(Table8[[#This Row],[Timeline - Monthwise]]-Table8[[#This Row],[Start Date..]]+1,"Duration Doesn't Exsists") -> Duration Doesn't Exsists | AG35: =IFERROR(Table8[[#This Row],[Timeline - Monthwise]]-TODAY(),"No ETA") -> No ETA | AH35: =IF(AB35=100%,"Completed",IF(AB35=0%,"Yet to Start","In Progress")) -> Completed | AJ35: Timeline not applicable | AL35: Live - As per Plan | AM35: LIVE - 100% Completed | AS35: =VLOOKUP(Table8[[#This Row],[CEM Number]],'71 CEMs'!$E$5:$E$76,1,0) -> I240700 | AT35: Timeline not applicable
A36: I240700 | B36: 45427 | C36: Gujranwala | D36: Gujranwala Ph3 | E36: Ajwa City_P2 | F36: 3046 | G36: 1218.4 | M36: =Table8[[#This Row],[Std Remarks]] -> NOT LIVE - RETAIN BUDGET | N36: =Table8[[#This Row],[% of Completion of Work Done]] -> 0.75 | O36: =Table8[[#This Row],[Customers According to % (Market Share)]] -> 1218.4 | P36: 74734285 | Q36: =(Table8[[#This Row],[Allocated Budget]]*$Q$2)+(Table8[[#This Row],[Allocated Budget]]*(1-Table8[[#This Row],[HP% based on Live % ( Work Progress)]])*(1-$Q$2)) -> 27091178 | R36: 47643106 | S36: 0 | U36: 0.4 | V36: 41664.379 | W36: 33270.982 | X36: Buried | Y36: =Table8[[#This Row],[% of Completion of Work Done]] -> 0.75 | Z36: NOT LIVE | AB36: 0.75 | AC36: =VALUE(SUBSTITUTE(AB36,"%","")) -> 0.75 | AD36: 46082 | AE36: =IFERROR(Table8[[#This Row],[Timeline - Monthwise]]-MIN(Table8[Start Date..]),"None") -> 31 | AF36: =IFERROR(Table8[[#This Row],[Timeline - Monthwise]]-Table8[[#This Row],[Start Date..]]+1,"Duration Doesn't Exsists") -> 32 | AG36: =IFERROR(Table8[[#This Row],[Timeline - Monthwise]]-TODAY(),"No ETA") -> -16 | AH36: =IF(AB36=100%,"Completed",IF(AB36=0%,"Yet to Start","In Progress")) -> In Progress | AI36: 46113 | AJ36: Apr-2026 | AK36: HHs placement in progress | AL36: Not Live - Work in Progress (WIP) | AM36: NOT LIVE - RETAIN BUDGET | AN36: 1 | AS36: =VLOOKUP(Table8[[#This Row],[CEM Number]],'71 CEMs'!$E$5:$E$76,1,0) -> I240700 | AT36: 46113
A37: I240703 | B37: 45427 | C37: Lahore | D37: Lahore Ph5 | E37: Etihad Town | F37: 2606 | G37: 1042.4 | M37: =Table8[[#This Row],[Std Remarks]] -> LIVE - 100% Completed | N37: =Table8[[#This Row],[% of Completion of Work Done]] -> 1 | O37: =Table8[[#This Row],[Customers According to % (Market Share)]] -> 1042.4 | P37: 35268957 | Q37: =Table8[[#This Row],[Allocated Budget]]*Table8[[#This Row],[Allocation Percentage]] -> 5290343.6 | R37: 29978614 | S37: -1 | U37: 0.4 | V37: 9645 | W37: 5208.75 | X37: Buried | Y37: =$Q$2 -> 0.15 | Z37: LIVE | AA37: Buried | AB37: 1 | AC37: =VALUE(SUBSTITUTE(AB37,"%","")) -> 1 | AD37: 46082 | AE37: =IFERROR(Table8[[#This Row],[Timeline - Monthwise]]-MIN(Table8[Start Date..]),"None") -> None | AF37: =IFERROR(Table8[[#This Row],[Timeline - Monthwise]]-Table8[[#This Row],[Start Date..]]+1,"Duration Doesn't Exsists") -> Duration Doesn't Exsists | AG37: =IFERROR(Table8[[#This Row],[Timeline - Monthwise]]-TODAY(),"No ETA") -> No ETA | AH37: =IF(AB37=100%,"Completed",IF(AB37=0%,"Yet to Start","In Progress")) -> Completed | AJ37: Timeline not applicable | AL37: Live - As per Plan | AM37: LIVE - 100% Completed | AS37: =VLOOKUP(Table8[[#This Row],[CEM Number]],'71 CEMs'!$E$5:$E$76,1,0) -> I240703 | AT37: Timeline not applicable
A38: I240703 | B38: 45427 | C38: Feeders/Transportations | D38: Lahore Ph5 | E38: Feeder | F38: 0 | G38: 0 | M38: =Table8[[#This Row],[Std Remarks]] -> FEEDER ETC WORK - RETAIN BUDGET | N38: =Table8[[#This Row],[% of Completion of Work Done]] -> 0 | O38: =Table8[[#This Row],[Customers According to % (Market Share)]] -> 0 | P38: 82640788 | Q38: =Table8[[#This Row],[Allocated Budget]]*Table8[[#This Row],[Allocation Percentage]] -> 41320394 | R38: 41320394 | S38: -1 | V38: 26448 | W38: 0 | Y38: =$Q$1 -> 0.5 | AB38: 0 | AC38: =VALUE(SUBSTITUTE(AB38,"%","")) -> 0 | AD38: 46082 | AE38: =IFERROR(Table8[[#This Row],[Timeline - Monthwise]]-MIN(Table8[Start Date..]),"None") -> None | AF38: =IFERROR(Table8[[#This Row],[Timeline - Monthwise]]-Table8[[#This Row],[Start Date..]]+1,"Duration Doesn't Exsists") -> Duration Doesn't Exsists | AG38: =IFERROR(Table8[[#This Row],[Timeline - Monthwise]]-TODAY(),"No ETA") -> No ETA | AH38: =IF(AB38=100%,"Completed",IF(AB38=0%,"Yet to Start","In Progress")) -> Yet to Start | AJ38: Timeline not applicable | AL38: Feeders/Trans | AM38: FEEDER ETC WORK - RETAIN BUDGET | AS38: =VLOOKUP(Table8[[#This Row],[CEM Number]],'71 CEMs'!$E$5:$E$76,1,0) -> I240703 | AT38: Timeline not applicable
A39: I240703 | B39: 45427 | C39: Lahore | D39: Lahore Ph5 | E39: Ferozpur Road | F39: 2278 | G39: 911.2 | M39: =Table8[[#This Row],[Std Remarks]] -> NOT LIVE - RETAIN BUDGET | N39: =Table8[[#This Row],[% of Completion of Work Done]] -> 0.1 | O39: =Table8[[#This Row],[Customers According to % (Market Share)]] -> 911.2 | P39: 29293629 | Q39: =(Table8[[#This Row],[Allocated Budget]]*$Q$2)+(Table8[[#This Row],[Allocated Budget]]*(1-Table8[[#This Row],[HP% based on Live % ( Work Progress)]])*(1-$Q$2)) -> 26803670 | R39: 2489958.4 | S39: -1 | U39: 0.4 | V39: 4462 | W39: 11277 | X39: Hybrid | Y39: =Table8[[#This Row],[% of Completion of Work Done]] -> 0.1 | Z39: NOT LIVE | AB39: 0.1 | AC39: =VALUE(SUBSTITUTE(AB39,"%","")) -> 0.1 | AD39: 46082 | AE39: =IFERROR(Table8[[#This Row],[Timeline - Monthwise]]-MIN(Table8[Start Date..]),"None") -> 31 | AF39: =IFERROR(Table8[[#This Row],[Timeline - Monthwise]]-Table8[[#This Row],[Start Date..]]+1,"Duration Doesn't Exsists") -> 32 | AG39: =IFERROR(Table8[[#This Row],[Timeline - Monthwise]]-TODAY(),"No ETA") -> -16 | AH39: =IF(AB39=100%,"Completed",IF(AB39=0%,"Yet to Start","In Progress")) -> In Progress | AI39: 46113 | AJ39: Apr-2026 | AK39: Civil Work hold by TEPA/LDA | AL39: Not Live - Work in Progress (WIP) | AM39: NOT LIVE - RETAIN BUDGET | AN39: 2 | AS39: =VLOOKUP(Table8[[#This Row],[CEM Number]],'71 CEMs'!$E$5:$E$76,1,0) -> I240703 | AT39: 46113
A40: I260599 | B40: No Initiation Date | C40: Dera Ghazi Khan | D40: DG Khan | E40: Ejaz Town | F40: 690 | G40: 310.5 | M40: =Table8[[#This Row],[Std Remarks]] -> NOT LIVE - RETAIN BUDGET | N40: =Table8[[#This Row],[% of Completion of Work Done]] -> 0 | O40: =Table8[[#This Row],[Customers According to % (Market Share)]] -> 310.5 | P40: 8524660.4 | Q40: =(Table8[[#This Row],[Allocated Budget]]*$Q$2)+(Table8[[#This Row],[Allocated Budget]]*(1-Table8[[#This Row],[HP% based on Live % ( Work Progress)]])*(1-$Q$2)) -> 8524660.4 | U40: 0.45 | V40: 2365.55 | W40: 8636.0911 | X40: Hybrid | Y40: =Table8[[#This Row],[% of Completion of Work Done]] -> 0 | Z40: NOT LIVE | AB40: 0 | AC40: =VALUE(SUBSTITUTE(AB40,"%","")) -> 0 | AD40: 46082 | AE40: =IFERROR(Table8[[#This Row],[Timeline - Monthwise]]-MIN(Table8[Start Date..]),"None") -> 214 | AF40: =IFERROR(Table8[[#This Row],[Timeline - Monthwise]]-Table8[[#This Row],[Start Date..]]+1,"Duration Doesn't Exsists") -> 215 | AG40: =IFERROR(Table8[[#This Row],[Timeline - Monthwise]]-TODAY(),"No ETA") -> 167 | AH40: =IF(AB40=100%,"Completed",IF(AB40=0%,"Yet to Start","In Progress")) -> Yet to Start | AI40: 6 Months | AJ40: Oct-2026 | AK40: These Projects have not been started yet, proceedings shall be done post eid | AL40: Not Live - Work to be initiated | AM40: NOT LIVE - RETAIN BUDGET | AS40: =VLOOKUP(Table8[[#This Row],[CEM Number]],'71 CEMs'!$E$5:$E$76,1,0) -> #N/A | AT40: 46296
A41: I260599 | B41: No Initiation Date | C41: Feeders/Transportations | D41: DG Khan | E41: Feeder | F41: 0 | G41: 0 | M41: =Table8[[#This Row],[Std Remarks]] -> FEEDER ETC WORK - RETAIN BUDGET | N41: =Table8[[#This Row],[% of Completion of Work Done]] -> 0 | O41: =Table8[[#This Row],[Customers According to % (Market Share)]] -> 0 | P41: 93527861 | Q41: =Table8[[#This Row],[Allocated Budget]]*Table8[[#This Row],[Allocation Percentage]] -> 93527861 | V41: 30856.1 | W41: 0 | Y41: =$R$1 -> 1 | AB41: 0 | AC41: =VALUE(SUBSTITUTE(AB41,"%","")) -> 0 | AD41: 46082 | AE41: =IFERROR(Table8[[#This Row],[Timeline - Monthwise]]-MIN(Table8[Start Date..]),"None") -> None | AF41: =IFERROR(Table8[[#This Row],[Timeline - Monthwise]]-Table8[[#This Row],[Start Date..]]+1,"Duration Doesn't Exsists") -> Duration Doesn't Exsists | AG41: =IFERROR(Table8[[#This Row],[Timeline - Monthwise]]-TODAY(),"No ETA") -> No ETA | AH41: =IF(AB41=100%,"Completed",IF(AB41=0%,"Yet to Start","In Progress")) -> Yet to Start | AJ41: Timeline not applicable | AL41: Feeders/Trans | AM41: FEEDER ETC WORK - RETAIN BUDGET | AS41: =VLOOKUP(Table8[[#This Row],[CEM Number]],'71 CEMs'!$E$5:$E$76,1,0) -> #N/A | AT41: Timeline not applicable
A42: I240682 | B42: 45428 | C42: Faisalabad | D42: Faisalabad Ph4 | E42: Al Barkat Villas | F42: 190 | G42: 76 | I42: 0 | J42: 0 | K42: 0 | L42: Yet not active | M42: =Table8[[#This Row],[Std Remarks]] -> SWAPPED | N42: =Table8[[#This Row],[% of Completion of Work Done]] -> 0 | O42: =Table8[[#This Row],[Customers According to % (Market Share)]] -> 76 | P42: 3623949.2 | Q42: 0 | R42: 3623949.2 | S42: -1 | U42: 0.4 | V42: 809.6 | W42: 1873.2538 | X42: Arial | Z42: NOT LIVE | AB42: 0 | AC42: =VALUE(SUBSTITUTE(AB42,"%","")) -> 0 | AD42: 46082 | AE42: =IFERROR(Table8[[#This Row],[Timeline - Monthwise]]-MIN(Table8[Start Date..]),"None") -> None | AF42: =IFERROR(Table8[[#This Row],[Timeline - Monthwise]]-Table8[[#This Row],[Start Date..]]+1,"Duration Doesn't Exsists") -> Duration Doesn't Exsists | AG42: =IFERROR(Table8[[#This Row],[Timeline - Monthwise]]-TODAY(),"No ETA") -> No ETA | AH42: =IF(AB42=100%,"Completed",IF(AB42=0%,"Yet to Start","In Progress")) -> Yet to Start | AJ42: Timeline not applicable | AK42: swapping with city walk | AL42: Swap Cases | AM42: SWAPPED | AP42: City Walk | AQ42: 4637080.9 | AR42: 254 | AS42: =VLOOKUP(Table8[[#This Row],[CEM Number]],'71 CEMs'!$E$5:$E$76,1,0) -> I240682 | AT42: Timeline not applicable
A43: I250210 | B43: 45549 | C43: Sargodha | D43: Sargodha | E43: Al Freed Garden Phase 1 | F43: 480 | G43: 192 | J43: Not Active | L43: Not Live | M43: =Table8[[#This Row],[Std Remarks]] -> NOT LIVE - RETAIN BUDGET | N43: =Table8[[#This Row],[% of Completion of Work Done]] -> 0.7 | O43: =Table8[[#This Row],[Customers According to % (Market Share)]] -> 192 | P43: 7111635.2 | Q43: =(Table8[[#This Row],[Allocated Budget]]*$Q$2)+(Table8[[#This Row],[Allocated Budget]]*(1-Table8[[#This Row],[HP% based on Live % ( Work Progress)]])*(1-$Q$2)) -> 2880212.3 | R43: 4231422.9 | S43: -1 | U43: 0.4 | V43: 1465.1 | W43: 6090 | X43: Hybrid | Y43: =Table8[[#This Row],[% of Completion of Work Done]] -> 0.7 | Z43: NOT LIVE | AB43: 0.7 | AC43: =VALUE(SUBSTITUTE(AB43,"%","")) -> 0.7 | AD43: 46082 | AE43: =IFERROR(Table8[[#This Row],[Timeline - Monthwise]]-MIN(Table8[Start Date..]),"None") -> 61 | AF43: =IFERROR(Table8[[#This Row],[Timeline - Monthwise]]-Table8[[#This Row],[Start Date..]]+1,"Duration Doesn't Exsists") -> 62 | AG43: =IFERROR(Table8[[#This Row],[Timeline - Monthwise]]-TODAY(),"No ETA") -> 14 | AH43: =IF(AB43=100%,"Completed",IF(AB43=0%,"Yet to Start","In Progress")) -> In Progress | AI43: 2 Months | AJ43: May-2026 | AK43: This Colony linked with the DPLC backup connectivity; once completed, the area will go live. | AL43: Swap Cases | AM43: NOT LIVE - RETAIN BUDGET | AN43: 1 | AS43: =VLOOKUP(Table8[[#This Row],[CEM Number]],'71 CEMs'!$E$5:$E$76,1,0) -> I250210 | AT43: 46143
A44: I250210 | B44: 45549 | C44: Sargodha | D44: Sargodha | E44: Al Freed Garden Phase 2 | F44: 670 | G44: 268 | J44: Not Active | L44: Not Live | M44: =Table8[[#This Row],[Std Remarks]] -> NOT LIVE - RETAIN BUDGET | N44: =Table8[[#This Row],[% of Completion of Work Done]] -> 0.7 | O44: =Table8[[#This Row],[Customers According to % (Market Share)]] -> 268 | P44: 8501572.8 | Q44: =(Table8[[#This Row],[Allocated Budget]]*$Q$2)+(Table8[[#This Row],[Allocated Budget]]*(1-Table8[[#This Row],[HP% based on Live % ( Work Progress)]])*(1-$Q$2)) -> 3443137 | R44: 5058435.8 | S44: -0.765 | U44: 0.4 | V44: 1472 | W44: 8346.25 | X44: Hybrid | Y44: =Table8[[#This Row],[% of Completion of Work Done]] -> 0.7 | Z44: NOT LIVE | AB44: 0.7 | AC44: =VALUE(SUBSTITUTE(AB44,"%","")) -> 0.7 | AD44: 46082 | AE44: =IFERROR(Table8[[#This Row],[Timeline - Monthwise]]-MIN(Table8[Start Date..]),"None") -> 61 | AF44: =IFERROR(Table8[[#This Row],[Timeline - Monthwise]]-Table8[[#This Row],[Start Date..]]+1,"Duration Doesn't Exsists") -> 62 | AG44: =IFERROR(Table8[[#This Row],[Timeline - Monthwise]]-TODAY(),"No ETA") -> 14 | AH44: =IF(AB44=100%,"Completed",IF(AB44=0%,"Yet to Start","In Progress")) -> In Progress | AI44: 2 Months | AJ44: May-2026 | AK44: This Colony linked with the DPLC backup connectivity; once completed, the area will go live. | AL44: Swap Cases | AM44: NOT LIVE - RETAIN BUDGET | AN44: 1 | AS44: =VLOOKUP(Table8[[#This Row],[CEM Number]],'71 CEMs'!$E$5:$E$76,1,0) -> I250210 | AT44: 46143
A45: I260361 | B45: No Initiation Date | C45: Lahore | D45: Lhr MW City & Al Hafeez Ph-1 | E45: Al Hafeez Garden Ph-1 | F45: 1406 | G45: 562.4 | M45: =Table8[[#This Row],[Std Remarks]] -> NOT LIVE - RETAIN BUDGET | N45: =Table8[[#This Row],[% of Completion of Work Done]] -> 0 | P45: 23973146 | Q45: =(Table8[[#This Row],[Allocated Budget]]*$Q$2)+(Table8[[#This Row],[Allocated Budget]]*(1-Table8[[#This Row],[HP% based on Live % ( Work Progress)]])*(1-$Q$2)) -> 23973146 | V45: 10945.7 | W45: 10112.5 | X45: Buried | Y45: =Table8[[#This Row],[% of Completion of Work Done]] -> 0 | Z45: Not Live | AB45: 0 | AC45: =VALUE(SUBSTITUTE(AB45,"%","")) -> 0 | AD45: 46082 | AE45: =IFERROR(Table8[[#This Row],[Timeline - Monthwise]]-MIN(Table8[Start Date..]),"None") -> 122 | AF45: =IFERROR(Table8[[#This Row],[Timeline - Monthwise]]-Table8[[#This Row],[Start Date..]]+1,"Duration Doesn't Exsists") -> 123 | AG45: =IFERROR(Table8[[#This Row],[Timeline - Monthwise]]-TODAY(),"No ETA") -> 75 | AH45: =IF(AB45=100%,"Completed",IF(AB45=0%,"Yet to Start","In Progress")) -> Yet to Start | AI45: 4 moths | AJ45: Jul-2026 | AK45: Hold by Society end. | AL45: Not Live - Others Reasons | AM45: NOT LIVE - RETAIN BUDGET | AS45: =VLOOKUP(Table8[[#This Row],[CEM Number]],'71 CEMs'!$E$5:$E$76,1,0) -> #N/A | AT45: 46204
A46: I260105 | B46: No Initiation Date | C46: Lahore | D46: Al Hafeez Garden & Tariq Garden | E46: Al Hafeez Garden Ph-5 | F46: 1450 | G46: 580 | M46: =Table8[[#This Row],[Std Remarks]] -> NOT LIVE - RETAIN BUDGET | N46: =Table8[[#This Row],[% of Completion of Work Done]] -> 0 | P46: 26639855 | Q46: =(Table8[[#This Row],[Allocated Budget]]*$Q$2)+(Table8[[#This Row],[Allocated Budget]]*(1-Table8[[#This Row],[HP% based on Live % ( Work Progress)]])*(1-$Q$2)) -> 26639855 | V46: 14837.408 | W46: 13184.986 | X46: Buried | Y46: =Table8[[#This Row],[% of Completion of Work Done]] -> 0 | Z46: Not Live | AB46: 0 | AC46: =VALUE(SUBSTITUTE(AB46,"%","")) -> 0 | AD46: 46082 | AE46: =IFERROR(Table8[[#This Row],[Timeline - Monthwise]]-MIN(Table8[Start Date..]),"None") -> 92 | AF46: =IFERROR(Table8[[#This Row],[Timeline - Monthwise]]-Table8[[#This Row],[Start Date..]]+1,"Duration Doesn't Exsists") -> 93 | AG46: =IFERROR(Table8[[#This Row],[Timeline - Monthwise]]-TODAY(),"No ETA") -> 45 | AH46: =IF(AB46=100%,"Completed",IF(AB46=0%,"Yet to Start","In Progress")) -> Yet to Start | AI46: 3 months | AJ46: Jun-2026 | AK46: Duct Plan Shared / Hold by Society end. | AL46: Not Live - Work in Progress (WIP) | AM46: NOT LIVE - RETAIN BUDGET | AS46: =VLOOKUP(Table8[[#This Row],[CEM Number]],'71 CEMs'!$E$5:$E$76,1,0) -> #N/A | AT46: 46174
A47: I260105 | B47: No Initiation Date | C47: Lahore | D47: Al Hafeez Garden & Tariq Garden | E47: Al Hafeez Gdn Ph-2 | F47: 1404 | G47: 561.6 | M47: =Table8[[#This Row],[Std Remarks]] -> LIVE - 100% Completed | N47: =Table8[[#This Row],[% of Completion of Work Done]] -> 1 | P47: 29240432 | Q47: =Table8[[#This Row],[Allocated Budget]]*Table8[[#This Row],[Allocation Percentage]] -> 4386064.8 | V47: 14059.426 | W47: 11125.549 | X47: Buried | Y47: =$Q$2 -> 0.15 | Z47: Live | AA47: Buried | AB47: 1 | AC47: =VALUE(SUBSTITUTE(AB47,"%","")) -> 1 | AD47: 46082 | AE47: =IFERROR(Table8[[#This Row],[Timeline - Monthwise]]-MIN(Table8[Start Date..]),"None") -> None | AF47: =IFERROR(Table8[[#This Row],[Timeline - Monthwise]]-Table8[[#This Row],[Start Date..]]+1,"Duration Doesn't Exsists") -> Duration Doesn't Exsists | AG47: =IFERROR(Table8[[#This Row],[Timeline - Monthwise]]-TODAY(),"No ETA") -> No ETA | AH47: =IF(AB47=100%,"Completed",IF(AB47=0%,"Yet to Start","In Progress")) -> Completed | AJ47: Timeline not applicable | AL47: Live - As per Plan | AM47: LIVE - 100% Completed | AS47: =VLOOKUP(Table8[[#This Row],[CEM Number]],'71 CEMs'!$E$5:$E$76,1,0) -> #N/A | AT47: Timeline not applicable
A48: I240440 | B48: 45310 | C48: Lahore | D48: Al Jalil & Al khalil LHE | E48: Al Hamra | F48: 424 | G48: 169.6 | M48: =Table8[[#This Row],[Std Remarks]] -> NOT LIVE - RETAIN BUDGET | N48: =Table8[[#This Row],[% of Completion of Work Done]] -> 0.4 | O48: =Table8[[#This Row],[Customers According to % (Market Share)]] -> 169.6 | P48: 6253881.3 | Q48: =(Table8[[#This Row],[Allocated Budget]]*$Q$2)+(Table8[[#This Row],[Allocated Budget]]*(1-Table8[[#This Row],[HP% based on Live % ( Work Progress)]])*(1-$Q$2)) -> 4127561.6 | R48: 2126319.6 | S48: -1 | U48: 0.4 | V48: 1585.85 | W48: 5599.5 | X48: Hybrid | Y48: =Table8[[#This Row],[% of Completion of Work Done]] -> 0.4 | Z48: NOT LIVE | AB48: 0.4 | AC48: =VALUE(SUBSTITUTE(AB48,"%","")) -> 0.4 | AD48: 46082 | AE48: =IFERROR(Table8[[#This Row],[Timeline - Monthwise]]-MIN(Table8[Start Date..]),"None") -> 31 | AF48: =IFERROR(Table8[[#This Row],[Timeline - Monthwise]]-Table8[[#This Row],[Start Date..]]+1,"Duration Doesn't Exsists") -> 32 | AG48: =IFERROR(Table8[[#This Row],[Timeline - Monthwise]]-TODAY(),"No ETA") -> -16 | AH48: =IF(AB48=100%,"Completed",IF(AB48=0%,"Yet to Start","In Progress")) -> In Progress | AI48: 46113 | AJ48: Apr-2026 | AK48: Civil Work in Progress | AL48: Not Live - Work in Progress (WIP) | AM48: NOT LIVE - RETAIN BUDGET | AN48: 1 | AO48: 1 | AS48: =VLOOKUP(Table8[[#This Row],[CEM Number]],'71 CEMs'!$E$5:$E$76,1,0) -> I240440 | AT48: 46113
A49: I260599 | B49: No Initiation Date | C49: Dera Ghazi Khan | D49: DG Khan | E49: Garden Town | F49: 488 | G49: 219.6 | M49: =Table8[[#This Row],[Std Remarks]] -> NOT LIVE - RETAIN BUDGET | N49: =Table8[[#This Row],[% of Completion of Work Done]] -> 0 | O49: =Table8[[#This Row],[Customers According to % (Market Share)]] -> 219.6 | P49: 12126847 | Q49: =(Table8[[#This Row],[Allocated Budget]]*$Q$2)+(Table8[[#This Row],[Allocated Budget]]*(1-Table8[[#This Row],[HP% based on Live % ( Work Progress)]])*(1-$Q$2)) -> 12126847 | U49: 0.45 | V49: 6265.9846 | W49: 4904.8718 | X49: Hybrid | Y49: =Table8[[#This Row],[% of Completion of Work Done]] -> 0 | Z49: NOT LIVE | AB49: 0 | AC49: =VALUE(SUBSTITUTE(AB49,"%","")) -> 0 | AD49: 46082 | AE49: =IFERROR(Table8[[#This Row],[Timeline - Monthwise]]-MIN(Table8[Start Date..]),"None") -> 214 | AF49: =IFERROR(Table8[[#This Row],[Timeline - Monthwise]]-Table8[[#This Row],[Start Date..]]+1,"Duration Doesn't Exsists") -> 215 | AG49: =IFERROR(Table8[[#This Row],[Timeline - Monthwise]]-TODAY(),"No ETA") -> 167 | AH49: =IF(AB49=100%,"Completed",IF(AB49=0%,"Yet to Start","In Progress")) -> Yet to Start | AI49: 6 Months | AJ49: Oct-2026 | AK49: These Projects have not been started yet, proceedings shall be done post eid | AL49: Not Live - Work to be initiated | AM49: NOT LIVE - RETAIN BUDGET | AS49: =VLOOKUP(Table8[[#This Row],[CEM Number]],'71 CEMs'!$E$5:$E$76,1,0) -> #N/A | AT49: 46296
A50: I260599 | B50: No Initiation Date | C50: Dera Ghazi Khan | D50: DG Khan | E50: Gul zameen Colony | F50: 196 | G50: 88.2 | M50: =Table8[[#This Row],[Std Remarks]] -> NOT LIVE - RETAIN BUDGET | N50: =Table8[[#This Row],[% of Completion of Work Done]] -> 0 | O50: =Table8[[#This Row],[Customers According to % (Market Share)]] -> 88.2 | P50: 3336731.9 | Q50: =(Table8[[#This Row],[Allocated Budget]]*$Q$2)+(Table8[[#This Row],[Allocated Budget]]*(1-Table8[[#This Row],[HP% based on Live % ( Work Progress)]])*(1-$Q$2)) -> 3336731.9 | U50: 0.45 | V50: 804.36 | W50: 2478.3943 | X50: Hybrid | Y50: =Table8[[#This Row],[% of Completion of Work Done]] -> 0 | Z50: NOT LIVE | AB50: 0 | AC50: =VALUE(SUBSTITUTE(AB50,"%","")) -> 0 | AD50: 46082 | AE50: =IFERROR(Table8[[#This Row],[Timeline - Monthwise]]-MIN(Table8[Start Date..]),"None") -> 214 | AF50: =IFERROR(Table8[[#This Row],[Timeline - Monthwise]]-Table8[[#This Row],[Start Date..]]+1,"Duration Doesn't Exsists") -> 215 | AG50: =IFERROR(Table8[[#This Row],[Timeline - Monthwise]]-TODAY(),"No ETA") -> 167 | AH50: =IF(AB50=100%,"Completed",IF(AB50=0%,"Yet to Start","In Progress")) -> Yet to Start | AI50: 6 Months | AJ50: Oct-2026 | AK50: These Projects have not been started yet, proceedings shall be done post eid | AL50: Not Live - Work to be initiated | AM50: NOT LIVE - RETAIN BUDGET | AS50: =VLOOKUP(Table8[[#This Row],[CEM Number]],'71 CEMs'!$E$5:$E$76,1,0) -> #N/A | AT50: 46296
A51: I260599 | B51: No Initiation Date | C51: Dera Ghazi Khan | D51: DG Khan | E51: Gulberg housing Society | F51: 1166 | G51: 524.7 | M51: =Table8[[#This Row],[Std Remarks]] -> NOT LIVE - RETAIN BUDGET | N51: =Table8[[#This Row],[% of Completion of Work Done]] -> 0 | O51: =Table8[[#This Row],[Customers According to % (Market Share)]] -> 524.7 | P51: 31413471 | Q51: =(Table8[[#This Row],[Allocated Budget]]*$Q$2)+(Table8[[#This Row],[Allocated Budget]]*(1-Table8[[#This Row],[HP% based on Live % ( Work Progress)]])*(1-$Q$2)) -> 31413471 | U51: 0.45 | V51: 15330.539 | W51: 14229.649 | X51: Hybrid | Y51: =Table8[[#This Row],[% of Completion of Work Done]] -> 0 | Z51: NOT LIVE | AB51: 0 | AC51: =VALUE(SUBSTITUTE(AB51,"%","")) -> 0 | AD51: 46082 | AE51: =IFERROR(Table8[[#This Row],[Timeline - Monthwise]]-MIN(Table8[Start Date..]),"None") -> 214 | AF51: =IFERROR(Table8[[#This Row],[Timeline - Monthwise]]-Table8[[#This Row],[Start Date..]]+1,"Duration Doesn't Exsists") -> 215 | AG51: =IFERROR(Table8[[#This Row],[Timeline - Monthwise]]-TODAY(),"No ETA") -> 167 | AH51: =IF(AB51=100%,"Completed",IF(AB51=0%,"Yet to Start","In Progress")) -> Yet to Start | AI51: 6 Months | AJ51: Oct-2026 | AK51: These Projects have not been started yet, proceedings shall be done post eid | AL51: Not Live - Work to be initiated | AM51: NOT LIVE - RETAIN BUDGET | AS51: =VLOOKUP(Table8[[#This Row],[CEM Number]],'71 CEMs'!$E$5:$E$76,1,0) -> #N/A | AT51: 46296
A52: I260599 | B52: No Initiation Date | C52: Dera Ghazi Khan | D52: DG Khan | E52: Indus Smart City | F52: 148 | G52: 66.6 | M52: =Table8[[#This Row],[Std Remarks]] -> NOT LIVE - RETAIN BUDGET | N52: =Table8[[#This Row],[% of Completion of Work Done]] -> 0 | O52: =Table8[[#This Row],[Customers According to % (Market Share)]] -> 66.6 | P52: 2754114.6 | Q52: =(Table8[[#This Row],[Allocated Budget]]*$Q$2)+(Table8[[#This Row],[Allocated Budget]]*(1-Table8[[#This Row],[HP% based on Live % ( Work Progress)]])*(1-$Q$2)) -> 2754114.6 | U52: 0.45 | V52: 578.36617 | W52: 2335.5 | X52: Hybrid | Y52: =Table8[[#This Row],[% of Completion of Work Done]] -> 0 | Z52: NOT LIVE | AB52: 0 | AC52: =VALUE(SUBSTITUTE(AB52,"%","")) -> 0 | AD52: 46082 | AE52: =IFERROR(Table8[[#This Row],[Timeline - Monthwise]]-MIN(Table8[Start Date..]),"None") -> 214 | AF52: =IFERROR(Table8[[#This Row],[Timeline - Monthwise]]-Table8[[#This Row],[Start Date..]]+1,"Duration Doesn't Exsists") -> 215 | AG52: =IFERROR(Table8[[#This Row],[Timeline - Monthwise]]-TODAY(),"No ETA") -> 167 | AH52: =IF(AB52=100%,"Completed",IF(AB52=0%,"Yet to Start","In Progress")) -> Yet to Start | AI52: 6 Months | AJ52: Oct-2026 | AK52: These Projects have not been started yet, proceedings shall be done post eid | AL52: Not Live - Work to be initiated | AM52: NOT LIVE - RETAIN BUDGET | AS52: =VLOOKUP(Table8[[#This Row],[CEM Number]],'71 CEMs'!$E$5:$E$76,1,0) -> #N/A | AT52: 46296
A53: I240440 | B53: 45310 | C53: Lahore | D53: Al Jalil & Al khalil LHE | E53: Al Jalil Housing P2 | F53: 2232 | G53: 892.8 | M53: =Table8[[#This Row],[Std Remarks]] -> LIVE - 100% Completed | N53: =Table8[[#This Row],[% of Completion of Work Done]] -> 1 | O53: =Table8[[#This Row],[Customers According to % (Market Share)]] -> 892.8 | P53: 49814023 | Q53: =Table8[[#This Row],[Allocated Budget]]*Table8[[#This Row],[Allocation Percentage]] -> 7472103.4 | R53: 42341919 | S53: -0.85 | U53: 0.4 | V53: 27165.947 | W53: 25218.667 | X53: Buried | Y53: =$Q$2 -> 0.15 | Z53: LIVE | AA53: Buried | AB53: 1 | AC53: =VALUE(SUBSTITUTE(AB53,"%","")) -> 1 | AD53: 46082 | AE53: =IFERROR(Table8[[#This Row],[Timeline - Monthwise]]-MIN(Table8[Start Date..]),"None") -> None | AF53: =IFERROR(Table8[[#This Row],[Timeline - Monthwise]]-Table8[[#This Row],[Start Date..]]+1,"Duration Doesn't Exsists") -> Duration Doesn't Exsists | AG53: =IFERROR(Table8[[#This Row],[Timeline - Monthwise]]-TODAY(),"No ETA") -> No ETA | AH53: =IF(AB53=100%,"Completed",IF(AB53=0%,"Yet to Start","In Progress")) -> Completed | AJ53: Timeline not applicable | AL53: Live - As per Plan | AM53: LIVE - 100% Completed | AO53: 1 | AS53: =VLOOKUP(Table8[[#This Row],[CEM Number]],'71 CEMs'!$E$5:$E$76,1,0) -> I240440 | AT53: Timeline not applicable
A54: I240440 | B54: 45310 | C54: Lahore | D54: Al Jalil & Al khalil LHE | E54: Al Jalil Housing P3 | F54: 2210 | G54: 884 | M54: =Table8[[#This Row],[Std Remarks]] -> LIVE - 100% Completed | N54: =Table8[[#This Row],[% of Completion of Work Done]] -> 1 | O54: =Table8[[#This Row],[Customers According to % (Market Share)]] -> 884 | P54: 38711035 | Q54: =Table8[[#This Row],[Allocated Budget]]*Table8[[#This Row],[Allocation Percentage]] -> 5806655.2 | R54: 32904380 | S54: -1 | U54: 0.4 | V54: 20894.584 | W54: 19995.722 | X54: Buried | Y54: =$Q$2 -> 0.15 | Z54: LIVE | AA54: Buried | AB54: 1 | AC54: =VALUE(SUBSTITUTE(AB54,"%","")) -> 1 | AD54: 46082 | AE54: =IFERROR(Table8[[#This Row],[Timeline - Monthwise]]-MIN(Table8[Start Date..]),"None") -> None | AF54: =IFERROR(Table8[[#This Row],[Timeline - Monthwise]]-Table8[[#This Row],[Start Date..]]+1,"Duration Doesn't Exsists") -> Duration Doesn't Exsists | AG54: =IFERROR(Table8[[#This Row],[Timeline - Monthwise]]-TODAY(),"No ETA") -> No ETA | AH54: =IF(AB54=100%,"Completed",IF(AB54=0%,"Yet to Start","In Progress")) -> Completed | AJ54: Timeline not applicable | AL54: Live - As per Plan | AM54: LIVE - 100% Completed | AO54: 1 | AS54: =VLOOKUP(Table8[[#This Row],[CEM Number]],'71 CEMs'!$E$5:$E$76,1,0) -> I240440 | AT54: Timeline not applicable
A55: I240440 | B55: 45310 | C55: Lahore | D55: Al Jalil & Al khalil LHE | E55: Al Jalil Housing P4 | F55: 2106 | G55: 842.4 | M55: =Table8[[#This Row],[Std Remarks]] -> NOT LIVE - RETAIN BUDGET | N55: =Table8[[#This Row],[% of Completion of Work Done]] -> 0 | O55: =Table8[[#This Row],[Customers According to % (Market Share)]] -> 842.4 | P55: 39895633 | Q55: =(Table8[[#This Row],[Allocated Budget]]*$Q$2)+(Table8[[#This Row],[Allocated Budget]]*(1-Table8[[#This Row],[HP% based on Live % ( Work Progress)]])*(1-$Q$2)) -> 39895633 | R55: 0 | S55: -0.85 | U55: 0.4 | V55: 22634.977 | W55: 21018.675 | X55: Buried | Y55: =Table8[[#This Row],[% of Completion of Work Done]] -> 0 | Z55: NOT LIVE | AB55: 0 | AC55: =VALUE(SUBSTITUTE(AB55,"%","")) -> 0 | AD55: 46082 | AE55: =IFERROR(Table8[[#This Row],[Timeline - Monthwise]]-MIN(Table8[Start Date..]),"None") -> None | AF55: =IFERROR(Table8[[#This Row],[Timeline - Monthwise]]-Table8[[#This Row],[Start Date..]]+1,"Duration Doesn't Exsists") -> Duration Doesn't Exsists | AG55: =IFERROR(Table8[[#This Row],[Timeline - Monthwise]]-TODAY(),"No ETA") -> No ETA | AH55: =IF(AB55=100%,"Completed",IF(AB55=0%,"Yet to Start","In Progress")) -> Yet to Start | AI55: Not Given By BUH | AJ55: Feedback Awaited | AK55: Need to retain | AL55: Not Live - Work to be initiated | AM55: NOT LIVE - RETAIN BUDGET | AN55: 2 | AO55: 1 | AS55: =VLOOKUP(Table8[[#This Row],[CEM Number]],'71 CEMs'!$E$5:$E$76,1,0) -> I240440 | AT55: Feedback Awaited
A56: I240440 | B56: 45310 | C56: Lahore | D56: Al Jalil & Al khalil LHE | E56: Al Kabeer Ph-2-Pk1 | F56: 2268 | G56: 907.2 | M56: =Table8[[#This Row],[Std Remarks]] -> LIVE - 100% Completed | N56: =Table8[[#This Row],[% of Completion of Work Done]] -> 1 | O56: =Table8[[#This Row],[Customers According to % (Market Share)]] -> 907.2 | P56: 39719478 | Q56: =Table8[[#This Row],[Allocated Budget]]*Table8[[#This Row],[Allocation Percentage]] -> 5957921.8 | R56: 33761557 | S56: -1 | U56: 0.4 | V56: 20815.722 | W56: 21072.583 | X56: Buried | Y56: =$Q$2 -> 0.15 | Z56: LIVE | AA56: Buried | AB56: 1 | AC56: =VALUE(SUBSTITUTE(AB56,"%","")) -> 1 | AD56: 46082 | AE56: =IFERROR(Table8[[#This Row],[Timeline - Monthwise]]-MIN(Table8[Start Date..]),"None") -> None | AF56: =IFERROR(Table8[[#This Row],[Timeline - Monthwise]]-Table8[[#This Row],[Start Date..]]+1,"Duration Doesn't Exsists") -> Duration Doesn't Exsists | AG56: =IFERROR(Table8[[#This Row],[Timeline - Monthwise]]-TODAY(),"No ETA") -> No ETA | AH56: =IF(AB56=100%,"Completed",IF(AB56=0%,"Yet to Start","In Progress")) -> Completed | AJ56: Timeline not applicable | AL56: Live - As per Plan | AM56: LIVE - 100% Completed | AS56: =VLOOKUP(Table8[[#This Row],[CEM Number]],'71 CEMs'!$E$5:$E$76,1,0) -> I240440 | AT56: Timeline not applicable
A57: I240440 | B57: 45310 | C57: Lahore | D57: Al Jalil & Al khalil LHE | E57: Al Kabeer Ph-2-Pk2 | F57: 3086 | G57: 1234.4 | M57: =Table8[[#This Row],[Std Remarks]] -> NOT LIVE - RETAIN BUDGET | N57: =Table8[[#This Row],[% of Completion of Work Done]] -> 0.25 | O57: =Table8[[#This Row],[Customers According to % (Market Share)]] -> 1234.4 | P57: 65205217 | Q57: =(Table8[[#This Row],[Allocated Budget]]*$Q$2)+(Table8[[#This Row],[Allocated Budget]]*(1-Table8[[#This Row],[HP% based on Live % ( Work Progress)]])*(1-$Q$2)) -> 51349108 | R57: 13856109 | S57: -0.85 | U57: 0.4 | V57: 33751.263 | W57: 28797.228 | X57: Buried | Y57: =Table8[[#This Row],[% of Completion of Work Done]] -> 0.25 | Z57: NOT LIVE | AB57: 0.25 | AC57: =VALUE(SUBSTITUTE(AB57,"%","")) -> 0.25 | AD57: 46082 | AE57: =IFERROR(Table8[[#This Row],[Timeline - Monthwise]]-MIN(Table8[Start Date..]),"None") -> 31 | AF57: =IFERROR(Table8[[#This Row],[Timeline - Monthwise]]-Table8[[#This Row],[Start Date..]]+1,"Duration Doesn't Exsists") -> 32 | AG57: =IFERROR(Table8[[#This Row],[Timeline - Monthwise]]-TODAY(),"No ETA") -> -16 | AH57: =IF(AB57=100%,"Completed",IF(AB57=0%,"Yet to Start","In Progress")) -> In Progress | AI57: 46113 | AJ57: Apr-2026 | AK57: Duct Plan Shared | AL57: Not Live - Work in Progress (WIP) | AM57: NOT LIVE - RETAIN BUDGET | AN57: 1 | AS57: =VLOOKUP(Table8[[#This Row],[CEM Number]],'71 CEMs'!$E$5:$E$76,1,0) -> I240440 | AT57: 46113
A58: I240440 | B58: 45310 | C58: Lahore | D58: Al Jalil & Al khalil LHE | E58: Al Kabeer Ph-2-Pk3 | F58: 776 | G58: 310.4 | M58: =Table8[[#This Row],[Std Remarks]] -> NOT LIVE - RETAIN BUDGET | N58: =Table8[[#This Row],[% of Completion of Work Done]] -> 0 | O58: =Table8[[#This Row],[Customers According to % (Market Share)]] -> 310.4 | P58: 18028083 | Q58: =(Table8[[#This Row],[Allocated Budget]]*$Q$2)+(Table8[[#This Row],[Allocated Budget]]*(1-Table8[[#This Row],[HP% based on Live % ( Work Progress)]])*(1-$Q$2)) -> 18028083 | R58: 0 | S58: -1 | U58: 0.4 | V58: 9468.5702 | W58: 7634.6282 | X58: Buried | Y58: =Table8[[#This Row],[% of Completion of Work Done]] -> 0 | Z58: NOT LIVE | AB58: 0 | AC58: =VALUE(SUBSTITUTE(AB58,"%","")) -> 0 | AD58: 46082 | AE58: =IFERROR(Table8[[#This Row],[Timeline - Monthwise]]-MIN(Table8[Start Date..]),"None") -> None | AF58: =IFERROR(Table8[[#This Row],[Timeline - Monthwise]]-Table8[[#This Row],[Start Date..]]+1,"Duration Doesn't Exsists") -> Duration Doesn't Exsists | AG58: =IFERROR(Table8[[#This Row],[Timeline - Monthwise]]-TODAY(),"No ETA") -> No ETA | AH58: =IF(AB58=100%,"Completed",IF(AB58=0%,"Yet to Start","In Progress")) -> Yet to Start | AI58: Not Given By BUH | AJ58: Feedback Awaited | AK58: Need to retain | AL58: Not Live - Work to be initiated | AM58: NOT LIVE - RETAIN BUDGET | AN58: 2 | AS58: =VLOOKUP(Table8[[#This Row],[CEM Number]],'71 CEMs'!$E$5:$E$76,1,0) -> I240440 | AT58: Feedback Awaited
A59: I240440 | B59: 45310 | C59: Lahore | D59: Al Jalil & Al khalil LHE | E59: Al Kabeer Town Ph-1 | F59: 512 | G59: 204.8 | M59: =Table8[[#This Row],[Std Remarks]] -> LIVE - 100% Completed | N59: =Table8[[#This Row],[% of Completion of Work Done]] -> 1 | O59: =Table8[[#This Row],[Customers According to % (Market Share)]] -> 204.8 | P59: 10728206 | Q59: =Table8[[#This Row],[Allocated Budget]]*Table8[[#This Row],[Allocation Percentage]] -> 1609231 | R59: 9118975.5 | S59: -0.85 | U59: 0.4 | V59: 4849.5 | W59: 3910.5 | X59: Buried | Y59: =$Q$2 -> 0.15 | Z59: LIVE | AA59: Buried | AB59: 1 | AC59: =VALUE(SUBSTITUTE(AB59,"%","")) -> 1 | AD59: 46082 | AE59: =IFERROR(Table8[[#This Row],[Timeline - Monthwise]]-MIN(Table8[Start Date..]),"None") -> None | AF59: =IFERROR(Table8[[#This Row],[Timeline - Monthwise]]-Table8[[#This Row],[Start Date..]]+1,"Duration Doesn't Exsists") -> Duration Doesn't Exsists | AG59: =IFERROR(Table8[[#This Row],[Timeline - Monthwise]]-TODAY(),"No ETA") -> No ETA | AH59: =IF(AB59=100%,"Completed",IF(AB59=0%,"Yet to Start","In Progress")) -> Completed | AJ59: Timeline not applicable | AL59: Live - As per Plan | AM59: LIVE - 100% Completed | AS59: =VLOOKUP(Table8[[#This Row],[CEM Number]],'71 CEMs'!$E$5:$E$76,1,0) -> I240440 | AT59: Timeline not applicable
A60: I260599 | B60: No Initiation Date | C60: Dera Ghazi Khan | D60: DG Khan | E60: K Gaardens | F60: 360 | G60: 162 | M60: =Table8[[#This Row],[Std Remarks]] -> NOT LIVE - RETAIN BUDGET | N60: =Table8[[#This Row],[% of Completion of Work Done]] -> 0 | O60: =Table8[[#This Row],[Customers According to % (Market Share)]] -> 162 | P60: 11056413 | Q60: =(Table8[[#This Row],[Allocated Budget]]*$Q$2)+(Table8[[#This Row],[Allocated Budget]]*(1-Table8[[#This Row],[HP% based on Live % ( Work Progress)]])*(1-$Q$2)) -> 11056413 | U60: 0.45 | V60: 5275.5827 | W60: 4704 | X60: Hybrid | Y60: =Table8[[#This Row],[% of Completion of Work Done]] -> 0 | Z60: NOT LIVE | AB60: 0 | AC60: =VALUE(SUBSTITUTE(AB60,"%","")) -> 0 | AD60: 46082 | AE60: =IFERROR(Table8[[#This Row],[Timeline - Monthwise]]-MIN(Table8[Start Date..]),"None") -> 214 | AF60: =IFERROR(Table8[[#This Row],[Timeline - Monthwise]]-Table8[[#This Row],[Start Date..]]+1,"Duration Doesn't Exsists") -> 215 | AG60: =IFERROR(Table8[[#This Row],[Timeline - Monthwise]]-TODAY(),"No ETA") -> 167 | AH60: =IF(AB60=100%,"Completed",IF(AB60=0%,"Yet to Start","In Progress")) -> Yet to Start | AI60: 6 Months | AJ60: Oct-2026 | AK60: These Projects have not been started yet, proceedings shall be done post eid | AL60: Not Live - Work to be initiated | AM60: NOT LIVE - RETAIN BUDGET | AS60: =VLOOKUP(Table8[[#This Row],[CEM Number]],'71 CEMs'!$E$5:$E$76,1,0) -> #N/A | AT60: 46296
A61: I260599 | B61: No Initiation Date | C61: Dera Ghazi Khan | D61: DG Khan | E61: Khayaban e Sarwar | F61: 1110 | G61: 499.5 | M61: =Table8[[#This Row],[Std Remarks]] -> NOT LIVE - RETAIN BUDGET | N61: =Table8[[#This Row],[% of Completion of Work Done]] -> 0 | O61: =Table8[[#This Row],[Customers According to % (Market Share)]] -> 499.5 | P61: 17604297 | Q61: =(Table8[[#This Row],[Allocated Budget]]*$Q$2)+(Table8[[#This Row],[Allocated Budget]]*(1-Table8[[#This Row],[HP% based on Live % ( Work Progress)]])*(1-$Q$2)) -> 17604297 | U61: 0.45 | V61: 3995.2781 | W61: 15367.227 | X61: Hybrid | Y61: =Table8[[#This Row],[% of Completion of Work Done]] -> 0 | Z61: NOT LIVE | AB61: 0 | AC61: =VALUE(SUBSTITUTE(AB61,"%","")) -> 0 | AD61: 46082 | AE61: =IFERROR(Table8[[#This Row],[Timeline - Monthwise]]-MIN(Table8[Start Date..]),"None") -> 214 | AF61: =IFERROR(Table8[[#This Row],[Timeline - Monthwise]]-Table8[[#This Row],[Start Date..]]+1,"Duration Doesn't Exsists") -> 215 | AG61: =IFERROR(Table8[[#This Row],[Timeline - Monthwise]]-TODAY(),"No ETA") -> 167 | AH61: =IF(AB61=100%,"Completed",IF(AB61=0%,"Yet to Start","In Progress")) -> Yet to Start | AI61: 6 Months | AJ61: Oct-2026 | AK61: These Projects have not been started yet, proceedings shall be done post eid | AL61: Not Live - Work to be initiated | AM61: NOT LIVE - RETAIN BUDGET | AS61: =VLOOKUP(Table8[[#This Row],[CEM Number]],'71 CEMs'!$E$5:$E$76,1,0) -> #N/A | AT61: 46296
A62: INT-23-00439 | B62: 44924 | C62: Multan | D62: Multan Misc. Areas | E62: Al Khalil Housing Scheme | F62: 140 | G62: 70 | L62: On hold | M62: =Table8[[#This Row],[Std Remarks]] -> LIVE - 100% Completed | N62: =Table8[[#This Row],[% of Completion of Work Done]] -> 1 | O62: =Table8[[#This Row],[Customers According to % (Market Share)]] -> 70 | P62: 2080552.8 | Q62: =Table8[[#This Row],[Allocated Budget]]*Table8[[#This Row],[Allocation Percentage]] -> 312082.91 | R62: 1768469.8 | S62: 0 | U62: 0.5 | V62: 408.25 | W62: 2460.65 | X62: Hybrid | Y62: =$Q$2 -> 0.15 | Z62: LIVE | AA62: Hybrid | AB62: 1 | AC62: =VALUE(SUBSTITUTE(AB62,"%","")) -> 1 | AD62: 46082 | AE62: =IFERROR(Table8[[#This Row],[Timeline - Monthwise]]-MIN(Table8[Start Date..]),"None") -> None | AF62: =IFERROR(Table8[[#This Row],[Timeline - Monthwise]]-Table8[[#This Row],[Start Date..]]+1,"Duration Doesn't Exsists") -> Duration Doesn't Exsists | AG62: =IFERROR(Table8[[#This Row],[Timeline - Monthwise]]-TODAY(),"No ETA") -> No ETA | AH62: =IF(AB62=100%,"Completed",IF(AB62=0%,"Yet to Start","In Progress")) -> Completed | AJ62: Timeline not applicable | AL62: Live - As per Plan | AM62: LIVE - 100% Completed | AS62: =VLOOKUP(Table8[[#This Row],[CEM Number]],'71 CEMs'!$E$5:$E$76,1,0) -> INT-23-00439 | AT62: Timeline not applicable
A63: I240537 | B63: 45351 | C63: Abbottabad | D63: Abbottabad Ph2 | E63: Al Mansoor Town Ext. | F63: 440 | G63: 176 | H63: 15 | I63: 0 | M63: =Table8[[#This Row],[Std Remarks]] -> LIVE - 100% Completed | N63: =Table8[[#This Row],[% of Completion of Work Done]] -> 1 | O63: =Table8[[#This Row],[Customers According to % (Market Share)]] -> 176 | P63: 3932662 | Q63: =Table8[[#This Row],[Allocated Budget]]*Table8[[#This Row],[Allocation Percentage]] -> 589899.31 | R63: 3342762.7 | S63: -0.85 | U63: 0.4 | V63: 0 | W63: 6073.9018 | X63: Arial | Y63: =$Q$2 -> 0.15 | Z63: LIVE | AA63: Arial | AB63: 1 | AC63: =VALUE(SUBSTITUTE(AB63,"%","")) -> 1 | AD63: 46082 | AE63: =IFERROR(Table8[[#This Row],[Timeline - Monthwise]]-MIN(Table8[Start Date..]),"None") -> None | AF63: =IFERROR(Table8[[#This Row],[Timeline - Monthwise]]-Table8[[#This Row],[Start Date..]]+1,"Duration Doesn't Exsists") -> Duration Doesn't Exsists | AG63: =IFERROR(Table8[[#This Row],[Timeline - Monthwise]]-TODAY(),"No ETA") -> No ETA | AH63: =IF(AB63=100%,"Completed",IF(AB63=0%,"Yet to Start","In Progress")) -> Completed | AJ63: Timeline not applicable | AL63: Live - As per Plan | AM63: LIVE - 100% Completed | AS63: =VLOOKUP(Table8[[#This Row],[CEM Number]],'71 CEMs'!$E$5:$E$76,1,0) -> I240537 | AT63: Timeline not applicable
A64: INT-21-00315 | B64: 44195 | C64: Gujranwala | D64: Gujranwala Ph2 | E64: Al mansoorah colony | F64: 492 | G64: 196.8 | M64: =Table8[[#This Row],[Std Remarks]] -> LIVE - 100% Completed | N64: =Table8[[#This Row],[% of Completion of Work Done]] -> 1 | O64: =Table8[[#This Row],[Customers According to % (Market Share)]] -> 196.8 | P64: 6719191.8 | Q64: =Table8[[#This Row],[Allocated Budget]]*Table8[[#This Row],[Allocation Percentage]] -> 1007878.8 | R64: 5711313 | S64: -0.5 | U64: 0.4 | V64: 2142.8 | W64: 3517.2525 | X64: Buried | Y64: =$Q$2 -> 0.15 | Z64: LIVE | AA64: Buried | AB64: 1 | AC64: =VALUE(SUBSTITUTE(AB64,"%","")) -> 1 | AD64: 46082 | AE64: =IFERROR(Table8[[#This Row],[Timeline - Monthwise]]-MIN(Table8[Start Date..]),"None") -> None | AF64: =IFERROR(Table8[[#This Row],[Timeline - Monthwise]]-Table8[[#This Row],[Start Date..]]+1,"Duration Doesn't Exsists") -> Duration Doesn't Exsists | AG64: =IFERROR(Table8[[#This Row],[Timeline - Monthwise]]-TODAY(),"No ETA") -> No ETA | AH64: =IF(AB64=100%,"Completed",IF(AB64=0%,"Yet to Start","In Progress")) -> Completed | AJ64: Timeline not applicable | AL64: Live - As per Plan | AM64: LIVE - 100% Completed | AS64: =VLOOKUP(Table8[[#This Row],[CEM Number]],'71 CEMs'!$E$5:$E$76,1,0) -> INT-21-00315 | AT64: Timeline not applicable
A65: I240704 | B65: 45427 | C65: Multan | D65: Multan Ph3 | E65: Al Nawab Rehman Villas AlKareem | F65: 1470 | G65: 588 | H65: 41 | I65: 2 | J65: 8 | K65: 31 | M65: =Table8[[#This Row],[Std Remarks]] -> LIVE - 100% Completed | N65: =Table8[[#This Row],[% of Completion of Work Done]] -> 1 | O65: =Table8[[#This Row],[Customers According to % (Market Share)]] -> 588 | P65: 13947729 | Q65: =Table8[[#This Row],[Allocated Budget]]*Table8[[#This Row],[Allocation Percentage]] -> 2092159.3 | R65: 11855569 | S65: -1 | U65: 0.4 | V65: 2288.5 | W65: 12414.894 | X65: Hybrid | Y65: =$Q$2 -> 0.15 | Z65: LIVE | AA65: Hybrid | AB65: 1 | AC65: =VALUE(SUBSTITUTE(AB65,"%","")) -> 1 | AD65: 46082 | AE65: =IFERROR(Table8[[#This Row],[Timeline - Monthwise]]-MIN(Table8[Start Date..]),"None") -> None | AF65: =IFERROR(Table8[[#This Row],[Timeline - Monthwise]]-Table8[[#This Row],[Start Date..]]+1,"Duration Doesn't Exsists") -> Duration Doesn't Exsists | AG65: =IFERROR(Table8[[#This Row],[Timeline - Monthwise]]-TODAY(),"No ETA") -> No ETA | AH65: =IF(AB65=100%,"Completed",IF(AB65=0%,"Yet to Start","In Progress")) -> Completed | AJ65: Timeline not applicable | AL65: Live - As per Plan | AM65: LIVE - 100% Completed | AS65: =VLOOKUP(Table8[[#This Row],[CEM Number]],'71 CEMs'!$E$5:$E$76,1,0) -> I240704 | AT65: Timeline not applicable
A66: I260105 | B66: No Initiation Date | C66: Lahore | D66: Al Hafeez Garden & Tariq Garden | E66: Al Raheem Gdn Ph-2 Extn. | F66: 1150 | G66: 460 | M66: =Table8[[#This Row],[Std Remarks]] -> NOT LIVE - RETAIN BUDGET | N66: =Table8[[#This Row],[% of Completion of Work Done]] -> 0 | P66: 22652076 | Q66: =(Table8[[#This Row],[Allocated Budget]]*$Q$2)+(Table8[[#This Row],[Allocated Budget]]*(1-Table8[[#This Row],[HP% based on Live % ( Work Progress)]])*(1-$Q$2)) -> 22652076 | V66: 11108.95 | W66: 9658.75 | X66: Buried | Y66: =Table8[[#This Row],[% of Completion of Work Done]] -> 0 | Z66: Not Live | AB66: 0 | AC66: =VALUE(SUBSTITUTE(AB66,"%","")) -> 0 | AD66: 46082 | AE66: =IFERROR(Table8[[#This Row],[Timeline - Monthwise]]-MIN(Table8[Start Date..]),"None") -> 214 | AF66: =IFERROR(Table8[[#This Row],[Timeline - Monthwise]]-Table8[[#This Row],[Start Date..]]+1,"Duration Doesn't Exsists") -> 215 | AG66: =IFERROR(Table8[[#This Row],[Timeline - Monthwise]]-TODAY(),"No ETA") -> 167 | AH66: =IF(AB66=100%,"Completed",IF(AB66=0%,"Yet to Start","In Progress")) -> Yet to Start | AI66: 6 Months | AJ66: Oct-2026 | AK66: To be started soon | AL66: Not Live - Work to be initiated | AM66: NOT LIVE - RETAIN BUDGET | AS66: =VLOOKUP(Table8[[#This Row],[CEM Number]],'71 CEMs'!$E$5:$E$76,1,0) -> #N/A | AT66: 46296
A67: I240705 | B67: 45427 | C67: Karachi | D67: Karachi Ph5 | E67: Al Rahim City Ph-1 | F67: 488 | G67: 195.2 | M67: =Table8[[#This Row],[Std Remarks]] -> LIVE - 100% Completed | N67: =Table8[[#This Row],[% of Completion of Work Done]] -> 1 | O67: =Table8[[#This Row],[Customers According to % (Market Share)]] -> 195.2 | P67: 7250852.8 | Q67: =Table8[[#This Row],[Allocated Budget]]*Table8[[#This Row],[Allocation Percentage]] -> 1087627.9 | R67: 6163224.9 | S67: -0.765 | U67: 0.4 | V67: 1076.1328 | W67: 3028.925 | X67: Hybrid | Y67: =$Q$2 -> 0.15 | Z67: LIVE | AA67: Hybrid | AB67: 1 | AC67: =VALUE(SUBSTITUTE(AB67,"%","")) -> 1 | AD67: 46082 | AE67: =IFERROR(Table8[[#This Row],[Timeline - Monthwise]]-MIN(Table8[Start Date..]),"None") -> None | AF67: =IFERROR(Table8[[#This Row],[Timeline - Monthwise]]-Table8[[#This Row],[Start Date..]]+1,"Duration Doesn't Exsists") -> Duration Doesn't Exsists | AG67: =IFERROR(Table8[[#This Row],[Timeline - Monthwise]]-TODAY(),"No ETA") -> No ETA | AH67: =IF(AB67=100%,"Completed",IF(AB67=0%,"Yet to Start","In Progress")) -> Completed | AJ67: Timeline not applicable | AL67: Live - As per Plan | AM67: LIVE - 100% Completed | AS67: =VLOOKUP(Table8[[#This Row],[CEM Number]],'71 CEMs'!$E$5:$E$76,1,0) -> I240705 | AT67: Timeline not applicable
A68: I240705 | B68: 45427 | C68: Karachi | D68: Karachi Ph5 | E68: Al Rahim City Ph-2 | F68: 480 | G68: 192 | M68: =Table8[[#This Row],[Std Remarks]] -> LIVE - 100% Completed | N68: =Table8[[#This Row],[% of Completion of Work Done]] -> 1 | O68: =Table8[[#This Row],[Customers According to % (Market Share)]] -> 192 | P68: 8776314.1 | Q68: =Table8[[#This Row],[Allocated Budget]]*Table8[[#This Row],[Allocation Percentage]] -> 1316447.1 | R68: 7459867 | S68: -1 | U68: 0.4 | V68: 1365.2114 | W68: 3028.925 | X68: Hybrid | Y68: =$Q$2 -> 0.15 | Z68: LIVE | AA68: Hybrid | AB68: 1 | AC68: =VALUE(SUBSTITUTE(AB68,"%","")) -> 1 | AD68: 46082 | AE68: =IFERROR(Table8[[#This Row],[Timeline - Monthwise]]-MIN(Table8[Start Date..]),"None") -> None | AF68: =IFERROR(Table8[[#This Row],[Timeline - Monthwise]]-Table8[[#This Row],[Start Date..]]+1,"Duration Doesn't Exsists") -> Duration Doesn't Exsists | AG68: =IFERROR(Table8[[#This Row],[Timeline - Monthwise]]-TODAY(),"No ETA") -> No ETA | AH68: =IF(AB68=100%,"Completed",IF(AB68=0%,"Yet to Start","In Progress")) -> Completed | AJ68: Timeline not applicable | AL68: Live - As per Plan | AM68: LIVE - 100% Completed | AS68: =VLOOKUP(Table8[[#This Row],[CEM Number]],'71 CEMs'!$E$5:$E$76,1,0) -> I240705 | AT68: Timeline not applicable
A69: I260599 | B69: No Initiation Date | C69: Dera Ghazi Khan | D69: DG Khan | E69: Khayaban i Abid | F69: 242 | G69: 108.9 | M69: =Table8[[#This Row],[Std Remarks]] -> NOT LIVE - RETAIN BUDGET | N69: =Table8[[#This Row],[% of Completion of Work Done]] -> 0 | O69: =Table8[[#This Row],[Customers According to % (Market Share)]] -> 108.9 | P69: 6512643.5 | Q69: =(Table8[[#This Row],[Allocated Budget]]*$Q$2)+(Table8[[#This Row],[Allocated Budget]]*(1-Table8[[#This Row],[HP% based on Live % ( Work Progress)]])*(1-$Q$2)) -> 6512643.5 | U69: 0.45 | V69: 3217.0834 | W69: 3051 | X69: Hybrid | Y69: =Table8[[#This Row],[% of Completion of Work Done]] -> 0 | Z69: NOT LIVE | AB69: 0 | AC69: =VALUE(SUBSTITUTE(AB69,"%","")) -> 0 | AD69: 46082 | AE69: =IFERROR(Table8[[#This Row],[Timeline - Monthwise]]-MIN(Table8[Start Date..]),"None") -> 214 | AF69: =IFERROR(Table8[[#This Row],[Timeline - Monthwise]]-Table8[[#This Row],[Start Date..]]+1,"Duration Doesn't Exsists") -> 215 | AG69: =IFERROR(Table8[[#This Row],[Timeline - Monthwise]]-TODAY(),"No ETA") -> 167 | AH69: =IF(AB69=100%,"Completed",IF(AB69=0%,"Yet to Start","In Progress")) -> Yet to Start | AI69: 6 Months | AJ69: Oct-2026 | AK69: These Projects have not been started yet, proceedings shall be done post eid | AL69: Not Live - Work to be initiated | AM69: NOT LIVE - RETAIN BUDGET | AS69: =VLOOKUP(Table8[[#This Row],[CEM Number]],'71 CEMs'!$E$5:$E$76,1,0) -> #N/A | AT69: 46296
A70: I260160 | B70: No Initiation Date | C70: Lahore | D70: Khyban-e-Amin, High court & Al Rehman PH4 | E70: Al Rehman Garden 4 | F70: 978 | G70: 391.2 | M70: =Table8[[#This Row],[Std Remarks]] -> NOT LIVE - RETAIN BUDGET | N70: =Table8[[#This Row],[% of Completion of Work Done]] -> 0.9 | P70: 21170252 | Q70: =(Table8[[#This Row],[Allocated Budget]]*$Q$2)+(Table8[[#This Row],[Allocated Budget]]*(1-Table8[[#This Row],[HP% based on Live % ( Work Progress)]])*(1-$Q$2)) -> 4975009.1 | V70: 10028 | W70: 7602.6683 | X70: Buried | Y70: =Table8[[#This Row],[% of Completion of Work Done]] -> 0.9 | Z70: Not Live | AB70: 0.9 | AC70: =VALUE(SUBSTITUTE(AB70,"%","")) -> 0.9 | AD70: 46082 | AE70: =IFERROR(Table8[[#This Row],[Timeline - Monthwise]]-MIN(Table8[Start Date..]),"None") -> 61 | AF70: =IFERROR(Table8[[#This Row],[Timeline - Monthwise]]-Table8[[#This Row],[Start Date..]]+1,"Duration Doesn't Exsists") -> 62 | AG70: =IFERROR(Table8[[#This Row],[Timeline - Monthwise]]-TODAY(),"No ETA") -> 14 | AH70: =IF(AB70=100%,"Completed",IF(AB70=0%,"Yet to Start","In Progress")) -> In Progress | AI70: 2 months | AJ70: May-2026 | AK70: Civil Work in Progress | AL70: Not Live - Work in Progress (WIP) | AM70: NOT LIVE - RETAIN BUDGET | AS70: =VLOOKUP(Table8[[#This Row],[CEM Number]],'71 CEMs'!$E$5:$E$76,1,0) -> #N/A | AT70: 46143
A71: I240682 | B71: 45428 | C71: Faisalabad | D71: Faisalabad Ph4 | E71: Al Rehmat Villa | F71: 228 | G71: 91.2 | I71: 6 | J71: 14 | K71: 41 | L71: Occupancy: 100 | M71: =Table8[[#This Row],[Std Remarks]] -> LIVE - 100% Completed | N71: =Table8[[#This Row],[% of Completion of Work Done]] -> 1 | O71: =Table8[[#This Row],[Customers According to % (Market Share)]] -> 91.2 | P71: 3471646.7 | Q71: =Table8[[#This Row],[Allocated Budget]]*Table8[[#This Row],[Allocation Percentage]] -> 520747.01 | R71: 2950899.7 | S71: 0 | U71: 0.4 | V71: 671.6 | W71: 2087.45 | X71: Hybrid | Y71: =$Q$2 -> 0.15 | Z71: LIVE | AA71: Arial | AB71: 1 | AC71: =VALUE(SUBSTITUTE(AB71,"%","")) -> 1 | AD71: 46082 | AE71: =IFERROR(Table8[[#This Row],[Timeline - Monthwise]]-MIN(Table8[Start Date..]),"None") -> None | AF71: =IFERROR(Table8[[#This Row],[Timeline - Monthwise]]-Table8[[#This Row],[Start Date..]]+1,"Duration Doesn't Exsists") -> Duration Doesn't Exsists | AG71: =IFERROR(Table8[[#This Row],[Timeline - Monthwise]]-TODAY(),"No ETA") -> No ETA | AH71: =IF(AB71=100%,"Completed",IF(AB71=0%,"Yet to Start","In Progress")) -> Completed | AJ71: Timeline not applicable | AL71: Live - As per Plan | AM71: LIVE - 100% Completed | AS71: =VLOOKUP(Table8[[#This Row],[CEM Number]],'71 CEMs'!$E$5:$E$76,1,0) -> I240682 | AT71: Timeline not applicable
A72: I260295 | B72: No Initiation Date | C72: Karachi | D72: Model Town_Sh Faisal_Faisal Cant | E72: Alamgir&Jannat ul Barkat | F72: 1020 | G72: 408 | M72: =Table8[[#This Row],[Std Remarks]] -> NOT LIVE - RETAIN BUDGET | N72: =Table8[[#This Row],[% of Completion of Work Done]] -> 0 | P72: 7583418.9 | Q72: =(Table8[[#This Row],[Allocated Budget]]*$Q$2)+(Table8[[#This Row],[Allocated Budget]]*(1-Table8[[#This Row],[HP% based on Live % ( Work Progress)]])*(1-$Q$2)) -> 7583418.9 | V72: 1115.291 | W72: 9719.1381 | X72: Hybrid | Y72: =Table8[[#This Row],[% of Completion of Work Done]] -> 0 | Z72: NOT LIVE | AB72: 0 | AC72: =VALUE(SUBSTITUTE(AB72,"%","")) -> 0 | AD72: 46082 | AE72: =IFERROR(Table8[[#This Row],[Timeline - Monthwise]]-MIN(Table8[Start Date..]),"None") -> 214 | AF72: =IFERROR(Table8[[#This Row],[Timeline - Monthwise]]-Table8[[#This Row],[Start Date..]]+1,"Duration Doesn't Exsists") -> 215 | AG72: =IFERROR(Table8[[#This Row],[Timeline - Monthwise]]-TODAY(),"No ETA") -> 167 | AH72: =IF(AB72=100%,"Completed",IF(AB72=0%,"Yet to Start","In Progress")) -> Yet to Start | AI72: 6 months | AJ72: Oct-2026 | AK72: Not started yet, permission issue | AL72: Not Live - Work to be initiated | AM72: NOT LIVE - RETAIN BUDGET | AS72: =VLOOKUP(Table8[[#This Row],[CEM Number]],'71 CEMs'!$E$5:$E$76,1,0) -> #N/A | AT72: 46296
A73: I260295 | B73: No Initiation Date | C73: Karachi | D73: Model Town_Sh Faisal_Faisal Cant | E73: Alfalah Society | F73: 1330 | G73: 532 | M73: =Table8[[#This Row],[Std Remarks]] -> NOT LIVE - RETAIN BUDGET | N73: =Table8[[#This Row],[% of Completion of Work Done]] -> 0 | P73: 9706625.9 | Q73: =(Table8[[#This Row],[Allocated Budget]]*$Q$2)+(Table8[[#This Row],[Allocated Budget]]*(1-Table8[[#This Row],[HP% based on Live % ( Work Progress)]])*(1-$Q$2)) -> 9706625.9 | V73: 1495.12 | W73: 7634.7687 | X73: Hybrid | Y73: =Table8[[#This Row],[% of Completion of Work Done]] -> 0 | Z73: NOT LIVE | AB73: 0 | AC73: =VALUE(SUBSTITUTE(AB73,"%","")) -> 0 | AD73: 46082 | AE73: =IFERROR(Table8[[#This Row],[Timeline - Monthwise]]-MIN(Table8[Start Date..]),"None") -> 214 | AF73: =IFERROR(Table8[[#This Row],[Timeline - Monthwise]]-Table8[[#This Row],[Start Date..]]+1,"Duration Doesn't Exsists") -> 215 | AG73: =IFERROR(Table8[[#This Row],[Timeline - Monthwise]]-TODAY(),"No ETA") -> 167 | AH73: =IF(AB73=100%,"Completed",IF(AB73=0%,"Yet to Start","In Progress")) -> Yet to Start | AI73: 6 months | AJ73: Oct-2026 | AK73: Not started yet, permission issue | AL73: Not Live - Work to be initiated | AM73: NOT LIVE - RETAIN BUDGET | AS73: =VLOOKUP(Table8[[#This Row],[CEM Number]],'71 CEMs'!$E$5:$E$76,1,0) -> #N/A | AT73: 46296
A74: INT-23-00437 | B74: 44924 | C74: Lahore | D74: Lahore Misc Areas | E74: Al-Hamd Society | F74: 264 | G74: 132 | M74: =Table8[[#This Row],[Std Remarks]] -> LIVE - 100% Completed | N74: =Table8[[#This Row],[% of Completion of Work Done]] -> 1 | O74: =Table8[[#This Row],[Customers According to % (Market Share)]] -> 132 | P74: 2532898.1 | Q74: =Table8[[#This Row],[Allocated Budget]]*Table8[[#This Row],[Allocation Percentage]] -> 379934.71 | R74: 2152963.3 | S74: 0 | U74: 0.5 | V74: 487.8524 | W74: 1459.4008 | X74: Hybrid | Y74: =$Q$2 -> 0.15 | Z74: LIVE | AA74: Hybrid | AB74: 1 | AC74: =VALUE(SUBSTITUTE(AB74,"%","")) -> 1 | AD74: 46082 | AE74: =IFERROR(Table8[[#This Row],[Timeline - Monthwise]]-MIN(Table8[Start Date..]),"None") -> None | AF74: =IFERROR(Table8[[#This Row],[Timeline - Monthwise]]-Table8[[#This Row],[Start Date..]]+1,"Duration Doesn't Exsists") -> Duration Doesn't Exsists | AG74: =IFERROR(Table8[[#This Row],[Timeline - Monthwise]]-TODAY(),"No ETA") -> No ETA | AH74: =IF(AB74=100%,"Completed",IF(AB74=0%,"Yet to Start","In Progress")) -> Completed | AJ74: Timeline not applicable | AL74: Live - As per Plan | AM74: LIVE - 100% Completed | AS74: =VLOOKUP(Table8[[#This Row],[CEM Number]],'71 CEMs'!$E$5:$E$76,1,0) -> INT-23-00437 | AT74: Timeline not applicable
A75: I260599 | B75: No Initiation Date | C75: Dera Ghazi Khan | D75: DG Khan | E75: Main Area P1 | F75: 3176 | G75: 1429.2 | M75: =Table8[[#This Row],[Std Remarks]] -> NOT LIVE - RETAIN BUDGET | N75: =Table8[[#This Row],[% of Completion of Work Done]] -> 0 | O75: =Table8[[#This Row],[Customers According to % (Market Share)]] -> 1429.2 | P75: 34606678 | Q75: =(Table8[[#This Row],[Allocated Budget]]*$Q$2)+(Table8[[#This Row],[Allocated Budget]]*(1-Table8[[#This Row],[HP% based on Live % ( Work Progress)]])*(1-$Q$2)) -> 34606678 | U75: 0.45 | V75: 7104 | W75: 31407.01 | X75: Hybrid | Y75: =Table8[[#This Row],[% of Completion of Work Done]] -> 0 | Z75: NOT LIVE | AB75: 0 | AC75: =VALUE(SUBSTITUTE(AB75,"%","")) -> 0 | AD75: 46082 | AE75: =IFERROR(Table8[[#This Row],[Timeline - Monthwise]]-MIN(Table8[Start Date..]),"None") -> 214 | AF75: =IFERROR(Table8[[#This Row],[Timeline - Monthwise]]-Table8[[#This Row],[Start Date..]]+1,"Duration Doesn't Exsists") -> 215 | AG75: =IFERROR(Table8[[#This Row],[Timeline - Monthwise]]-TODAY(),"No ETA") -> 167 | AH75: =IF(AB75=100%,"Completed",IF(AB75=0%,"Yet to Start","In Progress")) -> Yet to Start | AI75: 6 Months | AJ75: Oct-2026 | AK75: These Projects have not been started yet, proceedings shall be done post eid | AL75: Not Live - Work to be initiated | AM75: NOT LIVE - RETAIN BUDGET | AS75: =VLOOKUP(Table8[[#This Row],[CEM Number]],'71 CEMs'!$E$5:$E$76,1,0) -> #N/A | AT75: 46296
A76: I240680 | B76: 45428 | C76: Rahim Yar Khan | D76: RahimYar Khan Ph2 | E76: ALi + Fort + Madina | F76: 312 | G76: 124.8 | H76: 23 | I76: 6 | M76: =Table8[[#This Row],[Std Remarks]] -> LIVE - 100% Completed | N76: =Table8[[#This Row],[% of Completion of Work Done]] -> 1 | O76: =Table8[[#This Row],[Customers According to % (Market Share)]] -> 124.8 | P76: 6278514.5 | Q76: =Table8[[#This Row],[Allocated Budget]]*Table8[[#This Row],[Allocation Percentage]] -> 941777.17 | R76: 5336737.3 | S76: -1 | U76: 0.4 | V76: 1569.75 | W76: 3452.5 | X76: Hybrid | Y76: =$Q$2 -> 0.15 | Z76: LIVE | AA76: Hybrid | AB76: 1 | AC76: =VALUE(SUBSTITUTE(AB76,"%","")) -> 1 | AD76: 46082 | AE76: =IFERROR(Table8[[#This Row],[Timeline - Monthwise]]-MIN(Table8[Start Date..]),"None") -> None | AF76: =IFERROR(Table8[[#This Row],[Timeline - Monthwise]]-Table8[[#This Row],[Start Date..]]+1,"Duration Doesn't Exsists") -> Duration Doesn't Exsists | AG76: =IFERROR(Table8[[#This Row],[Timeline - Monthwise]]-TODAY(),"No ETA") -> No ETA | AH76: =IF(AB76=100%,"Completed",IF(AB76=0%,"Yet to Start","In Progress")) -> Completed | AJ76: Timeline not applicable | AL76: Live - As per Plan | AM76: LIVE - 100% Completed | AS76: =VLOOKUP(Table8[[#This Row],[CEM Number]],'71 CEMs'!$E$5:$E$76,1,0) -> I240680 | AT76: Timeline not applicable
A77: I260599 | B77: No Initiation Date | C77: Dera Ghazi Khan | D77: DG Khan | E77: Main Area P2 | F77: 3656 | G77: 1645.2 | M77: =Table8[[#This Row],[Std Remarks]] -> NOT LIVE - RETAIN BUDGET | N77: =Table8[[#This Row],[% of Completion of Work Done]] -> 0 | O77: =Table8[[#This Row],[Customers According to % (Market Share)]] -> 1645.2 | P77: 23123139 | Q77: =(Table8[[#This Row],[Allocated Budget]]*$Q$2)+(Table8[[#This Row],[Allocated Budget]]*(1-Table8[[#This Row],[HP% based on Live % ( Work Progress)]])*(1-$Q$2)) -> 23123139 | U77: 0.45 | V77: 2232 | W77: 34874.219 | X77: Hybrid | Y77: =Table8[[#This Row],[% of Completion of Work Done]] -> 0 | Z77: NOT LIVE | AB77: 0 | AC77: =VALUE(SUBSTITUTE(AB77,"%","")) -> 0 | AD77: 46082 | AE77: =IFERROR(Table8[[#This Row],[Timeline - Monthwise]]-MIN(Table8[Start Date..]),"None") -> 214 | AF77: =IFERROR(Table8[[#This Row],[Timeline - Monthwise]]-Table8[[#This Row],[Start Date..]]+1,"Duration Doesn't Exsists") -> 215 | AG77: =IFERROR(Table8[[#This Row],[Timeline - Monthwise]]-TODAY(),"No ETA") -> 167 | AH77: =IF(AB77=100%,"Completed",IF(AB77=0%,"Yet to Start","In Progress")) -> Yet to Start | AI77: 6 Months | AJ77: Oct-2026 | AK77: These Projects have not been started yet, proceedings shall be done post eid | AL77: Not Live - Work to be initiated | AM77: NOT LIVE - RETAIN BUDGET | AS77: =VLOOKUP(Table8[[#This Row],[CEM Number]],'71 CEMs'!$E$5:$E$76,1,0) -> #N/A | AT77: 46296
A78: I250681 | B78: 45742 | C78: Lahore | D78: CTC Lahore | E78: Ali Park & Nadirabad P1 | F78: 1424 | G78: =0.4*F78 -> 569.6 | M78: =Table8[[#This Row],[Std Remarks]] -> NOT LIVE - RETAIN BUDGET | N78: =Table8[[#This Row],[% of Completion of Work Done]] -> 0.9 | O78: =Table8[[#This Row],[Customers According to % (Market Share)]] -> 569.6 | P78: 9547055 | Q78: =(Table8[[#This Row],[Allocated Budget]]*$Q$2)+(Table8[[#This Row],[Allocated Budget]]*(1-Table8[[#This Row],[HP% based on Live % ( Work Progress)]])*(1-$Q$2)) -> 2243557.9 | R78: 7303497.1 | S78: -1 | V78: 2700.41 | W78: 11590.97 | X78: Hybrid | Y78: =Table8[[#This Row],[% of Completion of Work Done]] -> 0.9 | Z78: NOT LIVE | AB78: 0.9 | AC78: =VALUE(SUBSTITUTE(AB78,"%","")) -> 0.9 | AD78: 46082 | AE78: =IFERROR(Table8[[#This Row],[Timeline - Monthwise]]-MIN(Table8[Start Date..]),"None") -> 0 | AF78: =IFERROR(Table8[[#This Row],[Timeline - Monthwise]]-Table8[[#This Row],[Start Date..]]+1,"Duration Doesn't Exsists") -> 1 | AG78: =IFERROR(Table8[[#This Row],[Timeline - Monthwise]]-TODAY(),"No ETA") -> -47 | AH78: =IF(AB78=100%,"Completed",IF(AB78=0%,"Yet to Start","In Progress")) -> In Progress | AI78: 46054 | AJ78: Mar-2026 | AK78: Cable and ADT Plan Shared | AL78: Not Live - Work in Progress (WIP) | AM78: NOT LIVE - RETAIN BUDGET | AN78: 1 | AS78: =VLOOKUP(Table8[[#This Row],[CEM Number]],'71 CEMs'!$E$5:$E$76,1,0) -> I250681 | AT78: 46082
A79: I250681 | B79: 45742 | C79: Lahore | D79: CTC Lahore | E79: Ali Park & Nadirabad P2 | F79: 1512 | G79: =F79*0.4 -> 604.8 | M79: =Table8[[#This Row],[Std Remarks]] -> NOT LIVE - RETAIN BUDGET | N79: =Table8[[#This Row],[% of Completion of Work Done]] -> 0.7 | O79: =Table8[[#This Row],[Customers According to % (Market Share)]] -> 604.8 | P79: 9890121.3 | Q79: =(Table8[[#This Row],[Allocated Budget]]*$Q$2)+(Table8[[#This Row],[Allocated Budget]]*(1-Table8[[#This Row],[HP% based on Live % ( Work Progress)]])*(1-$Q$2)) -> 4005499.1 | R79: 5884622.2 | S79: -0.85 | V79: 3207 | W79: 11713.082 | X79: Hybrid | Y79: =Table8[[#This Row],[% of Completion of Work Done]] -> 0.7 | Z79: NOT LIVE | AB79: 0.7 | AC79: =VALUE(SUBSTITUTE(AB79,"%","")) -> 0.7 | AD79: 46082 | AE79: =IFERROR(Table8[[#This Row],[Timeline - Monthwise]]-MIN(Table8[Start Date..]),"None") -> 0 | AF79: =IFERROR(Table8[[#This Row],[Timeline - Monthwise]]-Table8[[#This Row],[Start Date..]]+1,"Duration Doesn't Exsists") -> 1 | AG79: =IFERROR(Table8[[#This Row],[Timeline - Monthwise]]-TODAY(),"No ETA") -> -47 | AH79: =IF(AB79=100%,"Completed",IF(AB79=0%,"Yet to Start","In Progress")) -> In Progress | AI79: 46082 | AJ79: Mar-2026 | AK79: Civil Work Completion | AL79: Not Live - Work in Progress (WIP) | AM79: NOT LIVE - RETAIN BUDGET | AN79: 1 | AO79: 1 | AS79: =VLOOKUP(Table8[[#This Row],[CEM Number]],'71 CEMs'!$E$5:$E$76,1,0) -> I250681 | AT79: 46082
A80: I260599 | B80: No Initiation Date | C80: Dera Ghazi Khan | D80: DG Khan | E80: Main Area P3 | F80: 1776 | G80: 799.2 | M80: =Table8[[#This Row],[Std Remarks]] -> NOT LIVE - RETAIN BUDGET | N80: =Table8[[#This Row],[% of Completion of Work Done]] -> 0 | O80: =Table8[[#This Row],[Customers According to % (Market Share)]] -> 799.2 | P80: 21710706 | Q80: =(Table8[[#This Row],[Allocated Budget]]*$Q$2)+(Table8[[#This Row],[Allocated Budget]]*(1-Table8[[#This Row],[HP% based on Live % ( Work Progress)]])*(1-$Q$2)) -> 21710706 | U80: 0.45 | V80: 4438 | W80: 21449.525 | X80: Hybrid | Y80: =Table8[[#This Row],[% of Completion of Work Done]] -> 0 | Z80: NOT LIVE | AB80: 0 | AC80: =VALUE(SUBSTITUTE(AB80,"%","")) -> 0 | AD80: 46082 | AE80: =IFERROR(Table8[[#This Row],[Timeline - Monthwise]]-MIN(Table8[Start Date..]),"None") -> 214 | AF80: =IFERROR(Table8[[#This Row],[Timeline - Monthwise]]-Table8[[#This Row],[Start Date..]]+1,"Duration Doesn't Exsists") -> 215 | AG80: =IFERROR(Table8[[#This Row],[Timeline - Monthwise]]-TODAY(),"No ETA") -> 167 | AH80: =IF(AB80=100%,"Completed",IF(AB80=0%,"Yet to Start","In Progress")) -> Yet to Start | AI80: 6 Months | AJ80: Oct-2026 | AK80: These Projects have not been started yet, proceedings shall be done post eid | AL80: Not Live - Work to be initiated | AM80: NOT LIVE - RETAIN BUDGET | AS80: =VLOOKUP(Table8[[#This Row],[CEM Number]],'71 CEMs'!$E$5:$E$76,1,0) -> #N/A | AT80: 46296
A81: I260599 | B81: No Initiation Date | C81: Dera Ghazi Khan | D81: DG Khan | E81: Model Town | F81: 1012 | G81: 455.4 | M81: =Table8[[#This Row],[Std Remarks]] -> NOT LIVE - RETAIN BUDGET | N81: =Table8[[#This Row],[% of Completion of Work Done]] -> 0 | O81: =Table8[[#This Row],[Customers According to % (Market Share)]] -> 455.4 | P81: 13749012 | Q81: =(Table8[[#This Row],[Allocated Budget]]*$Q$2)+(Table8[[#This Row],[Allocated Budget]]*(1-Table8[[#This Row],[HP% based on Live % ( Work Progress)]])*(1-$Q$2)) -> 13749012 | U81: 0.45 | V81: 3082.2647 | W81: 12538.131 | X81: Hybrid | Y81: =Table8[[#This Row],[% of Completion of Work Done]] -> 0 | Z81: NOT LIVE | AB81: 0 | AC81: =VALUE(SUBSTITUTE(AB81,"%","")) -> 0 | AD81: 46082 | AE81: =IFERROR(Table8[[#This Row],[Timeline - Monthwise]]-MIN(Table8[Start Date..]),"None") -> 214 | AF81: =IFERROR(Table8[[#This Row],[Timeline - Monthwise]]-Table8[[#This Row],[Start Date..]]+1,"Duration Doesn't Exsists") -> 215 | AG81: =IFERROR(Table8[[#This Row],[Timeline - Monthwise]]-TODAY(),"No ETA") -> 167 | AH81: =IF(AB81=100%,"Completed",IF(AB81=0%,"Yet to Start","In Progress")) -> Yet to Start | AI81: 6 Months | AJ81: Oct-2026 | AK81: These Projects have not been started yet, proceedings shall be done post eid | AL81: Not Live - Work to be initiated | AM81: NOT LIVE - RETAIN BUDGET | AS81: =VLOOKUP(Table8[[#This Row],[CEM Number]],'71 CEMs'!$E$5:$E$76,1,0) -> #N/A | AT81: 46296
A82: I240704 | B82: 45427 | C82: Multan | D82: Multan Ph3 | E82: Ali Town | F82: 1486 | G82: 594.4 | H82: 144 | I82: 15 | J82: 25 | K82: 104 | M82: =Table8[[#This Row],[Std Remarks]] -> LIVE - 100% Completed | N82: =Table8[[#This Row],[% of Completion of Work Done]] -> 1 | O82: =Table8[[#This Row],[Customers According to % (Market Share)]] -> 594.4 | P82: 15226493 | Q82: =Table8[[#This Row],[Allocated Budget]]*Table8[[#This Row],[Allocation Percentage]] -> 2283973.9 | R82: 12942519 | S82: -1 | U82: 0.4 | V82: 1975.05 | W82: 10888.05 | X82: Hybrid | Y82: =$Q$2 -> 0.15 | Z82: LIVE | AA82: Hybrid | AB82: 1 | AC82: =VALUE(SUBSTITUTE(AB82,"%","")) -> 1 | AD82: 46082 | AE82: =IFERROR(Table8[[#This Row],[Timeline - Monthwise]]-MIN(Table8[Start Date..]),"None") -> None | AF82: =IFERROR(Table8[[#This Row],[Timeline - Monthwise]]-Table8[[#This Row],[Start Date..]]+1,"Duration Doesn't Exsists") -> Duration Doesn't Exsists | AG82: =IFERROR(Table8[[#This Row],[Timeline - Monthwise]]-TODAY(),"No ETA") -> No ETA | AH82: =IF(AB82=100%,"Completed",IF(AB82=0%,"Yet to Start","In Progress")) -> Completed | AJ82: Timeline not applicable | AL82: Live - As per Plan | AM82: LIVE - 100% Completed | AS82: =VLOOKUP(Table8[[#This Row],[CEM Number]],'71 CEMs'!$E$5:$E$76,1,0) -> I240704 | AT82: Timeline not applicable
A83: I250734 | B83: No Initiation Date | C83: Bahawalpur | D83: Bahwalpur (P2)-B | E83: Alibad_Colony | F83: 278 | G83: 111.2 | K83: 20 | M83: =Table8[[#This Row],[Std Remarks]] -> LIVE - 100% Completed | N83: =Table8[[#This Row],[% of Completion of Work Done]] -> 1 | O83: =Table8[[#This Row],[Customers According to % (Market Share)]] -> 111.2 | P83: 2159567.6 | Q83: =Table8[[#This Row],[Allocated Budget]]*Table8[[#This Row],[Allocation Percentage]] -> 323935.15 | V83: 286.35 | W83: 2148.6131 | X83: Arial | Y83: =$Q$2 -> 0.15 | Z83: LIVE | AA83: Arial | AB83: 1 | AC83: =VALUE(SUBSTITUTE(AB83,"%","")) -> 1 | AD83: 46082 | AE83: =IFERROR(Table8[[#This Row],[Timeline - Monthwise]]-MIN(Table8[Start Date..]),"None") -> None | AF83: =IFERROR(Table8[[#This Row],[Timeline - Monthwise]]-Table8[[#This Row],[Start Date..]]+1,"Duration Doesn't Exsists") -> Duration Doesn't Exsists | AG83: =IFERROR(Table8[[#This Row],[Timeline - Monthwise]]-TODAY(),"No ETA") -> No ETA | AH83: =IF(AB83=100%,"Completed",IF(AB83=0%,"Yet to Start","In Progress")) -> Completed | AJ83: Timeline not applicable | AL83: Live - As per Plan | AM83: LIVE - 100% Completed | AS83: =VLOOKUP(Table8[[#This Row],[CEM Number]],'71 CEMs'!$E$5:$E$76,1,0) -> #N/A | AT83: Timeline not applicable
A84: I260599 | B84: No Initiation Date | C84: Dera Ghazi Khan | D84: DG Khan | E84: New Defence | F84: 930 | G84: 418.5 | M84: =Table8[[#This Row],[Std Remarks]] -> NOT LIVE - RETAIN BUDGET | N84: =Table8[[#This Row],[% of Completion of Work Done]] -> 0 | O84: =Table8[[#This Row],[Customers According to % (Market Share)]] -> 418.5 | P84: 27241910 | Q84: =(Table8[[#This Row],[Allocated Budget]]*$Q$2)+(Table8[[#This Row],[Allocated Budget]]*(1-Table8[[#This Row],[HP% based on Live % ( Work Progress)]])*(1-$Q$2)) -> 27241910 | U84: 0.45 | V84: 14073.206 | W84: 11862.51 | X84: Hybrid | Y84: =Table8[[#This Row],[% of Completion of Work Done]] -> 0 | Z84: NOT LIVE | AB84: 0 | AC84: =VALUE(SUBSTITUTE(AB84,"%","")) -> 0 | AD84: 46082 | AE84: =IFERROR(Table8[[#This Row],[Timeline - Monthwise]]-MIN(Table8[Start Date..]),"None") -> 214 | AF84: =IFERROR(Table8[[#This Row],[Timeline - Monthwise]]-Table8[[#This Row],[Start Date..]]+1,"Duration Doesn't Exsists") -> 215 | AG84: =IFERROR(Table8[[#This Row],[Timeline - Monthwise]]-TODAY(),"No ETA") -> 167 | AH84: =IF(AB84=100%,"Completed",IF(AB84=0%,"Yet to Start","In Progress")) -> Yet to Start | AI84: 6 Months | AJ84: Oct-2026 | AK84: These Projects have not been started yet, proceedings shall be done post eid | AL84: Not Live - Work to be initiated | AM84: NOT LIVE - RETAIN BUDGET | AS84: =VLOOKUP(Table8[[#This Row],[CEM Number]],'71 CEMs'!$E$5:$E$76,1,0) -> #N/A | AT84: 46296
A85: I260599 | B85: No Initiation Date | C85: Dera Ghazi Khan | D85: DG Khan | E85: New Model Town | F85: 398 | G85: 179.1 | M85: =Table8[[#This Row],[Std Remarks]] -> NOT LIVE - RETAIN BUDGET | N85: =Table8[[#This Row],[% of Completion of Work Done]] -> 0 | O85: =Table8[[#This Row],[Customers According to % (Market Share)]] -> 179.1 | P85: 4776860.7 | Q85: =(Table8[[#This Row],[Allocated Budget]]*$Q$2)+(Table8[[#This Row],[Allocated Budget]]*(1-Table8[[#This Row],[HP% based on Live % ( Work Progress)]])*(1-$Q$2)) -> 4776860.7 | U85: 0.45 | V85: 894.355 | W85: 5500.1274 | X85: Hybrid | Y85: =Table8[[#This Row],[% of Completion of Work Done]] -> 0 | Z85: NOT LIVE | AB85: 0 | AC85: =VALUE(SUBSTITUTE(AB85,"%","")) -> 0 | AD85: 46082 | AE85: =IFERROR(Table8[[#This Row],[Timeline - Monthwise]]-MIN(Table8[Start Date..]),"None") -> 214 | AF85: =IFERROR(Table8[[#This Row],[Timeline - Monthwise]]-Table8[[#This Row],[Start Date..]]+1,"Duration Doesn't Exsists") -> 215 | AG85: =IFERROR(Table8[[#This Row],[Timeline - Monthwise]]-TODAY(),"No ETA") -> 167 | AH85: =IF(AB85=100%,"Completed",IF(AB85=0%,"Yet to Start","In Progress")) -> Yet to Start | AI85: 6 Months | AJ85: Oct-2026 | AK85: These Projects have not been started yet, proceedings shall be done post eid | AL85: Not Live - Work to be initiated | AM85: NOT LIVE - RETAIN BUDGET | AS85: =VLOOKUP(Table8[[#This Row],[CEM Number]],'71 CEMs'!$E$5:$E$76,1,0) -> #N/A | AT85: 46296
A86: I260599 | B86: No Initiation Date | C86: Dera Ghazi Khan | D86: DG Khan | E86: NMC Colony 1 | F86: 296 | G86: 133.2 | M86: =Table8[[#This Row],[Std Remarks]] -> NOT LIVE - RETAIN BUDGET | N86: =Table8[[#This Row],[% of Completion of Work Done]] -> 0 | O86: =Table8[[#This Row],[Customers According to % (Market Share)]] -> 133.2 | P86: 4506777.2 | Q86: =(Table8[[#This Row],[Allocated Budget]]*$Q$2)+(Table8[[#This Row],[Allocated Budget]]*(1-Table8[[#This Row],[HP% based on Live % ( Work Progress)]])*(1-$Q$2)) -> 4506777.2 | U86: 0.45 | V86: 1160.4 | W86: 4682.6666 | X86: Hybrid | Y86: =Table8[[#This Row],[% of Completion of Work Done]] -> 0 | Z86: NOT LIVE | AB86: 0 | AC86: =VALUE(SUBSTITUTE(AB86,"%","")) -> 0 | AD86: 46082 | AE86: =IFERROR(Table8[[#This Row],[Timeline - Monthwise]]-MIN(Table8[Start Date..]),"None") -> 214 | AF86: =IFERROR(Table8[[#This Row],[Timeline - Monthwise]]-Table8[[#This Row],[Start Date..]]+1,"Duration Doesn't Exsists") -> 215 | AG86: =IFERROR(Table8[[#This Row],[Timeline - Monthwise]]-TODAY(),"No ETA") -> 167 | AH86: =IF(AB86=100%,"Completed",IF(AB86=0%,"Yet to Start","In Progress")) -> Yet to Start | AI86: 6 Months | AJ86: Oct-2026 | AK86: These Projects have not been started yet, proceedings shall be done post eid | AL86: Not Live - Work to be initiated | AM86: NOT LIVE - RETAIN BUDGET | AS86: =VLOOKUP(Table8[[#This Row],[CEM Number]],'71 CEMs'!$E$5:$E$76,1,0) -> #N/A | AT86: 46296
A87: INT-23-00439 | B87: 44924 | C87: Multan | D87: Multan Misc. Areas | E87: Allabad, AliTown & IslamPura | F87: 1024 | G87: 512 | H87: 55 | I87: 3 | J87: 3 | K87: 49 | M87: =Table8[[#This Row],[Std Remarks]] -> LIVE - 100% Completed | N87: =Table8[[#This Row],[% of Completion of Work Done]] -> 1 | O87: =Table8[[#This Row],[Customers According to % (Market Share)]] -> 512 | P87: 10704522 | Q87: =Table8[[#This Row],[Allocated Budget]]*Table8[[#This Row],[Allocation Percentage]] -> 1605678.3 | R87: 9098843.5 | S87: -1 | U87: 0.5 | V87: 2779.55 | W87: 8165.33 | X87: Hybrid | Y87: =$Q$2 -> 0.15 | Z87: LIVE | AA87: Hybrid | AB87: 1 | AC87: =VALUE(SUBSTITUTE(AB87,"%","")) -> 1 | AD87: 46082 | AE87: =IFERROR(Table8[[#This Row],[Timeline - Monthwise]]-MIN(Table8[Start Date..]),"None") -> None | AF87: =IFERROR(Table8[[#This Row],[Timeline - Monthwise]]-Table8[[#This Row],[Start Date..]]+1,"Duration Doesn't Exsists") -> Duration Doesn't Exsists | AG87: =IFERROR(Table8[[#This Row],[Timeline - Monthwise]]-TODAY(),"No ETA") -> No ETA | AH87: =IF(AB87=100%,"Completed",IF(AB87=0%,"Yet to Start","In Progress")) -> Completed | AJ87: Timeline not applicable | AL87: Live - As per Plan | AM87: LIVE - 100% Completed | AS87: =VLOOKUP(Table8[[#This Row],[CEM Number]],'71 CEMs'!$E$5:$E$76,1,0) -> INT-23-00439 | AT87: Timeline not applicable
A88: I260599 | B88: No Initiation Date | C88: Dera Ghazi Khan | D88: DG Khan | E88: Part of New Defence | F88: 262 | G88: 117.9 | M88: =Table8[[#This Row],[Std Remarks]] -> NOT LIVE - RETAIN BUDGET | N88: =Table8[[#This Row],[% of Completion of Work Done]] -> 0 | O88: =Table8[[#This Row],[Customers According to % (Market Share)]] -> 117.9 | P88: 7649956.6 | Q88: =(Table8[[#This Row],[Allocated Budget]]*$Q$2)+(Table8[[#This Row],[Allocated Budget]]*(1-Table8[[#This Row],[HP% based on Live % ( Work Progress)]])*(1-$Q$2)) -> 7649956.6 | U88: 0.45 | V88: 3704.7405 | W88: 3480.9257 | X88: Hybrid | Y88: =Table8[[#This Row],[% of Completion of Work Done]] -> 0 | Z88: NOT LIVE | AB88: 0 | AC88: =VALUE(SUBSTITUTE(AB88,"%","")) -> 0 | AD88: 46082 | AE88: =IFERROR(Table8[[#This Row],[Timeline - Monthwise]]-MIN(Table8[Start Date..]),"None") -> 214 | AF88: =IFERROR(Table8[[#This Row],[Timeline - Monthwise]]-Table8[[#This Row],[Start Date..]]+1,"Duration Doesn't Exsists") -> 215 | AG88: =IFERROR(Table8[[#This Row],[Timeline - Monthwise]]-TODAY(),"No ETA") -> 167 | AH88: =IF(AB88=100%,"Completed",IF(AB88=0%,"Yet to Start","In Progress")) -> Yet to Start | AI88: 6 Months | AJ88: Oct-2026 | AK88: These Projects have not been started yet, proceedings shall be done post eid | AL88: Not Live - Work to be initiated | AM88: NOT LIVE - RETAIN BUDGET | AS88: =VLOOKUP(Table8[[#This Row],[CEM Number]],'71 CEMs'!$E$5:$E$76,1,0) -> #N/A | AT88: 46296
A89: I260599 | B89: No Initiation Date | C89: Dera Ghazi Khan | D89: DG Khan | E89: Railway Civil Lines P1 | F89: 596 | G89: 268.2 | M89: =Table8[[#This Row],[Std Remarks]] -> NOT LIVE - RETAIN BUDGET | N89: =Table8[[#This Row],[% of Completion of Work Done]] -> 0 | O89: =Table8[[#This Row],[Customers According to % (Market Share)]] -> 268.2 | P89: 12742348 | Q89: =(Table8[[#This Row],[Allocated Budget]]*$Q$2)+(Table8[[#This Row],[Allocated Budget]]*(1-Table8[[#This Row],[HP% based on Live % ( Work Progress)]])*(1-$Q$2)) -> 12742348 | U89: 0.45 | V89: 3247.6 | W89: 10985.017 | X89: Hybrid | Y89: =Table8[[#This Row],[% of Completion of Work Done]] -> 0 | Z89: NOT LIVE | AB89: 0 | AC89: =VALUE(SUBSTITUTE(AB89,"%","")) -> 0 | AD89: 46082 | AE89: =IFERROR(Table8[[#This Row],[Timeline - Monthwise]]-MIN(Table8[Start Date..]),"None") -> 214 | AF89: =IFERROR(Table8[[#This Row],[Timeline - Monthwise]]-Table8[[#This Row],[Start Date..]]+1,"Duration Doesn't Exsists") -> 215 | AG89: =IFERROR(Table8[[#This Row],[Timeline - Monthwise]]-TODAY(),"No ETA") -> 167 | AH89: =IF(AB89=100%,"Completed",IF(AB89=0%,"Yet to Start","In Progress")) -> Yet to Start | AI89: 6 Months | AJ89: Oct-2026 | AK89: These Projects have not been started yet, proceedings shall be done post eid | AL89: Not Live - Work to be initiated | AM89: NOT LIVE - RETAIN BUDGET | AS89: =VLOOKUP(Table8[[#This Row],[CEM Number]],'71 CEMs'!$E$5:$E$76,1,0) -> #N/A | AT89: 46296
A90: I250734 | B90: No Initiation Date | C90: Bahawalpur | D90: Bahwalpur (P2)-B | E90: AlNoor Exct-Haram-Garden Ph-4 | F90: 298 | G90: 119.2 | K90: 37 | M90: =Table8[[#This Row],[Std Remarks]] -> LIVE - 100% Completed | N90: =Table8[[#This Row],[% of Completion of Work Done]] -> 1 | O90: =Table8[[#This Row],[Customers According to % (Market Share)]] -> 119.2 | P90: 10573838 | Q90: =Table8[[#This Row],[Allocated Budget]]*Table8[[#This Row],[Allocation Percentage]] -> 1586075.7 | V90: 5217.4146 | W90: 4654.9212 | X90: Buried | Y90: =$Q$2 -> 0.15 | Z90: LIVE | AA90: Buried | AB90: 1 | AC90: =VALUE(SUBSTITUTE(AB90,"%","")) -> 1 | AD90: 46082 | AE90: =IFERROR(Table8[[#This Row],[Timeline - Monthwise]]-MIN(Table8[Start Date..]),"None") -> None | AF90: =IFERROR(Table8[[#This Row],[Timeline - Monthwise]]-Table8[[#This Row],[Start Date..]]+1,"Duration Doesn't Exsists") -> Duration Doesn't Exsists | AG90: =IFERROR(Table8[[#This Row],[Timeline - Monthwise]]-TODAY(),"No ETA") -> No ETA | AH90: =IF(AB90=100%,"Completed",IF(AB90=0%,"Yet to Start","In Progress")) -> Completed | AJ90: Timeline not applicable | AL90: Live - As per Plan | AM90: LIVE - 100% Completed | AS90: =VLOOKUP(Table8[[#This Row],[CEM Number]],'71 CEMs'!$E$5:$E$76,1,0) -> #N/A | AT90: Timeline not applicable
A91: INT-23-00439 | B91: 44924 | C91: Multan | D91: Multan Misc. Areas | E91: AlQuresh Phase 1 | F91: 1366 | G91: 683 | H91: 200 | I91: 23 | J91: 33 | K91: 144 | M91: =Table8[[#This Row],[Std Remarks]] -> LIVE - 100% Completed | N91: =Table8[[#This Row],[% of Completion of Work Done]] -> 1 | O91: =Table8[[#This Row],[Customers According to % (Market Share)]] -> 683 | P91: 36186977 | Q91: =Table8[[#This Row],[Allocated Budget]]*Table8[[#This Row],[Allocation Percentage]] -> 5428046.5 | R91: 30758930 | S91: -0.85 | U91: 0.5 | V91: 19648.443 | W91: 17427.972 | X91: Hybrid | Y91: =$Q$2 -> 0.15 | Z91: LIVE | AA91: Hybrid | AB91: 1 | AC91: =VALUE(SUBSTITUTE(AB91,"%","")) -> 1 | AD91: 46082 | AE91: =IFERROR(Table8[[#This Row],[Timeline - Monthwise]]-MIN(Table8[Start Date..]),"None") -> None | AF91: =IFERROR(Table8[[#This Row],[Timeline - Monthwise]]-Table8[[#This Row],[Start Date..]]+1,"Duration Doesn't Exsists") -> Duration Doesn't Exsists | AG91: =IFERROR(Table8[[#This Row],[Timeline - Monthwise]]-TODAY(),"No ETA") -> No ETA | AH91: =IF(AB91=100%,"Completed",IF(AB91=0%,"Yet to Start","In Progress")) -> Completed | AJ91: Timeline not applicable | AL91: Live - As per Plan | AM91: LIVE - 100% Completed | AS91: =VLOOKUP(Table8[[#This Row],[CEM Number]],'71 CEMs'!$E$5:$E$76,1,0) -> INT-23-00439 | AT91: Timeline not applicable
A92: INT-23-00439 | B92: 44924 | C92: Multan | D92: Multan Misc. Areas | E92: AlQuresh Phase 2 | F92: 1420 | G92: 710 | H92: 0 | I92: 0 | J92: 0 | K92: 0 | L92: On hold | M92: =Table8[[#This Row],[Std Remarks]] -> NOT LIVE - RETAIN BUDGET | N92: =Table8[[#This Row],[% of Completion of Work Done]] -> 1 | O92: =Table8[[#This Row],[Customers According to % (Market Share)]] -> 710 | P92: 30642179 | Q92: =(Table8[[#This Row],[Allocated Budget]]*$Q$2)+(Table8[[#This Row],[Allocated Budget]]*(1-Table8[[#This Row],[HP% based on Live % ( Work Progress)]])*(1-$Q$2)) -> 4596326.9 | R92: 26045852 | S92: -1 | U92: 0.5 | V92: 15771.57 | W92: 13938.335 | X92: Hybrid | Y92: =Table8[[#This Row],[% of Completion of Work Done]] -> 1 | Z92: NOT LIVE | AB92: 1 | AC92: =VALUE(SUBSTITUTE(AB92,"%","")) -> 1 | AD92: 46082 | AE92: =IFERROR(Table8[[#This Row],[Timeline - Monthwise]]-MIN(Table8[Start Date..]),"None") -> 0 | AF92: =IFERROR(Table8[[#This Row],[Timeline - Monthwise]]-Table8[[#This Row],[Start Date..]]+1,"Duration Doesn't Exsists") -> 1 | AG92: =IFERROR(Table8[[#This Row],[Timeline - Monthwise]]-TODAY(),"No ETA") -> -47 | AH92: =IF(AB92=100%,"Completed",IF(AB92=0%,"Yet to Start","In Progress")) -> Completed | AI92: 46082 | AJ92: Mar-2026 | AK92: Permission Issue With Cable Operator/C.W completed | AL92: Not Live - Permission Issues | AM92: NOT LIVE - RETAIN BUDGET | AN92: 1 | AS92: =VLOOKUP(Table8[[#This Row],[CEM Number]],'71 CEMs'!$E$5:$E$76,1,0) -> INT-23-00439 | AT92: 46082
A93: I260599 | B93: No Initiation Date | C93: Dera Ghazi Khan | D93: DG Khan | E93: Railway Civil Lines P2 | F93: 570 | G93: 256.5 | M93: =Table8[[#This Row],[Std Remarks]] -> NOT LIVE - RETAIN BUDGET | N93: =Table8[[#This Row],[% of Completion of Work Done]] -> 0 | O93: =Table8[[#This Row],[Customers According to % (Market Share)]] -> 256.5 | P93: 10735976 | Q93: =(Table8[[#This Row],[Allocated Budget]]*$Q$2)+(Table8[[#This Row],[Allocated Budget]]*(1-Table8[[#This Row],[HP% based on Live % ( Work Progress)]])*(1-$Q$2)) -> 10735976 | U93: 0.45 | V93: 2379.35 | W93: 13118.555 | X93: Hybrid | Y93: =Table8[[#This Row],[% of Completion of Work Done]] -> 0 | Z93: NOT LIVE | AB93: 0 | AC93: =VALUE(SUBSTITUTE(AB93,"%","")) -> 0 | AD93: 46082 | AE93: =IFERROR(Table8[[#This Row],[Timeline - Monthwise]]-MIN(Table8[Start Date..]),"None") -> 214 | AF93: =IFERROR(Table8[[#This Row],[Timeline - Monthwise]]-Table8[[#This Row],[Start Date..]]+1,"Duration Doesn't Exsists") -> 215 | AG93: =IFERROR(Table8[[#This Row],[Timeline - Monthwise]]-TODAY(),"No ETA") -> 167 | AH93: =IF(AB93=100%,"Completed",IF(AB93=0%,"Yet to Start","In Progress")) -> Yet to Start | AI93: 6 Months | AJ93: Oct-2026 | AK93: These Projects have not been started yet, proceedings shall be done post eid | AL93: Not Live - Work to be initiated | AM93: NOT LIVE - RETAIN BUDGET | AS93: =VLOOKUP(Table8[[#This Row],[CEM Number]],'71 CEMs'!$E$5:$E$76,1,0) -> #N/A | AT93: 46296
A94: I260599 | B94: No Initiation Date | C94: Dera Ghazi Khan | D94: DG Khan | E94: Royal city | F94: 166 | G94: 74.7 | M94: =Table8[[#This Row],[Std Remarks]] -> NOT LIVE - RETAIN BUDGET | N94: =Table8[[#This Row],[% of Completion of Work Done]] -> 0 | O94: =Table8[[#This Row],[Customers According to % (Market Share)]] -> 74.7 | P94: 4378505.7 | Q94: =(Table8[[#This Row],[Allocated Budget]]*$Q$2)+(Table8[[#This Row],[Allocated Budget]]*(1-Table8[[#This Row],[HP% based on Live % ( Work Progress)]])*(1-$Q$2)) -> 4378505.7 | U94: 0.45 | V94: 2043.4812 | W94: 1900.95 | X94: Hybrid | Y94: =Table8[[#This Row],[% of Completion of Work Done]] -> 0 | Z94: NOT LIVE | AB94: 0 | AC94: =VALUE(SUBSTITUTE(AB94,"%","")) -> 0 | AD94: 46082 | AE94: =IFERROR(Table8[[#This Row],[Timeline - Monthwise]]-MIN(Table8[Start Date..]),"None") -> 214 | AF94: =IFERROR(Table8[[#This Row],[Timeline - Monthwise]]-Table8[[#This Row],[Start Date..]]+1,"Duration Doesn't Exsists") -> 215 | AG94: =IFERROR(Table8[[#This Row],[Timeline - Monthwise]]-TODAY(),"No ETA") -> 167 | AH94: =IF(AB94=100%,"Completed",IF(AB94=0%,"Yet to Start","In Progress")) -> Yet to Start | AI94: 6 Months | AJ94: Oct-2026 | AK94: These Projects have not been started yet, proceedings shall be done post eid | AL94: Not Live - Work to be initiated | AM94: NOT LIVE - RETAIN BUDGET | AS94: =VLOOKUP(Table8[[#This Row],[CEM Number]],'71 CEMs'!$E$5:$E$76,1,0) -> #N/A | AT94: 46296
A95: INT-23-00437 | B95: 44924 | C95: Lahore | D95: Lahore Misc Areas | E95: Al-Raheems Homes | F95: 120 | G95: 60 | M95: =Table8[[#This Row],[Std Remarks]] -> LIVE - 100% Completed | N95: =Table8[[#This Row],[% of Completion of Work Done]] -> 1 | O95: =Table8[[#This Row],[Customers According to % (Market Share)]] -> 60 | P95: 1163619.8 | Q95: =Table8[[#This Row],[Allocated Budget]]*Table8[[#This Row],[Allocation Percentage]] -> 174542.97 | R95: 989076.83 | S95: -1 | U95: 0.5 | V95: 169.75368 | W95: 790.6628 | X95: Hybrid | Y95: =$Q$2 -> 0.15 | Z95: LIVE | AA95: Hybrid | AB95: 1 | AC95: =VALUE(SUBSTITUTE(AB95,"%","")) -> 1 | AD95: 46082 | AE95: =IFERROR(Table8[[#This Row],[Timeline - Monthwise]]-MIN(Table8[Start Date..]),"None") -> None | AF95: =IFERROR(Table8[[#This Row],[Timeline - Monthwise]]-Table8[[#This Row],[Start Date..]]+1,"Duration Doesn't Exsists") -> Duration Doesn't Exsists | AG95: =IFERROR(Table8[[#This Row],[Timeline - Monthwise]]-TODAY(),"No ETA") -> No ETA | AH95: =IF(AB95=100%,"Completed",IF(AB95=0%,"Yet to Start","In Progress")) -> Completed | AJ95: Timeline not applicable | AL95: Live - As per Plan | AM95: LIVE - 100% Completed | AS95: =VLOOKUP(Table8[[#This Row],[CEM Number]],'71 CEMs'!$E$5:$E$76,1,0) -> INT-23-00437 | AT95: Timeline not applicable
A96: I250734 | B96: No Initiation Date | C96: Bahawalpur | D96: Bahwalpur (P2)-B | E96: Al-Rahim Garden & Crystal Homes | F96: 484 | G96: 193.6 | H96: Not Live Yet | M96: =Table8[[#This Row],[Std Remarks]] -> LIVE - 100% Completed | N96: =Table8[[#This Row],[% of Completion of Work Done]] -> 1 | O96: =Table8[[#This Row],[Customers According to % (Market Share)]] -> 193.6 | P96: 9615395.4 | Q96: =Table8[[#This Row],[Allocated Budget]]*Table8[[#This Row],[Allocation Percentage]] -> 1442309.3 | V96: 1552.6323 | W96: 6093.614 | X96: Buried | Y96: =$Q$2 -> 0.15 | Z96: LIVE | AA96: Buried | AB96: 1 | AC96: =VALUE(SUBSTITUTE(AB96,"%","")) -> 1 | AD96: 46082 | AE96: =IFERROR(Table8[[#This Row],[Timeline - Monthwise]]-MIN(Table8[Start Date..]),"None") -> None | AF96: =IFERROR(Table8[[#This Row],[Timeline - Monthwise]]-Table8[[#This Row],[Start Date..]]+1,"Duration Doesn't Exsists") -> Duration Doesn't Exsists | AG96: =IFERROR(Table8[[#This Row],[Timeline - Monthwise]]-TODAY(),"No ETA") -> No ETA | AH96: =IF(AB96=100%,"Completed",IF(AB96=0%,"Yet to Start","In Progress")) -> Completed | AJ96: Timeline not applicable | AK96: Crystal Home live but Al- Rahim Garden NoC Pending by society | AL96: Live - As per Plan | AM96: LIVE - 100% Completed | AS96: =VLOOKUP(Table8[[#This Row],[CEM Number]],'71 CEMs'!$E$5:$E$76,1,0) -> #N/A | AT96: Timeline not applicable
A97: I260599 | B97: No Initiation Date | C97: Dera Ghazi Khan | D97: DG Khan | E97: Royal Pearl Enclave | F97: 1768 | G97: 795.6 | M97: =Table8[[#This Row],[Std Remarks]] -> NOT LIVE - RETAIN BUDGET | N97: =Table8[[#This Row],[% of Completion of Work Done]] -> 0 | O97: =Table8[[#This Row],[Customers According to % (Market Share)]] -> 795.6 | P97: 55303644 | Q97: =(Table8[[#This Row],[Allocated Budget]]*$Q$2)+(Table8[[#This Row],[Allocated Budget]]*(1-Table8[[#This Row],[HP% based on Live % ( Work Progress)]])*(1-$Q$2)) -> 55303644 | U97: 0.45 | V97: 28101.015 | W97: 23997.5 | X97: Hybrid | Y97: =Table8[[#This Row],[% of Completion of Work Done]] -> 0 | Z97: NOT LIVE | AB97: 0 | AC97: =VALUE(SUBSTITUTE(AB97,"%","")) -> 0 | AD97: 46082 | AE97: =IFERROR(Table8[[#This Row],[Timeline - Monthwise]]-MIN(Table8[Start Date..]),"None") -> 214 | AF97: =IFERROR(Table8[[#This Row],[Timeline - Monthwise]]-Table8[[#This Row],[Start Date..]]+1,"Duration Doesn't Exsists") -> 215 | AG97: =IFERROR(Table8[[#This Row],[Timeline - Monthwise]]-TODAY(),"No ETA") -> 167 | AH97: =IF(AB97=100%,"Completed",IF(AB97=0%,"Yet to Start","In Progress")) -> Yet to Start | AI97: 6 Months | AJ97: Oct-2026 | AK97: These Projects have not been started yet, proceedings shall be done post eid | AL97: Not Live - Work to be initiated | AM97: NOT LIVE - RETAIN BUDGET | AS97: =VLOOKUP(Table8[[#This Row],[CEM Number]],'71 CEMs'!$E$5:$E$76,1,0) -> #N/A | AT97: 46296
A98: I260599 | B98: No Initiation Date | C98: Dera Ghazi Khan | D98: DG Khan | E98: Sana Valley | F98: 424 | G98: 190.8 | M98: =Table8[[#This Row],[Std Remarks]] -> NOT LIVE - RETAIN BUDGET | N98: =Table8[[#This Row],[% of Completion of Work Done]] -> 0 | O98: =Table8[[#This Row],[Customers According to % (Market Share)]] -> 190.8 | P98: 4178279.7 | Q98: =(Table8[[#This Row],[Allocated Budget]]*$Q$2)+(Table8[[#This Row],[Allocated Budget]]*(1-Table8[[#This Row],[HP% based on Live % ( Work Progress)]])*(1-$Q$2)) -> 4178279.7 | U98: 0.45 | V98: 831.6 | W98: 4651.9726 | X98: Hybrid | Y98: =Table8[[#This Row],[% of Completion of Work Done]] -> 0 | Z98: NOT LIVE | AB98: 0 | AC98: =VALUE(SUBSTITUTE(AB98,"%","")) -> 0 | AD98: 46082 | AE98: =IFERROR(Table8[[#This Row],[Timeline - Monthwise]]-MIN(Table8[Start Date..]),"None") -> 214 | AF98: =IFERROR(Table8[[#This Row],[Timeline - Monthwise]]-Table8[[#This Row],[Start Date..]]+1,"Duration Doesn't Exsists") -> 215 | AG98: =IFERROR(Table8[[#This Row],[Timeline - Monthwise]]-TODAY(),"No ETA") -> 167 | AH98: =IF(AB98=100%,"Completed",IF(AB98=0%,"Yet to Start","In Progress")) -> Yet to Start | AI98: 6 Months | AJ98: Oct-2026 | AK98: These Projects have not been started yet, proceedings shall be done post eid | AL98: Not Live - Work to be initiated | AM98: NOT LIVE - RETAIN BUDGET | AS98: =VLOOKUP(Table8[[#This Row],[CEM Number]],'71 CEMs'!$E$5:$E$76,1,0) -> #N/A | AT98: 46296
A99: I260599 | B99: No Initiation Date | C99: Feeders/Transportations | D99: DG Khan | E99: Transportation | F99: 0 | G99: 0 | M99: =Table8[[#This Row],[Std Remarks]] -> FEEDER ETC WORK - RETAIN BUDGET | N99: =Table8[[#This Row],[% of Completion of Work Done]] -> 0 | O99: =Table8[[#This Row],[Customers According to % (Market Share)]] -> 0 | P99: 9800000 | Q99: =Table8[[#This Row],[Allocated Budget]]*Table8[[#This Row],[Allocation Percentage]] -> 9800000 | V99: 0 | W99: 0 | Y99: =$R$1 -> 1 | AB99: 0 | AC99: =VALUE(SUBSTITUTE(AB99,"%","")) -> 0 | AD99: 46082 | AE99: =IFERROR(Table8[[#This Row],[Timeline - Monthwise]]-MIN(Table8[Start Date..]),"None") -> None | AF99: =IFERROR(Table8[[#This Row],[Timeline - Monthwise]]-Table8[[#This Row],[Start Date..]]+1,"Duration Doesn't Exsists") -> Duration Doesn't Exsists | AG99: =IFERROR(Table8[[#This Row],[Timeline - Monthwise]]-TODAY(),"No ETA") -> No ETA | AH99: =IF(AB99=100%,"Completed",IF(AB99=0%,"Yet to Start","In Progress")) -> Yet to Start | AJ99: Timeline not applicable | AL99: Feeders/Trans | AM99: FEEDER ETC WORK - RETAIN BUDGET | AS99: =VLOOKUP(Table8[[#This Row],[CEM Number]],'71 CEMs'!$E$5:$E$76,1,0) -> #N/A | AT99: Timeline not applicable
A100: I240539 | B100: 45350 | C100: Swat | D100: Swat Ph2 | E100: Aman kot | F100: 2538 | G100: 1015.2 | L100: Civil Work in progress | M100: =Table8[[#This Row],[Std Remarks]] -> NOT LIVE - RETAIN BUDGET | N100: =Table8[[#This Row],[% of Completion of Work Done]] -> 0.8 | O100: =N100*G100 -> 812.16 | P100: 24196912 | Q100: =(Table8[[#This Row],[Allocated Budget]]*$Q$2)+(Table8[[#This Row],[Allocated Budget]]*(1-Table8[[#This Row],[HP% based on Live % ( Work Progress)]])*(1-$Q$2)) -> 7743011.7 | R100: 16453900 | S100: -0.85 | U100: 0.4 | V100: 1710.9265 | W100: 28333.39 | X100: Hybrid | Y100: =Table8[[#This Row],[% of Completion of Work Done]] -> 0.8 | Z100: NOT LIVE | AB100: 0.8 | AC100: =VALUE(SUBSTITUTE(AB100,"%","")) -> 0.8 | AD100: 46082 | AE100: =IFERROR(Table8[[#This Row],[Timeline - Monthwise]]-MIN(Table8[Start Date..]),"None") -> 122 | AF100: =IFERROR(Table8[[#This Row],[Timeline - Monthwise]]-Table8[[#This Row],[Start Date..]]+1,"Duration Doesn't Exsists") -> 123 | AG100: =IFERROR(Table8[[#This Row],[Timeline - Monthwise]]-TODAY(),"No ETA") -> 75 | AH100: =IF(AB100=100%,"Completed",IF(AB100=0%,"Yet to Start","In Progress")) -> In Progress | AI100: 3 Months | AJ100: Jul-2026 | AK100: Civil Work Completion | AL100: Not Live - Work in Progress (WIP) | AM100: NOT LIVE - RETAIN BUDGET | AN100: 1 | AS100: =VLOOKUP(Table8[[#This Row],[CEM Number]],'71 CEMs'!$E$5:$E$76,1,0) -> I240539 | AT100: 46204
A101: INT-21-00315 | B101: 44195 | C101: Gujranwala | D101: Gujranwala Ph2 | E101: Aman Society | F101: 96 | G101: 38.4 | M101: =Table8[[#This Row],[Std Remarks]] -> LIVE - 100% Completed | N101: =Table8[[#This Row],[% of Completion of Work Done]] -> 1 | O101: =Table8[[#This Row],[Customers According to % (Market Share)]] -> 38.4 | P101: 4862657.5 | Q101: =Table8[[#This Row],[Allocated Budget]]*Table8[[#This Row],[Allocation Percentage]] -> 729398.62 | R101: 4133258.9 | S101: -1 | U101: 0.4 | V101: 0 | W101: 988.92132 | X101: Buried | Y101: =$Q$2 -> 0.15 | Z101: LIVE | AA101: Buried | AB101: 1 | AC101: =VALUE(SUBSTITUTE(AB101,"%","")) -> 1 | AD101: 46082 | AE101: =IFERROR(Table8[[#This Row],[Timeline - Monthwise]]-MIN(Table8[Start Date..]),"None") -> None | AF101: =IFERROR(Table8[[#This Row],[Timeline - Monthwise]]-Table8[[#This Row],[Start Date..]]+1,"Duration Doesn't Exsists") -> Duration Doesn't Exsists | AG101: =IFERROR(Table8[[#This Row],[Timeline - Monthwise]]-TODAY(),"No ETA") -> No ETA | AH101: =IF(AB101=100%,"Completed",IF(AB101=0%,"Yet to Start","In Progress")) -> Completed | AJ101: Timeline not applicable | AL101: Live - As per Plan | AM101: LIVE - 100% Completed | AS101: =VLOOKUP(Table8[[#This Row],[CEM Number]],'71 CEMs'!$E$5:$E$76,1,0) -> INT-21-00315 | AT101: Timeline not applicable
...

Sheet Sheet1

Sheet KPI 
C4: S.No | D4: Category | E4: KPI Name | F4: What it Tells | G4: Excel Formula (Concept)
C7: 1 | D7: Execution | E7: Total Projects | F7: Overall scale of operations | G7: =Areas!B1 -> 1150
C8: =C7+1 -> 2 | D8: Execution | E8: Live Projects | F8: Revenue-active deployments | G8: ='Live or Not Live'!B4 -> 525
C9: =C8+1 -> 3 | D9: Execution | E9: Not Live Projects | F9: Work completed but not activated | G9: ='Live or Not Live'!B5 -> 625
C10: =C9+1 -> 4 | D10: Execution | E10: Avg Completion % | F10: Overall execution progress | G10: =SUBTOTAL(1,Table8[% of Completion of Work Done]) -> 0.43469046
C11: =C10+1 -> 5 | D11: Execution | E11: Projects ≥80% Complete | F11: Near-finish pipeline | G11: =COUNTIF(Table8[% of Completion of Work Done],">=0.8") -> 579
C12: =C11+1 -> 6 | D12: Financial | E12: Total Allocated Budget | F12: Planned CAPEX | G12: =SUBTOTAL(9,Table8[Allocated Budget]) -> 2.209571e+10
C13: =C12+1 -> 7 | D13: Financial | E13: Total Revised Budget | F13: Updated CAPEX view | G13: =SUBTOTAL(9,Table8[Revised Budget]) -> 1.0815617e+10
C14: =C13+1 -> 8 | D14: Financial | E14: Budget Variance | F14: Over/under spend
C15: =C14+1 -> 9 | D15: Financial | E15: CAPEX at Risk | F15: Money stuck in near-complete, not-live projects
C16: =C15+1 -> 10 | D16: Financial | E16: Cost Efficiency | F16: Spend effectiveness
C17: =C16+1 -> 11 | D17: Risk | E17: Delayed Projects | F17: Execution delays
C18: =C17+1 -> 12 | D18: Risk | E18: Projects Delayed >10 Days | F18: Severe delays
C19: =C18+1 -> 13 | D19: Risk | E19: Near Complete Not Live | F19: Activation bottlenecks
C20: =C19+1 -> 14 | D20: Risk | E20: High CAPEX Not Live | F20: Financial exposure (all stalled)
C21: =C20+1 -> 15 | D21: Risk | E21: Zero Progress Projects | F21: Execution failure / inactivity | G21: =COUNTIF(Table8[% of Completion of Work Done],0) -> 745
C22: =C21+1 -> 16 | D22: Commercial | E22: Total Homes Passed (HP) | F22: Network deployment scale | G22: =SUBTOTAL(9,Table8[Total H.P]) -> 1444140
C23: =C22+1 -> 17 | D23: Commercial | E23: Active Customers | F23: Monetized base | G23: =SUBTOTAL(9,Table8[[Active ]]) -> 13574
C24: =C23+1 -> 18 | D24: Commercial | E24: Conversion % | F24: Deployment → revenue efficiency | G24: =G23/G22 -> 0.0093993657
C25: =C24+1 -> 19 | D25: Commercial | E25: Revenue Potential Blocked | F25: Customers stuck due to non-activation | G25: =SUMIFS(Table8[Total H.P],Table8[Current Status (Live/Not Live)],"Not Live",Table8[% of Completion of Work Done],">=0.8") -> 104840
C26: =C25+1 -> 20 | D26: Commercial | E26: Time to Live | F26: Delay between completion & activation | G26: =AVERAGE(Table8[Start Date..]-Table8[Timeline - Monthwise]) -> -214

Sheet Dashboard - Surface
D1: Approved SF Expansion Feasibilities Report | K1: Total Network | L1: Expected Home Passes | M1: Sellable Capacity | N1: Active Home Passes
J2: Total Network (HP) | K2: ='HP - Customer Network'!B1 -> 1444140 | L2: ='HP - Customer Network'!C1 -> 600881.5
A6: Number of Feasibility | B6: =Feasibilities!B1 -> 97 | D6: Live Areas | E6: =GETPIVOTDATA("Area / Section / Pocket / Society (Original Name)",'Live or Not Live'!$A$3,"Current Status (Live/Not Live)","LIVE") -> 525 | G6: Not Live Areas | H6: =GETPIVOTDATA("Area / Section / Pocket / Society (Original Name)",'Live or Not Live'!$A$3,"Current Status (Live/Not Live)","NOT LIVE") -> 625 | J6: Total Areas | K6: =H6+E6 -> 1150
A10: Live vs Non Live Ratio | G10: Standardized Comment Box | M10: Timeline Box | S10: =_xlfn.AGGREGATE(9,6,Q15:Q38) -> 513
M13: Month | O13: Quarter | Q13: Number of Areas | S13: Quarter - Total
G15: Comments | H15: Count of Areas | M15: 46023 | O15: Q1 | Q15: =IFERROR(VLOOKUP(M15,'Timeline Box'!$F$3:$G$9,2,0)," ") | S15: =SUM(Q15:Q17) -> 37
G16: LIVE - 100% Completed | H16: 512 | M16: 46054 | Q16: =IFERROR(VLOOKUP(M16,'Timeline Box'!$F$4:$G$12,2,0)," ")
G17: LIVE - 25% Completed | H17: 1 | M17: 46082 | Q17: =IFERROR(VLOOKUP(M17,'Timeline Box'!$F$4:$G$12,2,0)," ") -> 37
G18: LIVE - 50% Completed | H18: 6 | M18: 46113 | O18: Q2 | Q18: =IFERROR(VLOOKUP(M18,'Timeline Box'!$F$4:$G$12,2,0)," ") -> 61 | S18: =SUM(Q18:Q20) -> 151
G19: LIVE - 60% Completed | H19: 3 | M19: 46143 | Q19: =IFERROR(VLOOKUP(M19,'Timeline Box'!$F$4:$G$12,2,0)," ") -> 26
G20: LIVE - 80% Completed | H20: 5 | J20: Buried | K20: =GETPIVOTDATA("Area / Section / Pocket / Society (Original Name)",'Arial, Hybrid, Buried'!$A$3,"Originally Approved on: Arial, Buried, Hybrid","Buried") -> 253 | M20: 46174 | Q20: =IFERROR(VLOOKUP(M20,'Timeline Box'!$F$4:$G$12,2,0)," ") -> 64
G21: NOT LIVE - RETAIN BUDGET | H21: 533 | M21: 46204 | O21: Q3 | Q21: =IFERROR(VLOOKUP(M21,'Timeline Box'!$F$4:$G$12,2,0)," ") -> 33 | S21: =SUM(Q21:Q23) -> 33
G22: REMOVE BUDGET (P) | H22: 43 | M22: 46235 | Q22: =IFERROR(VLOOKUP(M22,'Timeline Box'!$F$4:$G$12,2,0)," ")
G23: REMOVE BUDGET (T) | H23: 19 | M23: 46266 | Q23: =IFERROR(VLOOKUP(M23,'Timeline Box'!$F$4:$G$12,2,0)," ")
G24: SWAPPED | H24: 28 | J24: Hybrid | K24: =GETPIVOTDATA("Area / Section / Pocket / Society (Original Name)",'Arial, Hybrid, Buried'!$A$3,"Originally Approved on: Arial, Buried, Hybrid","Hybrid") -> 804 | M24: 46296 | O24: Q4 | Q24: =IFERROR(VLOOKUP(M24,'Timeline Box'!$F$4:$G$12,2,0)," ") -> 292 | S24: =SUM(Q24:Q26) -> 292
G25: Grand Total | H25: 1150 | M25: 46327 | Q25: =IFERROR(VLOOKUP(M25,'Timeline Box'!$F$4:$G$12,2,0)," ")
M26: 46357 | Q26: =IFERROR(VLOOKUP(M26,'Timeline Box'!$F$4:$G$12,2,0)," ")
M27: 46388 | O27: Q1 | Q27: =IFERROR(VLOOKUP(M27,'Timeline Box'!$F$4:$G$12,2,0)," ") | S27: =SUM(Q27:Q29) -> 0
J28: Arial | K28: =GETPIVOTDATA("Area / Section / Pocket / Society (Original Name)",'Arial, Hybrid, Buried'!$A$3,"Originally Approved on: Arial, Buried, Hybrid","Arial") -> 93 | M28: 46419 | Q28: =IFERROR(VLOOKUP(M28,'Timeline Box'!$F$4:$G$12,2,0)," ")
M29: 46447 | Q29: =IFERROR(VLOOKUP(M29,'Timeline Box'!$F$4:$G$12,2,0)," ")
M30: 46478 | O30: Q2 | Q30: =IFERROR(VLOOKUP(M30,'Timeline Box'!$F$4:$G$12,2,0)," ") | S30: =SUM(Q30:Q32) -> 0
M31: 46508 | Q31: =IFERROR(VLOOKUP(M31,'Timeline Box'!$F$4:$G$12,2,0)," ")
A32: Orignally Approved Areas - Arial,Buried,Hybrid | G32: City Names | M32: 46539 | Q32: =IFERROR(VLOOKUP(M32,'Timeline Box'!$F$4:$G$12,2,0)," ")
M33: 46569 | O33: Q3 | Q33: =IFERROR(VLOOKUP(M33,'Timeline Box'!$F$4:$G$12,2,0)," ") | S33: =SUM(Q33:Q35) -> 0
M34: 46600 | Q34: =IFERROR(VLOOKUP(M34,'Timeline Box'!$F$4:$G$12,2,0)," ")
M35: 46631 | Q35: =IFERROR(VLOOKUP(M35,'Timeline Box'!$F$4:$G$12,2,0)," ")
M36: 46661 | O36: Q4 | Q36: =IFERROR(VLOOKUP(M36,'Timeline Box'!$F$4:$G$12,2,0)," ") | S36: =SUM(Q36:Q38) -> 0
M37: 46692 | Q37: =IFERROR(VLOOKUP(M37,'Timeline Box'!$F$4:$G$12,2,0)," ")
M38: 46722 | Q38: =IFERROR(VLOOKUP(M38,'Timeline Box'!$F$4:$G$12,2,0)," ")
Q40: Feedback Awaited | R40: 45

Sheet City Names
A1: Number of CEMs | B1: =COUNTA(A4:A98)-1 -> 34
A3: Row Labels | B3: Count of Fesibility Name
A4: Abbottabad | B4: 8
A5: Bahawalpur | B5: 30
A6: Chitral | B6: 2
A7: Daska | B7: 43
A8: Dera Ghazi Khan | B8: 31
A9: Faisalabad | B9: 42
A10: Gujranwala | B10: 72
A11: Hafizabad | B11: 28
A12: Haripur | B12: 15
A13: Hyderabad | B13: 29
A14: Islamabad | B14: 71
A15: Jhang | B15: 21
... A38: Grand Total | B38: 1150

Sheet Dashboard - Feasibility
C1: Approved SF Expansion Feasibilities Report - Area Focused
A7: Number of Feasibility | B7: =Feasibilities!B1 -> 97
A10: Live Areas | B10: =GETPIVOTDATA("Area / Section / Pocket / Society (Original Name)",'Live or Not Live'!$A$3,"Current Status (Live/Not Live)","LIVE") -> 525
A13: Not Live Areas | B13: =GETPIVOTDATA("Area / Section / Pocket / Society (Original Name)",'Live or Not Live'!$A$3,"Current Status (Live/Not Live)","NOT LIVE") -> 625
A16: Total Network (HP) | B16: ='HP - Customer Network'!B1 -> 1444140
A19: Expected HP | B19: ='HP - Customer Network'!C1 -> 600881.5
A38: Fesibility Name | B38: Area / Section / Pocket / Society (Original Name) | C38: Remarks Grouped | D38: Total HP | E38: Expected Customers Based on Market Share (%) | F38: Expected Customers Based on Completion of Work
A39: Abbottabad | B39: Gulfam Town_Mera Muzzafar | C39: Live - As per Plan | D39: 450 | E39: 180 | F39: 180
B40: Malikpura | C40: Live - As per Plan | D40: 714 | E40: 285.6 | F40: 285.6
B41: Salhad | C41: Swap Cases | D41: 700 | E41: 280 | F41: 280
A42: Abbottabad Ph2 | B42: Al Mansoor Town Ext. | C42: Live - As per Plan | D42: 440 | E42: 176 | F42: 176
B43: Jhangi Qazian | C43: Live - As per Plan | D43: 420 | E43: 168 | F43: 168
B44: Jhangi Saeedan Extension | C44: Live - As per Plan | D44: 482 | E44: 192.8 | F44: 192.8
B45: Kaghan Colony Extension | C45: Live - As per Plan | D45: 302 | E45: 120.8 | F45: 120.8
B46: Kareenpura Extension | C46: Live - As per Plan | D46: 182 | E46: 72.8 | F46: 72.8
A47: Al Hafeez Garden & Tariq Garden | B47: Al Hafeez Garden Ph-5 | C47: Not Live - Work in Progress (WIP) | D47: 1450 | E47: 580
B48: Al Hafeez Gdn Ph-2 | C48: Live - As per Plan | D48: 1404 | E48: 561.6
B49: Al Raheem Gdn Ph-2 Extn. | C49: Not Live - Work to be initiated | D49: 1150 | E49: 460
B50: Tariq Garden | C50: Permenant Budget Removal | D50: 1498 | E50: 599.2
A51: Al Jalil & Al khalil LHE | B51: Al Hamra | C51: Not Live - Work in Progress (WIP) | D51: 424 | E51: 169.6 | F51: 169.6
B52: Al Jalil Housing P2 | C52: Live - As per Plan | D52: 2232 | E52: 892.8 | F52: 892.8
B53: Al Jalil Housing P3 | C53: Live - As per Plan | D53: 2210 | E53: 884 | F53: 884
B54: Al Jalil Housing P4 | C54: Not Live - Work to be initiated | D54: 2106 | E54: 842.4 | F54: 842.4
B55: Al Kabeer Ph-2-Pk1 | C55: Live - As per Plan | D55: 2268 | E55: 907.2 | F55: 907.2
B56: Al Kabeer Ph-2-Pk2 | C56: Not Live - Work in Progress (WIP) | D56: 3086 | E56: 1234.4 | F56: 1234.4
B57: Al Kabeer Ph-2-Pk3 | C57: Not Live - Work to be initiated | D57: 776 | E57: 310.4 | F57: 310.4
B58: Al Kabeer Town Ph-1 | C58: Live - As per Plan | D58: 512 | E58: 204.8 | F58: 204.8
B59: Central Park Housing-P1 | C59: Permenant Budget Removal | D59: 1526 | E59: 610.4 | F59: 610.4
B60: Central Park Housing-P2 | C60: Permenant Budget Removal | D60: 1200 | E60: 480 | F60: 480
B61: Central Park Housing-P3 | C61: Permenant Budget Removal | D61: 1206 | E61: 482.4 | F61: 482.4
A62: Askari (1-6) Karachi | B62: Akari-1 | C62: Live - As per Plan | D62: 320 | E62: 160 | F62: 160
B63: Akari-2 | C63: Live - As per Plan | D63: 240 | E63: 120 | F63: 120
B64: Akari-3 | C64: Live - As per Plan | D64: 970 | E64: 485 | F64: 485
B65: Askari-4 | C65: Live - As per Plan | D65: 1612 | E65: 806 | F65: 806
B66: Askari-5 P1 | C66: Live - As per Plan | D66: 728 | E66: 364 | F66: 364
B67: Askari-5 P2 | C67: Live - As per Plan | D67: 3460 | E67: 1730 | F67: 1730
B68: Askari-5G | C68: Live - As per Plan | D68: 282 | E68: 141 | F68: 141
B69: Askari-5H | C69: Not Live - Work to be initiated | D69: 216 | E69: 108 | F69: 108
B70: Askari-5J | C70: Live - As per Plan | D70: 1300 | E70: 650 | F70: 650
B71: Askari-6 Sec 01 | C71: Live - As per Plan | D71: 566 | E71: 283 | F71: 283
B72: Askari-6 Sec 02 | C72: Not Live - Work to be initiated | D72: 470 | E72: 235 | F72: 235
B73: Askari-6 Sec 03 | C73: Not Live - Work to be initiated | D73: 1040 | E73: 520 | F73: 520
B74: Askari-6 Sec 04 | C74: Not Live - Work to be initiated | D74: 936 | E74: 468 | F74: 468
... B81: Askari-6 Sec 11 | C81: Not Live - Work to be initiated | D81: 936 | E81: 468 | F81: 468
A82: Askari Lahore | B82: Askari-1 | C82: Live - As per Plan | D82: 720 | E82: 288 | F82: 288
B83: Askari-10 P1 | C83: Live - As per Plan | D83: 3018 | E83: 1207.2 | F83: 1207.2
B84: Askari-10 P2 | C84: Live - As per Plan | D84: 1734 | E84: 693.6 | F84: 693.6
B85: Askari-10 Sec-S | C85: Live - As per Plan | D85: 216 | E85: 86.4 | F85: 43.2
B86: Askari-11 P1 | C86: Not Live - Work to be initiated | D86: 972 | E86: 388.8 | F86: 388.8
B87: Askari-11 P2 | C87: Not Live - Work to be initiated | D87: 1628 | E87: 651.2 | F87: 651.2
B88: Askari-11 P3 | C88: Not Live - Work to be initiated | D88: 960 | E88: 384 | F88: 384
B89: Askari-2 | C89: Live - As per Plan | D89: 228 | E89: 91.2 | F89: 91.2
B90: Askari-5 | C90: Live - As per Plan | D90: 1104 | E90: 441.6 | F90: 441.6
B91: Askari-9 | C91: Live - As per Plan | D91: 828 | E91: 331.2 | F91: 331.2
A92: Askari Multan | B92: Askari-1 | C92: Live - As per Plan | D92: 182 | E92: 72.8 | F92: 72.8
B93: Askari-2 | C93: Live - As per Plan | D93: 292 | E93: 116.8 | F93: 116.8
B94: Askari-3 | C94: Live - As per Plan | D94: 506 | E94: 202.4 | F94: 202.4
A95: Askari RWP (4-7-10) | B95: Askari-10 | C95: Live - As per Plan | D95: 372 | E95: 148.8 | F95: 148.8
B96: Askari-4 | C96: Live - As per Plan | D96: 864 | E96: 345.6 | F96: 345.6
B97: Askari-7 P1 | C97: Swap Cases | D97: 472 | E97: 188.8 | F97: 188.8
B98: Askari-7 P2 | C98: Swap Cases | D98: 964 | E98: 385.6 | F98: 385.6
B99: Nazeer Apt. | C99: Live - As per Plan | D99: 54 | E99: 21.6 | F99: 21.6
B100: Willoughby Road appartments | C100: Live - As per Plan | D100: 1328 | E100: 531.2 | F100: 531.2
A101: Askari Sialkot | B101: Askari-I | C101: Live - As per Plan | D101: 272 | E101: 163.2 | F101: 163.2
B102: Askari-II | C102: Live - As per Plan | D102: 500 | E102: 300 | F102: 300
A103: Bahadurabad (KTTC) | B103: Bahadurabad & Sharfabad | C103: Live - As per Plan | D103: 2446 | E103: 978.4 | F103: 978.4
A104: Bahawalpur | B104: Japan Town | C104: Live - As per Plan | D104: 486 | E104: 243 | F104: 243
A105: Bahawalpur (P3) | B105: Asif & Hassan Town | C105: Live - As per Plan | D105: 1740 | E105: 696 | F105: 696
B106: Cheema Town Ph-2 | C106: Live - As per Plan | D106: 700 | E106: 280 | F106: 280
B107: Japan Town | C107: Live - As per Plan | D107: 486 | E107: 194.4 | F107: 194.4
B108: Medical Colony | C108: Live - As per Plan | D108: 432 | E108: 172.8 | F108: 172.8
A109: Bahwalpur (P2)-B | B109: 3 Marla Scheme | C109: Not Live - Work in Progress (WIP) | D109: 1730 | E109: 692 | F109: 692
B110: Alibad_Colony | C110: Live - As per Plan | D110: 278 | E110: 111.2 | F110: 111.2
B111: AlNoor Exct-Haram-Garden Ph-4 | C111: Live - As per Plan | D111: 298 | E111: 119.2 | F111: 119.2
B112: Al-Rahim Garden & Crystal Homes | C112: Live - As per Plan | D112: 484 | E112: 193.6 | F112: 193.6
B113: Anwarabad Colony | C113: Not Live - Work in Progress (WIP) | D113: 332 | E113: 132.8 | F113: 132.8
B114: Askari | C114: Live - As per Plan | D114: 108 | E114: 43.2 | F114: 43.2
B115: Band Road Extension & Makhdumpu | C115: Not Live - Work in Progress (WIP) | D115: 2086 | E115: 834.4 | F115: 834.4
B116: Fauji Basti | C116: Not Live - Work in Progress (WIP) | D116: 1206 | E116: 482.4 | F116: 482.4
B117: Green and Al-hafeez Town | C117: Not Live - Work in Progress (WIP) | D117: 1886 | E117: 754.4 | F117: 754.4
B118: Habib Colony | C118: Live - As per Plan | D118: 518 | E118: 207.2 | F118: 207.2
B119: Haseeb Town,Fahad Colony & Dila | C119: Not Live - Work in Progress (WIP) | D119: 3180 | E119: 1272 | F119: 1272
B120: Islamia Colony PK1 | C120: Not Live - Work in Progress (WIP) | D120: 1158 | E120: 463.2 | F120: 463.2
B121: Islamia Colony PK2 | C121: Not Live - Work in Progress (WIP) | D121: 2030 | E121: 812 | F121: 812
... B133: Taha Town | C133: Not Live - Permission Issues | D133: 428 | E133: 171.2 | F133: 171.2
A134: Buffer Zone Khi | B134: P1 | C134: Live - As per Plan | D134: 2246 | E134: 673.8 | F134: 673.8
B135: P1 | C135: Not Live - Work to be initiated | D135: 2246 | E135: 673.8
B136: P2 | C136: Live - As per Plan | D136: 1880 | E136: 564 | F136: 564
B137: P2 | C137: Not Live - Work to be initiated | D137: 1880 | E137: 564
B138: P3 | C138: Live - As per Plan | D138: 1774 | E138: 532.2 | F138: 532.2
B139: P3 | C139: Not Live - Work to be initiated | D139: 1774 | E139: 532.2
B140: P4 | C140: Live - As per Plan | D140: 3244 | E140: 973.2 | F140: 973.2
B141: P4 | C141: Not Live - Work to be initiated | D141: 3244 | E141: 973.2
B142: P5 | C142: Live - As per Plan | D142: 6000 | E142: 1800 | F142: 1800
B143: P5 | C143: Not Live - Work to be initiated | D143: 6000 | E143: 1800
B144: P6 | C144: Live - As per Plan | D144: 3298 | E144: 989.4 | F144: 989.4
B145: P6 | C145: Not Live - Work to be initiated | D145: 3298 | E145: 989.4
A146: Chinar Bagh Lahore | B146: Chinar_Bagh_P01 | C146: Live - As per Plan | D146: 694 | E146: 277.6 | F146: 277.6
B147: Chinar_Bagh_P02 | C147: Live - As per Plan | D147: 962 | E147: 384.8 | F147: 384.8
B148: Chinar_Bagh_P03 | C148: Live - As per Plan | D148: 898 | E148: 359.2 | F148: 359.2
...

Sheet Dashboard - Financials
C1: Approved SF Expansion Feasibilities Report - Financial Focused
J2: *Actual data as per 18th march 2026
A7: Number of Feasibility | B7: =Feasibilities!B1 -> 97
A10: Total Areas | B10: =B16+B13 -> 1150
A13: Live Areas | B13: =GETPIVOTDATA("Area / Section / Pocket / Society (Original Name)",'Live or Not Live'!$A$3,"Current Status (Live/Not Live)","LIVE") -> 525
A16: Not Live Areas | B16: =GETPIVOTDATA("Area / Section / Pocket / Society (Original Name)",'Live or Not Live'!$A$3,"Current Status (Live/Not Live)","NOT LIVE") -> 625
A19: Total Network (HP) | B19: ='HP - Customer Network'!B1 -> 1444140
A22: Expected HP | B22: ='HP - Customer Network'!C1 -> 600881.5
A25: Allocated Budget | B25: =B42 -> 2.209571e+10
A28: Budget Requirement - Remaining Work | B28: =D42 -> 1.0815617e+10
A31: Actual | B31: =C42 -> 3.3640419e+09
A34: Net Savings | B34: =B25-(B28+B31) -> 7.9160508e+09
A38: Budget Position
A42: Grand Total | B42: =SUBTOTAL(9,B47:B143) -> 2.209571e+10 | C42: =SUBTOTAL(9,C47:C143) -> 3.3640419e+09 | D42: =SUBTOTAL(9,D47:D143) -> 1.0815617e+10 | E42: =B42-C42-D42 -> 7.9160508e+09
B45: Allocated Budget | C45: Actual Incurred | D45: Budget Requirement - Remaining Work | E45: Net Savings
A46: CEM Number
A47: 100 | B47: =IFERROR(VLOOKUP(A47,Actuals!$H$1722:$I$1819,2,0)," ") -> 5.1899817e+08 | C47: =IFERROR(VLOOKUP(A47,Actuals!$N$44:$O$129,2,0)," ") | D47: =IFERROR(VLOOKUP(A47,Actuals!$H$1722:$J$1819,3,0)," ") -> 5.1899817e+08 | E47: =IFERROR(B47-C47-D47," ")
A48: 102 | B48: =IFERROR(VLOOKUP(A48,Actuals!$H$1722:$I$1819,2,0)," ") -> 3.2095049e+08 | C48: =IFERROR(VLOOKUP(A48,Actuals!$N$44:$O$129,2,0)," ") | D48: =IFERROR(VLOOKUP(A48,Actuals!$H$1722:$J$1819,3,0)," ") -> 3.2095049e+08 | E48: =IFERROR(B48-C48-D48," ")
A49: 103 | B49: =IFERROR(VLOOKUP(A49,Actuals!$H$1722:$I$1819,2,0)," ") -> 2.6488024e+08 | C49: =IFERROR(VLOOKUP(A49,Actuals!$N$44:$O$129,2,0)," ") | D49: =IFERROR(VLOOKUP(A49,Actuals!$H$1722:$J$1819,3,0)," ") -> 2.6488024e+08 | E49: =IFERROR(B49-C49-D49," ")
A50: 104 | B50: =IFERROR(VLOOKUP(A50,Actuals!$H$1722:$I$1819,2,0)," ") -> 2.0146775e+08 | C50: =IFERROR(VLOOKUP(A50,Actuals!$N$44:$O$129,2,0)," ") | D50: =IFERROR(VLOOKUP(A50,Actuals!$H$1722:$J$1819,3,0)," ") -> 1.2106226e+08 | E50: =IFERROR(B50-C50-D50," ")
A51: 105 | B51: =IFERROR(VLOOKUP(A51,Actuals!$H$1722:$I$1819,2,0)," ") -> 4.6921328e+08 | C51: =IFERROR(VLOOKUP(A51,Actuals!$N$44:$O$129,2,0)," ") | D51: =IFERROR(VLOOKUP(A51,Actuals!$H$1722:$J$1819,3,0)," ") -> 4.6830911e+08 | E51: =IFERROR(B51-C51-D51," ")
A52: 106 | B52: =IFERROR(VLOOKUP(A52,Actuals!$H$1722:$I$1819,2,0)," ") -> 5.3792293e+08 | C52: =IFERROR(VLOOKUP(A52,Actuals!$N$44:$O$129,2,0)," ") | D52: =IFERROR(VLOOKUP(A52,Actuals!$H$1722:$J$1819,3,0)," ") -> 5.3792293e+08 | E52: =IFERROR(B52-C52-D52," ")
A53: 107 | B53: =IFERROR(VLOOKUP(A53,Actuals!$H$1722:$I$1819,2,0)," ") -> 2.0744134e+08 | C53: =IFERROR(VLOOKUP(A53,Actuals!$N$44:$O$129,2,0)," ") | D53: =IFERROR(VLOOKUP(A53,Actuals!$H$1722:$J$1819,3,0)," ") -> 2.0744134e+08 | E53: =IFERROR(B53-C53-D53," ")
A54: 108 | B54: =IFERROR(VLOOKUP(A54,Actuals!$H$1722:$I$1819,2,0)," ") -> 3.9965733e+08 | C54: =IFERROR(VLOOKUP(A54,Actuals!$N$44:$O$129,2,0)," ") | D54: =IFERROR(VLOOKUP(A54,Actuals!$H$1722:$J$1819,3,0)," ") -> 3.9965733e+08 | E54: =IFERROR(B54-C54-D54," ")
A55: 109 | B55: =IFERROR(VLOOKUP(A55,Actuals!$H$1722:$I$1819,2,0)," ") -> 3.2499897e+08 | C55: =IFERROR(VLOOKUP(A55,Actuals!$N$44:$O$129,2,0)," ") | D55: =IFERROR(VLOOKUP(A55,Actuals!$H$1722:$J$1819,3,0)," ") -> 2.9737405e+08 | E55: =IFERROR(B55-C55-D55," ")
A56: 110 | B56: =IFERROR(VLOOKUP(A56,Actuals!$H$1722:$I$1819,2,0)," ") -> 2.9916211e+08 | C56: =IFERROR(VLOOKUP(A56,Actuals!$N$44:$O$129,2,0)," ") | D56: =IFERROR(VLOOKUP(A56,Actuals!$H$1722:$J$1819,3,0)," ") -> 2.9916211e+08 | E56: =IFERROR(B56-C56-D56," ")
A57: 111 | B57: =IFERROR(VLOOKUP(A57,Actuals!$H$1722:$I$1819,2,0)," ") -> 16500000 | C57: =IFERROR(VLOOKUP(A57,Actuals!$N$44:$O$129,2,0)," ") | D57: =IFERROR(VLOOKUP(A57,Actuals!$H$1722:$J$1819,3,0)," ") -> 16500000 | E57: =IFERROR(B57-C57-D57," ")
A58: 112 | B58: =IFERROR(VLOOKUP(A58,Actuals!$H$1722:$I$1819,2,0)," ") -> 4.1902155e+08 | C58: =IFERROR(VLOOKUP(A58,Actuals!$N$44:$O$129,2,0)," ") | D58: =IFERROR(VLOOKUP(A58,Actuals!$H$1722:$J$1819,3,0)," ") -> 4.1902155e+08 | E58: =IFERROR(B58-C58-D58," ")
A59: I240188 | B59: =IFERROR(VLOOKUP(A59,Actuals!$H$1722:$I$1819,2,0)," ") -> 1.0815963e+08 | C59: =IFERROR(VLOOKUP(A59,Actuals!$N$44:$O$129,2,0)," ") -> 32303880 | D59: =IFERROR(VLOOKUP(A59,Actuals!$H$1722:$J$1819,3,0)," ") -> 11498885 | E59: =IFERROR(B59-C59-D59," ") -> 64356866
A60: I240189 | B60: =IFERROR(VLOOKUP(A60,Actuals!$H$1722:$I$1819,2,0)," ") -> 1.2862079e+08 | C60: =IFERROR(VLOOKUP(A60,Actuals!$N$44:$O$129,2,0)," ") -> 48635714 | D60: =IFERROR(VLOOKUP(A60,Actuals!$H$1722:$J$1819,3,0)," ") -> 21340968 | E60: =IFERROR(B60-C60-D60," ") -> 58644104
A61: I240190 | B61: =IFERROR(VLOOKUP(A61,Actuals!$H$1722:$I$1819,2,0)," ") -> 1.3382738e+08 | C61: =IFERROR(VLOOKUP(A61,Actuals!$N$44:$O$129,2,0)," ") -> 23221418 | D61: =IFERROR(VLOOKUP(A61,Actuals!$H$1722:$J$1819,3,0)," ") -> 26296056 | E61: =IFERROR(B61-C61-D61," ") -> 84309901
A62: I240435 | B62: =IFERROR(VLOOKUP(A62,Actuals!$H$1722:$I$1819,2,0)," ") -> 2.4849986e+08 | C62: =IFERROR(VLOOKUP(A62,Actuals!$N$44:$O$129,2,0)," ") -> 67652365 | D62: =IFERROR(VLOOKUP(A62,Actuals!$H$1722:$J$1819,3,0)," ") -> 48350596 | E62: =IFERROR(B62-C62-D62," ") -> 1.324969e+08
A63: I240437 | B63: =IFERROR(VLOOKUP(A63,Actuals!$H$1722:$I$1819,2,0)," ") -> 2.8598643e+08 | C63: =IFERROR(VLOOKUP(A63,Actuals!$N$44:$O$129,2,0)," ") -> 32014191 | D63: =IFERROR(VLOOKUP(A63,Actuals!$H$1722:$J$1819,3,0)," ") -> 1.849719e+08 | E63: =IFERROR(B63-C63-D63," ") -> 69000334
A64: I240438 | B64: =IFERROR(VLOOKUP(A64,Actuals!$H$1722:$I$1819,2,0)," ") -> 1.9785014e+08 | C64: =IFERROR(VLOOKUP(A64,Actuals!$N$44:$O$129,2,0)," ") -> 81236524 | D64: =IFERROR(VLOOKUP(A64,Actuals!$H$1722:$J$1819,3,0)," ") -> 1.0479376e+08 | E64: =IFERROR(B64-C64-D64," ") -> 11819858
A65: I240440 | B65: =IFERROR(VLOOKUP(A65,Actuals!$H$1722:$I$1819,2,0)," ") -> 3.8074728e+08 | C65: =IFERROR(VLOOKUP(A65,Actuals!$N$44:$O$129,2,0)," ") -> 26049440 | D65: =IFERROR(VLOOKUP(A65,Actuals!$H$1722:$J$1819,3,0)," ") -> 1.5974547e+08 | E65: =IFERROR(B65-C65-D65," ") -> 1.9495237e+08
A66: I240442 | B66: =IFERROR(VLOOKUP(A66,Actuals!$H$1722:$I$1819,2,0)," ") -> 1.2082465e+08 | C66: =IFERROR(VLOOKUP(A66,Actuals!$N$44:$O$129,2,0)," ") -> 12671695 | D66: =IFERROR(VLOOKUP(A66,Actuals!$H$1722:$J$1819,3,0)," ") -> 76638796 | E66: =IFERROR(B66-C66-D66," ") -> 31514161
A67: I240459 | B67: =IFERROR(VLOOKUP(A67,Actuals!$H$1722:$I$1819,2,0)," ") -> 12138005 | C67: =IFERROR(VLOOKUP(A67,Actuals!$N$44:$O$129,2,0)," ") -> 48327875 | D67: =IFERROR(VLOOKUP(A67,Actuals!$H$1722:$J$1819,3,0)," ") -> 2044350.8 | E67: =IFERROR(B67-C67-D67," ") -> -38234221
A68: I240518 | B68: =IFERROR(VLOOKUP(A68,Actuals!$H$1722:$I$1819,2,0)," ") -> 1.1205061e+08 | C68: =IFERROR(VLOOKUP(A68,Actuals!$N$44:$O$129,2,0)," ") -> 2778864.9 | D68: =IFERROR(VLOOKUP(A68,Actuals!$H$1722:$J$1819,3,0)," ") -> 21773385 | E68: =IFERROR(B68-C68-D68," ") -> 87498357
A69: I240519 | B69: =IFERROR(VLOOKUP(A69,Actuals!$H$1722:$I$1819,2,0)," ") -> 2.9758151e+08 | C69: =IFERROR(VLOOKUP(A69,Actuals!$N$44:$O$129,2,0)," ") -> 5337898.4 | D69: =IFERROR(VLOOKUP(A69,Actuals!$H$1722:$J$1819,3,0)," ") -> 2.8848267e+08 | E69: =IFERROR(B69-C69-D69," ") -> 3760941.6
A70: I240537 | B70: =IFERROR(VLOOKUP(A70,Actuals!$H$1722:$I$1819,2,0)," ") -> 23356438 | C70: =IFERROR(VLOOKUP(A70,Actuals!$N$44:$O$129,2,0)," ") -> 21906187 | D70: =IFERROR(VLOOKUP(A70,Actuals!$H$1722:$J$1819,3,0)," ") -> 4885213.3 | E70: =IFERROR(B70-C70-D70," ") -> -3434961.7
... A143: INT-23-00764 | B143: =IFERROR(VLOOKUP(A143,Actuals!$H$1722:$I$1819,2,0)," ") -> 3.5004237e+08 | C143: =IFERROR(VLOOKUP(A143,Actuals!$N$44:$O$129,2,0)," ") -> 57769976 | D143: =IFERROR(VLOOKUP(A143,Actuals!$H$1722:$J$1819,3,0)," ") -> 1.3337187e+08 | E143: =IFERROR(B143-C143-D143," ") -> 1.5890053e+08
A144: Grand Total

Sheet Standardized Comments
A1: Number of CEMs | B1: =COUNT(B4:B98) -> 10
A3: Row Labels | B3: Count of Fesibility Name
A4: LIVE - 100% Completed | B4: 512
A5: LIVE - 25% Completed | B5: 1
A6: LIVE - 50% Completed | B6: 6
A7: LIVE - 60% Completed | B7: 3
A8: LIVE - 80% Completed | B8: 5
A9: NOT LIVE - RETAIN BUDGET | B9: 533
A10: REMOVE BUDGET (P) | B10: 43
A11: REMOVE BUDGET (T) | B11: 19
A12: SWAPPED | B12: 28
A13: Grand Total | B13: 1150

Sheet Swap Details
F2: =+SUBTOTAL(9,F6:F33) -> 16264 | G2: =+SUBTOTAL(9,G6:G33) -> 6557.4 | H2: =+SUBTOTAL(9,H6:H33) -> 2.1767701e+08 | L2: =+SUBTOTAL(9,L6:L33)-SUM(L8:L16,L22,L20,L27,L29,L30,L31) -> 1.3262552e+08 | M2: =+SUBTOTAL(9,M6:M33)-SUM(M8:M16,M22,M20,M27,M29,M30,M31) -> 5144
A5: CEM Number | B5: CEM Initiation Date | C5: City Name | D5: Fesibility Name | E5: Area / Section / Pocket / Society (Original Name) | F5: Total H.P | G5: Customers According to % (Market Share) | H5: Allocated Budget | I5: Total Civil works - Buried | J5: Total Civil works - Arial | K5: Swapped With - | L5: Swapped/Removal Budget | M5: HP - Revised
A6: I250207 | B6: 45547 | C6: Abbottabad | D6: Abbottabad | E6: Salhad | F6: 700 | G6: 280 | H6: 13746943 | I6: 2963.1422 | J6: 19896.044 | K6: Banda Jaat & Iqbal Road | L6: 0 | M6: ?
A7: I250206 | B7: 45547 | C7: Daska | D7: Daska | E7: Bhatti Colony | F7: 536 | G7: 214.4 | H7: 5635736 | I7: 992.46265 | J7: 4986.8027 | K7: Meraj Housing | L7: 22604832 | M7: 542
A8: I250206 | B8: 45547 | C8: Daska | D8: Daska | E8: Faisal_Town | F8: 320 | G8: 128 | H8: 5536549 | I8: 1147.7 | J8: 4422.5 | K8: Meraj Housing | L8: 22604832 | M8: 542
A9: I250206 | B9: 45547 | C9: Daska | D9: Daska | E9: Islampura | F9: 1132 | G9: 452.8 | H9: 8329511.4 | I9: 961.4 | J9: 9642.5 | K9: Meraj Housing | L9: 22604832 | M9: 542
A10: I250206 | B10: 45547 | C10: Daska | D10: Daska | E10: Rehmanpura | F10: 652 | G10: 260.8 | H10: 6639116.5 | I10: 1094.8 | J10: 6366 | K10: Meraj Housing | L10: 22604832 | M10: 542
A11: I250206 | B11: 45547 | C11: Daska | D11: Daska | E11: Unknown Society 20 | F11: 424 | G11: 169.6 | H11: 4694817.2 | I11: 833.75 | J11: 4094.8 | K11: Meraj Housing | L11: 22604832 | M11: 542
A12: I250206 | B12: 45547 | C12: Daska | D12: Daska | E12: Unknown Society_22 | F12: 418 | G12: 167.2 | H12: 4623068.2 | I12: 792.35 | J12: 4278 | K12: Meraj Housing | L12: 22604832 | M12: 542
A13: I250206 | B13: 45547 | C13: Daska | D13: Daska | E13: Unkown Society 17 | F13: 208 | G13: 83.2 | H13: 2299604 | I13: 366.85 | J13: 1911.1 | K13: Meraj Housing | L13: 22604832 | M13: 542
A14: I250206 | B14: 45547 | C14: Daska | D14: Daska | E14: Unkown Society 18 | F14: 154 | G14: 61.6 | H14: 2190435 | I14: 411.7 | J14: 1274.55 | K14: Meraj Housing | L14: 22604832 | M14: 542
A15: I250206 | B15: 45547 | C15: Daska | D15: Daska | E15: Unkown Society 19 | F15: 94 | G15: 37.6 | H15: 1473900.8 | I15: 209.3 | J15: 919.3 | K15: Meraj Housing | L15: 22604832 | M15: 542
A16: I250206 | B16: 45547 | C16: Daska | D16: Daska | E16: Unkown Society 24 | F16: 66 | G16: 26.4 | H16: 1047427.5 | I16: 143.75 | J16: 587.25 | K16: Meraj Housing | L16: 22604832 | M16: 542
A17: I240682 | B17: 45428 | C17: Faisalabad | D17: Faisalabad Ph4 | E17: Al Barkat Villas | F17: 190 | G17: 76 | H17: 3623949.2 | I17: 809.6 | J17: 1873.2538 | K17: City Walk | L17: 4637080.9 | M17: 254
A18: I240682 | B18: 45428 | C18: Faisalabad | D18: Faisalabad Ph4 | E18: Khy-e-Manzoor | F18: 432 | G18: 172.8 | H18: 5761950.4 | I18: 1139.65 | J18: 4442.475 | K18: Pine Garden | L18: 0 | M18: ?!
A19: I240702 | B19: 45427 | C19: Hyderabad | D19: Hyderabad | E19: Latifabad No 09 | F19: 1316 | G19: 526.4 | H19: 15091681 | I19: 2605.9 | J19: 11969.406 | K19: Latifabad #2 | L19: 7901516.4 | M19: 858
A20: I250205 | B20: 45547 | C20: Jhelum | D20: Jhelum Ph2 | E20: Chal Jamal | F20: 312 | G20: 124.8 | H20: 5688153 | I20: 1657.15 | J20: 5093.85 | K20: Gharmala, Gharmala Monan & Chittan | L20: 5811629.1 | M20: 628
A21: I250205 | B21: 45547 | C21: Jhelum | D21: Jhelum Ph2 | E21: Shamas Pur | F21: 198 | G21: 79.2 | H21: 2131178 | I21: 409.4 | J21: 1628.35 | K21: Gharmala, Gharmala Monan & Chittan | L21: 5811629.1 | M21: 628
A22: I240705 | B22: 45427 | C22: Karachi | D22: Karachi Ph5 | E22: Khayaban-e-Patni CHS | F22: 212 | G22: 84.8 | H22: 4887798.5 | I22: 1079.9494 | J22: 2731.3402 | K22: Hansa | L22: 9247426 | M22: 0
A23: I240705 | B23: 45427 | C23: Karachi | D23: Karachi Ph5 | E23: Kokan CHS | F23: 346 | G23: 138.4 | H23: 11269033 | I23: 2155.1646 | J23: 5318.6079 | K23: Hansa | L23: 9247426 | M23: 0
A24: I250213 | B24: 45549 | C24: Mardan | D24: Mardan | E24: Mohabatabad P1 | F24: 340 | G24: 136 | H24: 4566394 | I24: 845.25 | J24: 3726.45 | K24: new muhabbatabad | L24: 0 | M24: ?
A25: I250213 | B25: 45549 | C25: Mardan | D25: Mardan | E25: Mohabatabad P2 | F25: 456 | G25: 182.4 | H25: 5853007.9 | I25: 1220.15 | J25: 4251.57 | K25: new muhabbatabad | L25: 0 | M25: ?
A26: INT-23-00439 | B26: 44924 | C26: Multan | D26: Multan Misc. Areas | E26: Defence Housing Society | F26: 518 | G26: 259 | H26: 12724228 | I26: 6884.6077 | J26: 6437.5466 | K26: Pace City and White House Scoiety | L26: 11729455 | M26: 844
A27: I240684 | B27: 45428 | C27: Rawalpindi | D27: Askari RWP (4-7-10) | E27: Askari-7 P1 | F27: 472 | G27: 188.8 | H27: 6238771.3 | I27: 1938.3435 | J27: 1150.534 | K27: Askari 12 | L27: 6355978.3 | M27: 160
A28: I240684 | B28: 45428 | C28: Rawalpindi | D28: Askari RWP (4-7-10) | E28: Askari-7 P2 | F28: 964 | G28: 385.6 | H28: 14207823 | I28: 4421.6685 | J28: 3298.834 | K28: Askari 12 | L28: 6355978.3 | M28: 160
A29: I250209 | B29: 45549 | C29: Rawalpindi | D29: Rawalpindi | E29: Gulshanabad P01 | F29: 1758 | G29: 703.2 | H29: 17094645 | I29: 2826.7 | J29: 19588.601 | K29: G-16 developed part only | L29: 54483572 | M29: 1606
A30: I250209 | B30: 45549 | C30: Rawalpindi | D30: Rawalpindi | E30: Gulshanabad P02 | F30: 1470 | G30: 588 | H30: 16562639 | I30: 3055.55 | J30: 20330.037 | K30: G-16 developed part only | L30: 54483572 | M30: 1606
A31: I250209 | B31: 45549 | C31: Rawalpindi | D31: Rawalpindi | E31: Gulshanabad P03 | F31: 916 | G31: 366.4 | H31: 11424746 | I31: 2458.7 | J31: 10956.301 | K31: G-16 developed part only | L31: 54483572 | M31: 1606
A32: I250209 | B32: 45549 | C32: Rawalpindi | D32: Rawalpindi | E32: Sanobar City | F32: 1454 | G32: 581.6 | H32: 11170103 | I32: 1561.7 | J32: 12560.364 | K32: G-16 developed part only | L32: 54483572 | M32: 1606
A33: I250210 | B33: 45549 | C33: Sargodha | D33: Sargodha | E33: Remount Depot | F33: 206 | G33: 82.4 | H33: 13163801 | I33: 3986.2481 | J33: 6688.1052 | K33: Grand A-1 City | L33: 9854031.3 | M33: 252
C41: Summary - Swaps
C43: Cost | D43: Allocated Budget | E43: =H2 -> 2.1767701e+08
C44: Cost | D44: Swapped Budget | E44: =L2 -> 1.3262552e+08
C45: Revenue | D45: Allocated Budget | E45: =F2 -> 16264
C46: Revenue | D46: Swapped Budget | E46: =M2 -> 5144
C47: Cost | D47: Dip | E47: =(E44-E43)/E43 -> -0.39072334
C48: Revenue | D48: Dip | E48: =(E46-E45)/E45 -> -0.68371864

Sheet Actuals
B3: Number of Total Areas | C3: =SUBTOTAL(9,C6:C203)/2 -> 1.8581034e+10 | D3: =SUBTOTAL(9,D6:D203)/2 -> 8.480651e+09 | E3: =SUBTOTAL(9,E6:E203)/2 -> 1.0135167e+10 | H3: Number of Total Areas | I3: 2.209571e+10 | J3: 1.0815617e+10 | K3: 1.0712793e+10
B5: Row Labels | C5: Sum of Allocated Budget | D5: Sum of Revised Budget | E5: Sum of Difference | H5: Row Labels | I5: Sum of Allocated Budget | J5: Sum of Revised Budget | K5: Sum of Difference
B6: Abbottabad | C6: 46635361 | D6: 4933262.7 | E6: 41702098 | H6: Abbottabad | I6: 46635361 | J6: 4933262.7 | K6: 41702098
B7: Bahawalpur | C7: 2.3472034e+08 | D7: 78068027 | E7: 48751767 | H7: Bahawalpur | I7: 2.3472034e+08 | J7: 78068027 | K7: 48751767
B8: Chitral | C8: 1.0745748e+08 | D8: 69955211 | E8: 37502271 | H8: Chitral | I8: 1.0745748e+08 | J8: 69955211 | K8: 37502271
B9: Daska | C9: 2.3819094e+08 | D9: 1.5004045e+08 | E9: 88150495 | H9: Daska | I9: 2.3819094e+08 | J9: 1.5004045e+08 | K9: 88150495
B10: Dera Ghazi Khan | C10: 4.1567031e+08 | D10: 4.1567031e+08 | H10: Dera Ghazi Khan | I10: 4.1567031e+08 | J10: 4.1567031e+08
B11: Faisalabad | C11: 7.1513106e+08 | D11: 91398554 | E11: 5.6781073e+08 | H11: Faisalabad | I11: 7.1513106e+08 | J11: 91398554 | K11: 5.6781073e+08
B12: Gujranwala | C12: 1.6429799e+09 | D12: 5.917392e+08 | E12: 1.0158168e+09 | H12: Feeders/Transportations | I12: 3.5146755e+09 | J12: 2.334966e+09 | K12: 1.1930728e+09
B13: Hafizabad | C13: 2.525768e+08 | D13: 2.525768e+08 | H13: Gujranwala | I13: 1.6429799e+09 | J13: 5.917392e+08 | K13: 1.0158168e+09
B14: Haripur | C14: 1.661863e+08 | D14: 37229960 | E14: 1.2895634e+08 | H14: Hafizabad | I14: 2.525768e+08 | J14: 2.525768e+08
B15: Hyderabad | C15: 2.4718492e+08 | D15: 62007416 | E15: 1.7899249e+08 | H15: Haripur | I15: 1.661863e+08 | J15: 37229960 | K15: 1.2895634e+08
B16: Islamabad | C16: 1.8992789e+09 | D16: 8.5374564e+08 | E16: 1.0404171e+09 | H16: Hyderabad | I16: 2.4718492e+08 | J16: 62007416 | K16: 1.7899249e+08
B17: Jhang | C17: 1.9091471e+08 | D17: 1.9091471e+08 | H17: Islamabad | I17: 1.8992789e+09 | J17: 8.5374564e+08 | K17: 1.0404171e+09
B18: Jhelum | C18: 1.7292679e+08 | D18: 71668193 | E18: 51090933 | H18: Jhang | I18: 1.9091471e+08 | J18: 1.9091471e+08
B19: Karachi | C19: 2.1482582e+09 | D19: 9.1201307e+08 | E19: 1.1443347e+09 | H19: Jhelum | I19: 1.7292679e+08 | J19: 71668193 | K19: 51090933
B20: Kasur | C20: 2.7718237e+08 | D20: 2.762782e+08 | H20: Karachi | I20: 2.1482582e+09 | J20: 9.1201307e+08 | K20: 1.1443347e+09
B21: Lahore | C21: 4.6871497e+09 | D21: 2.1832791e+09 | E21: 2.378936e+09 | H21: Kasur | I21: 2.7718237e+08 | J21: 2.762782e+08
B22: Lalamusa | C22: 1.5178954e+08 | D22: 1.5178954e+08 | H22: Lahore | I22: 4.6871497e+09 | J22: 2.1832791e+09 | K22: 2.378936e+09
B23: Mandi Bahauddin | C23: 3.0304575e+08 | D23: 3.0304575e+08 | H23: Lalamusa | I23: 1.5178954e+08 | J23: 1.5178954e+08
B24: Mardan | C24: 1.9876333e+08 | D24: 27323022 | E24: 1.714403e+08 | H24: Mandi Bahauddin | I24: 3.0304575e+08 | J24: 3.0304575e+08
B25: Multan | C25: 1.2777487e+09 | D25: 4.440241e+08 | E25: 8.0609967e+08 | H25: Mardan | I25: 1.9876333e+08 | J25: 27323022 | K25: 1.714403e+08
B26: Narowal | C26: 2.7474469e+08 | D26: 2.7474469e+08 | H26: Multan | I26: 1.2777487e+09 | J26: 4.440241e+08 | K26: 8.0609967e+08
B27: Okara | C27: 1.024588e+08 | D27: 15368820 | E27: 87089979 | H27: Narowal | I27: 2.7474469e+08 | J27: 2.7474469e+08
B28: Peshawar | C28: 3.0707597e+08 | D28: 99622300 | E28: 2.0745367e+08 | H28: Okara | I28: 1.024588e+08 | J28: 15368820 | K28: 87089979
B29: Quetta | C29: 1.3533896e+08 | D29: 22356218 | E29: 1.1298274e+08 | H29: Peshawar | I29: 3.0707597e+08 | J29: 99622300 | K29: 2.0745367e+08
B30: Rahim Yar Khan | C30: 1.1107145e+08 | D30: 14964640 | E30: 96106805 | H30: Quetta | I30: 1.3533896e+08 | J30: 22356218 | K30: 1.1298274e+08
B31: Rawalpindi | C31: 1.7727756e+08 | D31: 47104579 | E31: 1.3017298e+08 | H31: Rahim Yar Khan | I31: 1.1107145e+08 | J31: 14964640 | K31: 96106805
B32: Sadiqabad | C32: 3.5043392e+08 | D32: 3.5043392e+08 | H32: Rawalpindi | I32: 1.7727756e+08 | J32: 47104579 | K32: 1.3017298e+08
B33: Sahiwal | C33: 85781337 | D33: 42199240 | E33: 39901742 | H33: Sadiqabad | I33: 3.5043392e+08 | J33: 3.5043392e+08
B34: Sargodha | C34: 1.9330305e+08 | D34: 50749454 | E34: 1.425536e+08 | H34: Sahiwal | I34: 85781337 | J34: 42199240 | K34: 39901742
B35: Sialkot | C35: 4.8328493e+08 | D35: 1.4187399e+08 | E35: 3.4141093e+08 | H35: Sargodha | I35: 1.9330305e+08 | J35: 50749454 | K35: 1.425536e+08
B36: Swat | C36: 4.659263e+08 | D36: 93712460 | E36: 3.6429266e+08 | H36: Sialkot | I36: 4.8328493e+08 | J36: 1.4187399e+08 | K36: 3.4141093e+08
B37: Torkhan Border | C37: 125214350 | D37: 18782152 | E37: 1.064322e+08 | H37: Swat | I37: 4.659263e+08 | J37: 93712460 | K37: 3.6429266e+08
B38: Wahh | C38: 2.1079129e+08 | D38: 19469859 | E38: 1.9132143e+08 | H38: Torkhan Border | I38: 125214350 | J38: 18782152 | K38: 1.064322e+08
B39: Sukkur | C39: 1.8454016e+08 | D39: 1.2156825e+08 | H39: Wahh | I39: 2.1079129e+08 | J39: 19469859 | K39: 1.9132143e+08
B40: Grand Total | C40: 1.8581034e+10 | D40: 8.480651e+09 | E40: 9.5197204e+09 | H40: Sukkur | I40: 1.8454016e+08 | J40: 1.2156825e+08
H41: Grand Total | I41: 2.209571e+10 | J41: 1.0815617e+10 | K41: 1.0712793e+10
B44: CEMz | C44: Orders | D44: Details | E44: Budget | F44: Actual | G44: Commitment | H44: Assigned | I44: Available | K44: Row Labels | L44: Sum of Actual | N44: Row Labels | O44: Sum of Actual
B45: I240188 | C45: I240188000 | D45: StormFiber Expansion – DHA | E45: 6606972.9 | F45: 6606972.9 | H45: 6606972.9 | K45: I240188 | L45: 32303880 | N45: I240188 | O45: 32303880
B46: I240188 | C46: I240188001 | D46: Cabinets & Accessories - | E46: 8597643.8 | F46: 52195.56 | H46: 52195.56 | I46: 8545448.3 | K46: I240189 | L46: 48635714 | N46: I240189 | O46: 48635714
B47: I240188 | C47: I240188002 | D47: Consumable & Accessories | E47: 2553619.6 | F47: 23156.47 | H47: 23156.47 | I47: 2530463.1 | K47: I240190 | L47: 23221418 | N47: I240190 | O47: 23221418
B48: I240188 | C48: I240188003 | D48: Cables - (Feeder Access | E48: 4367822.5 | F48: 741397.52 | H48: 741397.52 | I48: 3626425 | K48: I240435 | L48: 67652365 | N48: I240435 | O48: 67652365
B49: I240188 | C49: I240188004 | D49: Enclosures - (Feeder Ac | E49: 1011367.6 | F49: 1269.94 | H49: 1269.94 | I49: 1010097.6 | K49: I240437 | L49: 32014191 | N49: I240437 | O49: 32014191
B50: I240188 | C50: I240188005 | D50: Splitters - (Access & Dis | E50: 1628109.6 | F50: 18464.24 | H50: 18464.24 | I50: 1609645.3 | K50: I240438 | L50: 81236524 | N50: I240438 | O50: 81236524
B51: I240188 | C51: I240188006 | D51: Duct - (HDPE / GI with | E51: 3795144 | I51: 3795144 | K51: I240440 | L51: 26049440 | N51: I240440 | O51: 26049440
B52: I240188 | C52: I240188007 | D52: Handholes - (HH / Chamb | E52: 8004000 | I52: 8004000 | K52: I240442 | L52: 12671695 | N52: I240442 | O52: 12671695
B53: I240188 | C53: I240188008 | D53: FDT Foundation | E53: 40000 | I53: 40000 | K53: I240459 | L53: 48327875 | N53: I240459 | O53: 48327875
B54: I240188 | C54: I240188009 | D54: Infrastructure Laying - | E54: 5764812 | F54: 212290 | G54: 4102970 | H54: 4315260 | I54: 1449552 | K54: I240518 | L54: 2778864.9 | N54: I240518 | O54: 2778864.9
B55: I240188 | C55: I240188010 | D55: Cable Hauling - (Aerial | E55: 2679920.4 | F55: 10770 | H55: 10770 | I55: 2669150.4 | K55: I240519 | L55: 5337898.4 | N55: I240519 | O55: 5337898.4
B56: I240188 | C56: I240188011 | D56: Building Attachments - | E56: 990000 | I56: 990000 | K56: I240537 | L56: 21906187 | N56: I240537 | O56: 21906187
B57: I240188 | C57: I240188012 | D57: Transportation - (Vehic | E57: 900000 | I57: 900000 | K57: I240538 | L57: 30224940 | N57: I240538 | O57: 30224940
B58: I240188 | C58: I240188013 | D58: Tool Kit - (Access) | E58: 150000 | F58: 109800 | H58: 109800 | I58: 40200 | K58: I240539 | L58: 50550349 | N58: I240539 | O58: 50550349
B59: I240188 | C59: I240188014 | D59: Tool Kit - (Dev.) | E59: 80000 | I59: 80000 | K59: I240540 | L59: 20154770 | N59: I240540 | O59: 20154770
B60: I240188 | C60: I240188015 | D60: Cable prepartion Tools - | E60: 150000 | I60: 150000 | K60: I240557 | L60: 48265830 | N60: I240557 | O60: 48265830
B61: I240188 | C61: I240188016 | D61: Splice Machine | E61: 800000 | I61: 800000 | K61: I240678 | L61: 34886785 | N61: I240678 | O61: 34886785
B62: I240188 | C62: I240188017 | D62: Cleavers | E62: 400000 | I62: 400000 | K62: I240679 | L62: 12874811 | N62: I240679 | O62: 12874811
B63: I240188 | C63: I240188018 | D63: VFLS | E63: 100000 | I63: 100000 | K63: I240680 | L63: 11241889 | N63: I240680 | O63: 11241889
B64: I240188 | C64: I240188019 | D64: PON Power Meters. | E64: 600000 | I64: 600000 | K64: I240681 | L64: 1.0884325e+08 | N64: I240681 | O64: 1.0884325e+08
B65: I240188 | C65: I240188020 | D65: CATV Transmission Equipmen | E65: 2094400 | F65: 894755.6 | H65: 894755.6 | I65: 1199644.4 | K65: I240682 | L65: 44345651 | N65: I240682 | O65: 44345651
B66: I240188 | C66: I240188021 | D66: PON cards | E66: 2156000 | I66: 2156000 | K66: I240683 | L66: 16462579 | N66: I240683 | O66: 16462579
B67: I240188 | C67: I240188022 | D67: Bolan | E67: 3600000 | I67: 3600000 | K67: I240684 | L67: 47923741 | N67: I240684 | O67: 47923741
B68: I240188 | C68: I240189000 | D68: StormFiber Expansion – Que | E68: 23632808 | F68: 23632808 | H68: 23632808 | K68: I240700 | L68: 30109711 | N68: I240700 | O68: 30109711
B69: I240189 | C69: I240189001 | D69: Cabinets & Accessories - | E69: 3498481.4 | F69: 416841.66 | H69: 416841.66 | I69: 3081639.7 | K69: I240701 | L69: 41959381 | N69: I240701 | O69: 41959381
B70: I240189 | C70: I240189002 | D70: Consumable & Accessories | E70: 2357620.9 | F70: 1822312.2 | H70: 1822312.2 | I70: 535308.71 | K70: I240702 | L70: 1.3516647e+08 | N70: I240702 | O70: 1.3516647e+08
B71: I240189 | C71: I240189003 | D71: Cables - (Feeder Access | E71: 21840678 | F71: 3295504.3 | H71: 3295504.3 | I71: 18545174 | K71: I240703 | L71: 1.1053422e+08 | N71: I240703 | O71: 1.1053422e+08
B72: I240189 | C72: I240189004 | D72: Enclosures - (Feeder Ac | E72: 913937.53 | F72: 51921.69 | H72: 51921.69 | I72: 862015.84 | K72: I240704 | L72: 1.0629108e+08 | N72: I240704 | O72: 1.0629108e+08
B73: I240189 | C73: I240189005 | D73: Splitters - (Access & Dis | E73: 972582.45 | F73: 127163.68 | H73: 127163.68 | I73: 845418.77 | K73: I240705 | L73: 99528765 | N73: I240705 | O73: 99528765
B74: I240189 | C74: I240189006 | D74: Duct - (HDPE / GI with | E74: 24188045 | I74: 24188045 | K74: I240782 | L74: 6399057.1 | N74: I240782 | O74: 6399057.1
B75: I240189 | C75: I240189007 | D75: Handholes - (HH / Chamb | E75: 4112000 | I75: 4112000 | K75: I250114 | L75: 9911416.8 | N75: I250114 | O75: 9911416.8
B76: I240189 | C76: I240189008 | D76: Poles | E76: 168000 | I76: 168000 | K76: I250201 | L76: 2914326.9 | N76: I250201 | O76: 2914326.9
B77: I240189 | C77: I240189009 | D77: FDT Foundation | E77: 100000 | I77: 100000 | K77: I250202 | L77: 6064833.3 | N77: I250202 | O77: 6064833.3
B78: I240189 | C78: I240189010 | D78: Infrastructure Laying - | E78: 26376051 | I78: 26376051 | K78: I250203 | L78: 10830900 | N78: I250203 | O78: 10830900
B79: I240189 | C79: I240189011 | D79: Cable Hauling - (Aerial | E79: 3384838.5 | I79: 3384838.5 | K79: I250205 | L79: 9650887.1 | N79: I250205 | O79: 9650887.1
B80: I240189 | C80: I240189012 | D80: Building Attachments - | E80: 1844500 | I80: 1844500 | K80: I250206 | L80: 37654770 | N80: I250206 | O80: 37654770
B81: I240189 | C81: I240189013 | D81: Transportation - (Vehic | E81: 3050000 | F81: 233720 | H81: 233720 | I81: 2816280 | K81: I250207 | L81: 8876461.5 | N81: I250207 | O81: 8876461.5
B82: I240189 | C82: I240189014 | D82: Tool Kit - (Access) | E82: 150000 | F82: 126830 | H82: 126830 | I82: 23170 | K82: I250208 | L82: 12376240 | N82: I250208 | O82: 12376240
B83: I240189 | C83: I240189015 | D83: Tool Kit - (Dev.) | E83: 120000 | I83: 120000 | K83: I250209 | L83: 54634503 | N83: I250209 | O83: 54634503
B84: I240189 | C84: I240189016 | D84: Cable prepartion Tools - | E84: 450000 | F84: 2499.99 | H84: 2499.99 | I84: 447500.01 | K84: I250210 | L84: 18557157 | N84: I250210 | O84: 18557157
B85: I240189 | C85: I240189017 | D85: Splice Machine | E85: 1400000 | F85: 737898.01 | H85: 737898.01 | I85: 662101.99 | K85: I250211 | L85: 37329299 | N85: I250211 | O85: 37329299
B86: I240189 | C86: I240189018 | D86: Cleavers | E86: 240000 | F86: 190000 | H86: 190000 | I86: 50000 | K86: I250212 | L86: 21624782 | N86: I250212 | O86: 21624782
B87: I240189 | C87: I240189019 | D87: VFLs | E87: 120000 | I87: 120000 | K87: I250213 | L87: 15484689 | N87: I250213 | O87: 15484689
B88: I240189 | C88: I240189020 | D88: OTDR - For Core / FTTH b | E88: 1075000 | I88: 1075000 | K88: I250298 | L88: 80833806 | N88: I250298 | O88: 80833806
B89: I240189 | C89: I240189021 | D89: PON Power Meters. | E89: 480000 | F89: 192174.13 | H89: 192174.13 | I89: 287825.87 | K89: I250307 | L89: 50504525 | N89: I250307 | O89: 50504525
B90: I240189 | C90: I240189022 | D90: CATV Transmission Equipmen | E90: 2372402.2 | F90: 894755.6 | H90: 894755.6 | I90: 1477646.6 | K90: I250326 | L90: 29990114 | N90: I250326 | O90: 29990114
B91: I240189 | C91: I240189023 | D91: PON Cards | E91: 3407400 | I91: 3407400 | K91: I250327 | L91: 18753966 | N91: I250327 | O91: 18753966
B92: I240189 | C92: I240189024 | D92: Bolan | E92: 4335120.7 | F92: 16386.78 | H92: 16386.78 | I92: 4318734 | K92: I250374 | L92: 0 | N92: I250374 | O92: 0
B93: I240189 | C93: I240190000 | D93: StormFiber Expansion – Sia | E93: 40527706 | F93: 40527706 | H93: 40527706 | K93: I250375 | L93: 13863425 | N93: I250375 | O93: 13863425
B94: I240190 | C94: I240190001 | D94: Cabinets & Accessories - | E94: 4326752.6 | F94: 253812.83 | H94: 253812.83 | I94: 4072939.8 | K94: I250376 | L94: 72610872 | N94: I250376 | O94: 72610872
B95: I240190 | C95: I240190002 | D95: Consumable & Accessories | E95: 1657151.4 | F95: 1354458.9 | H95: 1354458.9 | I95: 302692.52 | K95: I250377 | L95: 12761740 | N95: I250377 | O95: 12761740
B96: I240190 | C96: I240190003 | D96: Cables - (Feeder Access | E96: 12392349 | F96: 4056681.2 | H96: 4056681.2 | I96: 8335668.3 | K96: I250378 | L96: 15200322 | N96: I250378 | O96: 15200322
B97: I240190 | C97: I240190004 | D97: Enclosures - (Feeder Ac | E97: 653599.8 | F97: 111050.93 | H97: 111050.93 | I97: 542548.87 | K97: I250379 | L97: 1.1595584e+08 | N97: I250379 | O97: 1.1595584e+08
B98: I240190 | C98: I240190005 | D98: Splitters - (Access & Dis | E98: 789646.42 | F98: 34641.72 | H98: 34641.72 | I98: 755004.7 | K98: I250380 | L98: 11888900 | N98: I250380 | O98: 11888900
B99: I240190 | C99: I240190006 | D99: Duct - (HDPE / GI with | E99: 39249550 | F99: 18541.86 | H99: 18541.86 | I99: 39231009 | K99: I250681 | L99: 11082543 | N99: I250681 | O99: 11082543
B100: I240190 | C100: I240190007 | D100: Handholes - (HH / Chamb | E100: 7293500 | I100: 7293500 | K100: I250734 | L100: 21098168 | N100: I250734 | O100: 21098168
B101: I240190 | C101: I240190008 | D101: Poles | E101: 560000 | I101: 560000 | K101: I250737 | L101: 24952502 | N101: I250737 | O101: 24952502
B102: I240190 | C102: I240190009 | D102: FDT Foundation | E102: 100000 | I102: 100000 | K102: I260060 | L102: 6618364.3 | N102: I260060 | O102: 6618364.3
B103: I240190 | C103: I240190010 | D103: Infrastructure Laying - | E103: 15558348 | I103: 15558348 | K103: I260061 | L103: 1.3959725e+08 | N103: I260061 | O103: 1.3959725e+08
B104: I240190 | C104: I240190011 | D104: Cable Hauling - (Aerial | E104: 4713513.6 | I104: 4713513.6 | K104: I260068 | L104: 28887112 | N104: I260068 | O104: 28887112
B105: I240190 | C105: I240190012 | D105: Building Attachments - | E105: 782998.68 | I105: 782998.68 | K105: I260105 | L105: 0 | N105: I260105 | O105: 0
...

Sheet TBD
F5: Gantt Chart | G5: Monitoring the timeline | K5: Jan | L5: Feb | M5: Mar | N5: Apr | O5: May | P5: Jun
G6: Reason?
G9: Area 1 | H9: 46023 | I9: 46082
F12: Add the data - to be invoiced file by Waqas bhai | I12: book 2
F14: NOT ASSIGNED - USE JUST ACTUAL | I14: exp

Sheet Live or Not Live
A1: Live/Not Live Count | XEZ1: Live/Not Live %
A3: Row Labels | B3: Count of Area / Section / Pocket / Society (Original Name) | XEZ3: Row Labels | XFA3: Count of Area / Section / Pocket / Society (Original Name)
A4: LIVE | B4: 525 | XEZ4: LIVE | XFA4: 0.45652174
A5: NOT LIVE | B5: 625 | XEZ5: NOT LIVE | XFA5: 0.54347826
A6: Grand Total | B6: 1150 | XEZ6: Grand Total | XFA6: 1

Sheet Areas
A1: Number of Total Areas | B1: =SUBTOTAL(9,B4:B1109) -> 1150
A3: Row Labels | B3: Count of Area / Section / Pocket / Society (Original Name)
A4: Between Fizaghat & Sangota | B4: 1
A5: 1-4L | B5: 1
A6: 18_P1 | B6: 1
A7: 18_P2 | B7: 1
A8: 3 Marla Scheme | B8: 1
A9: Abdul Khaliq Colony | B9: 1
A10: Abdullah City | B10: 1
A11: Abdullah Colony & Nawa Killy | B11: 1
A12: Abdullah Sports Tower Ext | B12: 1
A13: Abid Colony | B13: 1
A14: Abid Market | B14: 1
A15: AbrazulMinal_KingsBridgeView | B15: 1
... A1110: Grand Total | B1110: 1150

Sheet Feasibilities
A1: Number of CEMs | B1: =SUBTOTAL(3,A4:A1439)-1 -> 97
A3: Row Labels | B3: Count of Fesibility Name | Y3: CEM Number
A4: 100 | B4: 31 | Y4: 100
A5: 102 | B5: 28 | Y5: 102
A6: 103 | B6: 21 | Y6: 103
A7: 104 | B7: 12 | Y7: 104
A8: 105 | B8: 35 | Y8: 105
A9: 106 | B9: 22 | Y9: 106
A10: 107 | B10: 8 | Y10: 107
A11: 108 | B11: 25 | Y11: 108
A12: 109 | B12: 6 | Y12: 109
A13: 110 | B13: 30 | Y13: 110
A14: 111 | B14: 1 | Y14: 111
A15: 112 | B15: 44 | Y15: 112
A16: I240188 | B16: 3 | Y16: I240188 | AB16: Row Labels | AC16: Sum of Allocated Budget
A17: I240189 | B17: 2 | Y17: I240189 | AB17: 100 | AC17: 4.1567031e+08
A18: I240190 | B18: 4 | Y18: I240190 | AB18: 102 | AC18: 2.525768e+08
A19: I240435 | B19: 4 | Y19: I240435 | AB19: 103 | AC19: 1.9091471e+08
A20: I240437 | B20: 10 | Y20: I240437 | AB20: 104 | AC20: 1.891894e+08
A21: I240438 | B21: 12 | Y21: I240438 | AB21: 105 | AC21: 2.7718237e+08
A22: I240440 | B22: 11 | Y22: I240440 | AB22: 106 | AC22: 5.2892293e+08
A23: I240442 | B23: 2 | Y23: I240442 | AB23: 107 | AC23: 1.5178954e+08
A24: I240459 | B24: 2 | Y24: I240459 | AB24: 108 | AC24: 3.0304575e+08
A25: I240518 | B25: 5 | Y25: I240518 | AB25: 109 | AC25: 3.2499897e+08
A26: I240519 | B26: 5 | Y26: I240519 | AB26: 110 | AC26: 2.7474469e+08
A27: I240537 | B27: 5 | Y27: I240537 | AB27: 111 | AC27: 16500000
A28: I240538 | B28: 12 | Y28: I240538 | AB28: 112 | AC28: 3.5043392e+08
A29: I240539 | B29: 12 | Y29: I240539 | AB29: I240188 | AC29: 92903746 | AD29: Actual Incurred | AE29: Required Budget to Complete the Remaining Work | AF29: Net Savings
A30: I240540 | B30: 21 | Y30: I240540 | AB30: I240189 | AC30: 1.2276979e+08 | AD30: 6167069.3 | AE30: #N/A | AF30: #N/A
A31: I240557 | B31: 2 | Y31: I240557 | AB31: I240190 | AC31: 1.1605038e+08 | AD31: 26612785 | AE31: #N/A | AF31: #N/A
A32: I240678 | B32: 30 | Y32: I240678 | AB32: I240435 | AC32: 2.1685524e+08 | AD32: 4752709.9 | AE32: #N/A | AF32: #N/A
A33: I240679 | B33: 5 | Y33: I240679 | AB33: I240437 | AC33: 2.3544293e+08 | AD33: 5720633.1 | AE33: 5280950.3 | AF33: 41485728
A34: I240680 | B34: 10 | Y34: I240680 | AB34: I240438 | AC34: 1.6619984e+08 | AD34: 23696325 | AE34: 20187657 | AF34: 55733688
A35: I240681 | B35: 2 | Y35: I240681 | AB35: I240440 | AC35: 3.2974893e+08 | AD35: 58998586 | AE35: 4.1191849e+08 | AF35: 1.4631067e+08
A36: I240682 | B36: 33 | Y36: I240682 | AB36: I240442 | AC36: 1.0745748e+08 | AD36: 34791383 | AE36: 1.2677782e+08 | AF36: 5.2350041e+08
A37: I240683 | B37: 4 | Y37: I240683 | AB37: I240459 | AC37: 11499005 | AD37: 46257089 | AE37: 3.4177442e+08 | AF37: 7477903.3
A38: I240684 | B38: 6 | Y38: I240684 | AB38: I240518 | AC38: 95923257 | AD38: 1.9871365e+08 | AE38: 44427722 | AF38: -35199721
A39: I240700 | B39: 28 | Y39: I240700 | AB39: I240519 | AC39: 2.7938383e+08
A40: I240701 | B40: 4 | Y40: I240701 | AB40: I240537 | AC40: 19408588
A41: I240702 | B41: 24 | Y41: I240702 | AB41: I240538 | AC41: 1.4272731e+08
A42: I240703 | B42: 37 | Y42: I240703 | AB42: I240539 | AC42: 2.3375623e+08
A43: I240704 | B43: 34 | Y43: I240704 | AB43: I240540 | AC43: 1.611433e+08
A44: I240705 | B44: 34 | Y44: I240705 | AB44: I240557 | AC44: 18684459
A45: I240782 | B45: 1 | Y45: I240782 | AB45: I240678 | AC45: 3.5573555e+08
A46: I250114 | B46: 1 | Y46: I250114 | AB46: I240679 | AC46: 10311892
A47: I250201 | B47: 2 | Y47: I250201 | AB47: I240680 | AC47: 1.1107145e+08
A48: I250202 | B48: 3 | Y48: I250202 | AB48: I240681 | AC48: 12569175
A49: I250203 | B49: 1 | Y49: I250203 | AB49: I240682 | AC49: 5.3741251e+08
A50: I250205 | B50: 7 | Y50: I250205 | AB50: I240683 | AC50: 57392829
... A100: INT-23-00764 | B100: 20 | Y100: INT-23-00764 | AB100: INT-21-00315 | AC100: 7.1521394e+08
A101: Grand Total | B101: 1150 | AB101: INT-23-00435 | AC101: 86670916
AB102: INT-23-00436 | AC102: 38125384
AB103: INT-23-00437 | AC103: 1.6609404e+08
AB104: INT-23-00438 | AC104: 12265712
AB105: INT-23-00439 | AC105: 4.2167679e+08
AB106: INT-23-00440 | AC106: 34497805
AB107: INT-23-00441 | AC107: 1.1020384e+08
AB108: INT-23-00442 | AC108: 19658578
AB109: INT-23-00444 | AC109: 1.4145505e+08
AB110: INT-23-00445 | AC110: 19830974
AB111: INT-23-00446 | AC111: 1.4393093e+08
AB112: INT-23-00447 | AC112: 1.6726388e+08
AB113: INT-23-00764 | AC113: 2.8485241e+08
AB114: Grand Total | AC114: 1.8581034e+10

Sheet ODN Remarks Grouped
A3: Row Labels | B3: Count of Fesibility Name
A4: Feeders/Trans | B4: 223
A5: Permenant Budget Removal | B5: 43
A6: Swap Cases | B6: 33
A7: Live - As per Plan | B7: 513
A8: Not Live - Permission Issues | B8: 27
A9: Not Live - Others Reasons | B9: 18
A10: Temporary Budget Removal | B10: 19
A11: Live - Permission Awaited | B11: 13
A12: Not Live - Work in Progress (WIP) | B12: 100
A13: Not Live - Work to be initiated | B13: 384
A14: Grand Total | B14: 1373

Sheet Actuals (W)
B2: CEM | C2: =COUNTA(B3:B99) -> 12 | N2: Upper Limit | O2: Lower Limit
A3: CEM Number not generated | B3: 100 | C3: INT-21-00315 | D3: I240188 | I3: I240188 | J3: 9 | K3: 9 | L3: 9 | N3: I240188001 | O3: I240188999 | P3: =1 -> 1
A4: CEM Number not generated | B4: 102 | C4: INT-23-00435 | D4: I240189 | I4: I240189 | J4: 9 | K4: 9 | L4: 9 | N4: I240189001 | O4: I240189999 | P4: =P3+1 -> 2
A5: CEM Number not generated | B5: 103 | C5: INT-23-00436 | D5: I240190 | I5: I240190 | J5: 9 | K5: 9 | L5: 9 | N5: I240190001 | O5: I240190999 | P5: =P4+1 -> 3
A6: CEM Number not generated | B6: 104 | C6: INT-23-00437 | D6: I240435 | I6: I240435 | J6: 9 | K6: 9 | L6: 9 | N6: I240435001 | O6: I240435999 | P6: =P5+1 -> 4
A7: CEM Number not generated | B7: 105 | C7: INT-23-00438 | D7: I240437 | I7: I240437 | J7: 9 | K7: 9 | L7: 9 | N7: I240437001 | O7: I240437999 | P7: =P6+1 -> 5
A8: CEM Number not generated | B8: 106 | C8: INT-23-00439 | D8: I240438 | I8: I240438 | J8: 9 | K8: 9 | L8: 9 | N8: I240438001 | O8: I240438999 | P8: =P7+1 -> 6
A9: CEM Number not generated | B9: 107 | C9: INT-23-00440 | D9: I240440 | I9: I240440 | J9: 9 | K9: 9 | L9: 9 | N9: I240440001 | O9: I240440999 | P9: =P8+1 -> 7
A10: CEM Number not generated | B10: 108 | C10: INT-23-00441 | D10: I240442 | I10: I240442 | J10: 9 | K10: 9 | L10: 9 | N10: I240442001 | O10: I240442999 | P10: =P9+1 -> 8
A11: CEM Number not generated | B11: 109 | C11: INT-23-00442 | D11: I240459 | I11: I240459 | J11: 9 | K11: 9 | L11: 9 | N11: I240459001 | O11: I240459999 | P11: =P10+1 -> 9
A12: CEM Number not generated | B12: 110 | C12: INT-23-00444 | D12: I240518 | I12: I240518 | J12: 9 | K12: 9 | L12: 9 | N12: I240518001 | O12: I240518999 | P12: =P11+1 -> 10
A13: CEM Number not generated | B13: 111 | C13: INT-23-00445 | D13: I240519 | I13: I240519 | J13: 9 | K13: 9 | L13: 9 | N13: I240519001 | O13: I240519999 | P13: =P12+1 -> 11
A14: CEM Number not generated | B14: 112 | C14: INT-23-00446 | D14: I240537 | I14: I240537 | J14: 9 | K14: 9 | L14: 9 | N14: I240537001 | O14: I240537999 | P14: =P13+1 -> 12
C15: INT-23-00447 | D15: I240538 | I15: I240538 | J15: 9 | K15: 9 | L15: 9 | N15: I240538001 | O15: I240538999 | P15: =P14+1 -> 13
C16: INT-23-00764 | D16: I240539 | I16: I240539 | J16: 9 | K16: 9 | L16: 9 | N16: I240539001 | O16: I240539999 | P16: =P15+1 -> 14
D17: I240540 | I17: I240540 | J17: 9 | K17: 9 | L17: 9 | N17: I240540001 | O17: I240540999 | P17: =P16+1 -> 15
D18: I240557 | I18: I240557 | J18: 9 | K18: 9 | L18: 9 | N18: I240557001 | O18: I240557999 | P18: =P17+1 -> 16
D19: I240678 | I19: I240678 | J19: 9 | K19: 9 | L19: 9 | N19: I240678001 | O19: I240678999 | P19: =P18+1 -> 17
D20: I240679 | I20: I240679 | J20: 9 | K20: 9 | L20: 9 | N20: I240679001 | O20: I240679999 | P20: =P19+1 -> 18
D21: I240680 | I21: I240680 | J21: 9 | K21: 9 | L21: 9 | N21: I240680001 | O21: I240680999 | P21: =P20+1 -> 19
D22: I240681 | I22: I240681 | J22: 9 | K22: 9 | L22: 9 | N22: I240681001 | O22: I240681999 | P22: =P21+1 -> 20
D23: I240682 | I23: I240682 | J23: 9 | K23: 9 | L23: 9 | N23: I240682001 | O23: I240682999 | P23: =P22+1 -> 21
D24: I240683 | I24: I240683 | J24: 9 | K24: 9 | L24: 9 | N24: I240683001 | O24: I240683999 | P24: =P23+1 -> 22
D25: I240684 | I25: I240684 | J25: 9 | K25: 9 | L25: 9 | N25: I240684001 | O25: I240684999 | P25: =P24+1 -> 23
D26: I240700 | I26: I240700 | J26: 9 | K26: 9 | L26: 9 | N26: I240700001 | O26: I240700999 | P26: =P25+1 -> 24
D27: I240701 | I27: I240701 | J27: 9 | K27: 9 | L27: 9 | N27: I240701001 | O27: I240701999 | P27: =P26+1 -> 25
D28: I240702 | I28: I240702 | J28: 9 | K28: 9 | L28: 9 | N28: I240702001 | O28: I240702999 | P28: =P27+1 -> 26
... D73: I260361 | I73: I260361 | J73: 9 | K73: 9 | L73: 9 | N73: I260361001 | O73: I260361999 | P73: =P72+1 -> 71

Sheet Allocated Budget Check
A3: Row Labels | B3: Sum of Allocated Budget | G3: Row Labels | H3: Sum of Allocated Budget | I3: Data Bank | J3: Var | M3: Row Labels | N3: Sum of Allocated Budget (Fig in Rs.)
A4: 100 | B4: 5.1899817e+08 | D4: 100 | E4: 5.1899817e+08 | G4: I240188 | H4: 1.0815963e+08 | I4: =VLOOKUP(G4,$M$3:$N$89,2,0) -> 1.0815963e+08 | J4: =H4-I4 -> 0 | M4: I250734 | N4: 2.1498846e+08
A5: 102 | B5: 3.2095049e+08 | D5: 102 | E5: 3.2095049e+08 | G5: I240189 | H5: 1.2862079e+08 | I5: =VLOOKUP(G5,$M$3:$N$89,2,0) -> 1.2862079e+08 | J5: =H5-I5 -> 0 | M5: I260060 | N5: 25004870
A6: 103 | B6: 2.6488024e+08 | D6: 103 | E6: 2.6488024e+08 | G6: I240190 | H6: 1.3382738e+08 | I6: =VLOOKUP(G6,$M$3:$N$89,2,0) -> 1.3382738e+08 | J6: =H6-I6 -> 0 | M6: I260061 | N6: 1.0715925e+08
A7: 104 | B7: 2.0146775e+08 | D7: 104 | E7: 2.0146775e+08 | G7: I240435 | H7: 2.4849986e+08 | I7: =VLOOKUP(G7,$M$3:$N$89,2,0) -> 2.4849986e+08 | J7: =H7-I7 -> 0 | M7: I260105 | N7: 1.1964119e+08
A8: 105 | B8: 4.6921328e+08 | D8: 105 | E8: 4.6921328e+08 | G8: I240437 | H8: 2.8598643e+08 | I8: =VLOOKUP(G8,$M$3:$N$89,2,0) -> 2.8598643e+08 | J8: =H8-I8 -> 0 | M8: I260159 | N8: 67815324
